Workbook

Sheet Léeme
A1: Oráculo del conjunto de referencia (5.2) del Proyecto 077
A2: Plataforma de gestión de activos financieros. Estadía de Ramon Ernesto Nieblas Mendivil en PluriOne S.A. de C.V. Construido el jueves 15 de octubre de 2026, antes de programar el motor; lo congela un commit en el repositorio.
A4: Qué es
A5: Es el oráculo de la sección 5.2 del SRS: un escenario con un usuario de prueba (oraculo@example.com), dos portafolios (Principal y Secundario), dos intermediarios (Casa A y Casa B), tres instrumentos de demostración (DEMOACC, DEMOETF y DEMOFIB) y cuatro emisiones de CETES (BI261008, BI261105, BI261217 y BI270318), con las cifras que el motor único debe reproducir: costo y resultado no realizado por intermediario, valor de mercado, valuación de CETES (RF-26b), liquidación al vencimiento (RF-26a), serie diaria, TWR y máxima caída.
A6: Cada cifra de este libro es una fórmula visible que parte de las entradas, escritas en azul. Ninguna cifra se calculó fuera de la hoja y se pegó como valor. El libro lo arma genera_libro.py y lo recalcula Excel.
A7: Las mismas cifras se obtuvieron por un segundo camino independiente: calcula_oraculo.py, en Python con decimal de 28 dígitos y algoritmos distintos (costo total por par en un ciclo diario, en vez de kardex y SUMIFS). compara_vias.py las compara una por una; el resultado está en comparacion_vias.csv y en el README.
A8: pytest compara el motor contra esperados/*.csv, que tienen las cifras de Python sin redondear, con las tolerancias de RNF-01: 0.01 en importes y 0.001 puntos porcentuales en TWR y máxima caída; y comprueba los rechazos de rechazos_rf28.csv (hoja Rechazos).
A10: Cómo leerlo
A11: Colores: azul = entrada escrita a mano (de entradas/*.csv); se puede cambiar su valor dentro de la estructura existente (precios, tasas, cantidades, importes, fechas de transacciones). Gris = rótulo de estructura (la fecha, el portafolio, el instrumento y el intermediario de cada fila de Valuación diaria, CETES, Serie, Precios y Posiciones): define qué filas existen y no se edita en la hoja; para agregar pares, fechas, cortes o periodos, o cambiar el inicio o el fin de un periodo, se cambian entradas/*.csv y se regenera el libro con genera_libro.py. Negro = fórmula. Fuente Arial en todo el libro.
A12: Unidades: importes en pesos (MXN), sin redondear (se muestran con 4 decimales). Tasas en por ciento anual. r(t), índices, TWR y caídas como fracción (0.01 = 1 %), con su equivalente en por ciento. P de CETES con 7 decimales.
A13: • Entradas: Parámetros (intervalo, serie, usuario), cortes, periodos, portafolios, intermediarios, instrumentos, fuentes, versiones de licencia, cargas y el calendario completo de días sin operaciones de 2026 (114 fechas).
A14: • Transacciones: T01 a T16 (entradas) y, por fórmula: monto, costo o ingreso por título, aportación A, retiro R y el kardex del costo promedio por par portafolio-instrumento-intermediario.
... A71: Desde la carpeta del oráculo (la del README), con PYTHONIOENCODING=utf-8: python -I -B calcula_oraculo.py → python -B genera_libro.py → powershell.exe -NoProfile -ExecutionPolicy Bypass -File scripts/recalc_excel.ps1 oraculo_5_2.xlsx → python -B compara_vias.py. Los dos que usan openpyxl van sin -I (openpyxl está en el site-packages del usuario, que -I excluye); la carpeta no tiene archivos .py que tapen la biblioteca estándar. La hoja Comprobaciones debe terminar en VERDADERO.

Sheet Entradas
A1: Entradas del oráculo (5.2)
A2: Azul: entrada escrita a mano (de entradas/*.csv). Negro: fórmula. Gris: rótulo de estructura. Las llaves sustitutas (id) las asigna la base; aquí cada fila se liga por llave natural. Una celda vacía en una columna que admite nulos (direccion, obligacion_suprimir) es NULL.
A4: Parámetros (S-09, P-14)
A5: parámetro | B5: valor | C5: descripción
A6: intervalo_semillas_inicio | B6: 46275 | C6: Primer dia del intervalo de las semillas de precios (S-09, P-14); dia de las primeras compras
A7: intervalo_semillas_fin | B7: 46309 | C7: Ultimo dia del intervalo de las semillas de precios (S-09, P-14)
A8: serie_inicio | B8: 46275 | C8: Cierre base de la serie diaria: V(10/09), I = 1
A9: serie_fin | B9: 46309 | C9: Ultimo dia de la serie diaria
A10: usuario_correo | B10: oraculo@example.com | C10: Usuario de prueba con datos ficticios (S-04)
A12: Fechas de corte
A13: fecha_corte | B13: motivo
A14: 46278 | B14: Domingo: se valua con los cierres del 11/09 (criterio 4 de RF-08); P2 aun sin posicion
A15: 46281 | B15: Festivo (DOF 10/12/2025): se valua con los cierres del 15/09; DEMOACC en dos intermediarios (OE-5)
A16: 46303 | B16: Vencimiento de BI261008 y reinversion T16; DEMOFIB sin cierre ese dia (usa el del 07/10)
A17: 46309 | B17: Corte final del periodo
A19: Periodos de TWR y máxima caída | C19: Cambiar el inicio o el fin de un periodo exige editar entradas/periodos.csv y volver a correr genera_libro.py: los bloques diarios de Periodos tienen un largo fijo (Comprobaciones lo verifica).
A20: periodo | B20: portafolio_nombre | C20: inicio | D20: fin | E20: propósito
A21: P1-A | B21: Principal | C21: 46276 | D21: 46309 | E21: Periodo completo (base V(10/09))
A22: P1-B | B22: Principal | C22: 46276 | D22: 46295 | E22: Primer tramo; encadenamiento con P1-C
A23: P1-C | B23: Principal | C23: 46296 | D23: 46309 | E23: Segundo tramo (base V(30/09)); r(01/10) < 0, el maximo es I = 1
A24: P1-D | B24: Principal | C24: 46304 | D24: 46307 | E24: Serie que no baja: maxima caida 0 (criterio 2 de RF-10)
A25: P2-A | B25: Secundario | C25: 46276 | D25: 46309 | E25: Factor 1 con denominador 0 del 11/09 al 13/09; comprobacion por dos caminos
A26: P2-C | B26: Secundario | C26: 46296 | D26: 46309 | E26: Sin flujos (criterio 1 de RF-09)
A28: Portafolios (usuario de prueba, S-04)
A29: usuario_correo | B29: nombre | C29: divisa_base
A30: oraculo@example.com | B30: Principal | C30: MXN
A31: oraculo@example.com | B31: Secundario | C31: MXN
A33: Intermediarios (RF-25)
A34: usuario_correo | B34: nombre
A35: oraculo@example.com | B35: Casa A
A36: oraculo@example.com | B36: Casa B
A38: Instrumentos (instrumento y emision_cetes; RF-04)
A39: clave | B39: nombre | C39: clase_activo | D39: divisa | E39: de_demostracion | F39: vencimiento | G39: valor_nominal | H39: ¿clave válida? (RF-04, RD-04) | I39: ¿marca congruente?
A40: DEMOACC | B40: Acción de demostración | C40: accion | D40: MXN | E40: TRUE | H40: =IF(C40="cetes",A40="BI"&RIGHT(YEAR(F40),2)&RIGHT("0"&MONTH(F40),2)&RIGHT("0"&DAY(F40),2),NOT(AND(LEFT(A40,2)="BI",LEN(A40)=8,ISNUMBER(--MID(A40,3,6))))) -> TRUE | I40: =E40=(C40<>"cetes") -> TRUE
A41: DEMOETF | B41: ETF de demostración | C41: etf | D41: MXN | E41: TRUE | H41: =IF(C41="cetes",A41="BI"&RIGHT(YEAR(F41),2)&RIGHT("0"&MONTH(F41),2)&RIGHT("0"&DAY(F41),2),NOT(AND(LEFT(A41,2)="BI",LEN(A41)=8,ISNUMBER(--MID(A41,3,6))))) -> TRUE | I41: =E41=(C41<>"cetes") -> TRUE
A42: DEMOFIB | B42: FIBRA de demostración | C42: fibra | D42: MXN | E42: TRUE | H42: =IF(C42="cetes",A42="BI"&RIGHT(YEAR(F42),2)&RIGHT("0"&MONTH(F42),2)&RIGHT("0"&DAY(F42),2),NOT(AND(LEFT(A42,2)="BI",LEN(A42)=8,ISNUMBER(--MID(A42,3,6))))) -> TRUE | I42: =E42=(C42<>"cetes") -> TRUE
A43: BI261008 | B43: CETES con vencimiento el 08/10/2026 | C43: cetes | D43: MXN | E43: FALSE | F43: 46303 | G43: 10 | H43: =IF(C43="cetes",A43="BI"&RIGHT(YEAR(F43),2)&RIGHT("0"&MONTH(F43),2)&RIGHT("0"&DAY(F43),2),NOT(AND(LEFT(A43,2)="BI",LEN(A43)=8,ISNUMBER(--MID(A43,3,6))))) -> TRUE | I43: =E43=(C43<>"cetes") -> TRUE
A44: BI261105 | B44: CETES con vencimiento el 05/11/2026 | C44: cetes | D44: MXN | E44: FALSE | F44: 46331 | G44: 10 | H44: =IF(C44="cetes",A44="BI"&RIGHT(YEAR(F44),2)&RIGHT("0"&MONTH(F44),2)&RIGHT("0"&DAY(F44),2),NOT(AND(LEFT(A44,2)="BI",LEN(A44)=8,ISNUMBER(--MID(A44,3,6))))) -> TRUE | I44: =E44=(C44<>"cetes") -> TRUE
A45: BI261217 | B45: CETES con vencimiento el 17/12/2026 | C45: cetes | D45: MXN | E45: FALSE | F45: 46373 | G45: 10 | H45: =IF(C45="cetes",A45="BI"&RIGHT(YEAR(F45),2)&RIGHT("0"&MONTH(F45),2)&RIGHT("0"&DAY(F45),2),NOT(AND(LEFT(A45,2)="BI",LEN(A45)=8,ISNUMBER(--MID(A45,3,6))))) -> TRUE | I45: =E45=(C45<>"cetes") -> TRUE
A46: BI270318 | B46: CETES con vencimiento el 18/03/2027 | C46: cetes | D46: MXN | E46: FALSE | F46: 46464 | G46: 10 | H46: =IF(C46="cetes",A46="BI"&RIGHT(YEAR(F46),2)&RIGHT("0"&MONTH(F46),2)&RIGHT("0"&DAY(F46),2),NOT(AND(LEFT(A46,2)="BI",LEN(A46)=8,ISNUMBER(--MID(A46,3,6))))) -> TRUE | I46: =E46=(C46<>"cetes") -> TRUE
A48: Fuentes de datos (fuente_datos; RF-31)
A49: nombre | B49: direccion | C49: de_demostracion
A50: Banco de México | B50: https://www.banxico.org.mx | C50: FALSE
A51: Semilla sintetica de demostracion 077 | C51: TRUE
A53: Versiones de licencia (version_licencia; RF-31 crit. 1; R-05; D-03)
A54: fuente_nombre | B54: version | C54: usos_permitidos | D54: obligacion_suprimir | E54: atribucion
A55: Banco de México | B55: 1 | C55: Reproducir y utilizar la información que publica el Banco de México, con la sola condición de mencionar la fuente y su dirección de Internet (R-05; D-03) | E55: Fuente: Banco de México, https://www.banxico.org.mx
A56: Semilla sintetica de demostracion 077 | B56: 1 | C56: Datos sintéticos creados para el Proyecto 077: uso libre dentro de la aplicación y sus pruebas, solo como datos de demostración | E56: Datos de demostración: precios sintéticos, no son precios reales
A58: Cargas de datos (carga_datos; RF-07, RF-30, RF-31 crit. 1)
A59: carga | B59: fuente_nombre | C59: version | D59: origen | E59: fecha_inicial | F59: fecha_final | G59: resultado | H59: observaciones_incorporadas | I59: observaciones_omitidas | J59: valores_sustituidos | K59: filas de la semilla con esta carga | L59: primera fecha de sus datos | M59: última fecha de sus datos | N59: ¿cuadra con la semilla?
A60: C-PRECIOS | B60: Semilla sintetica de demostracion 077 | C60: 1 | D60: semilla | E60: 46275 | F60: 46309 | G60: completa | H60: 71 | I60: 0 | J60: {} | K60: =COUNTIF(Precios!$E$5:$E$75,A60)+COUNTIF(Tasas!$G$5:$G$36,A60) -> 71 | L60: =IF(COUNTIF(Precios!$E$5:$E$75,A60)>0,_xlfn.MINIFS(Precios!$B$5:$B$75,Precios!$E$5:$E$75,A60),_xlfn.MINIFS(Tasas!$B$5:$B$36,Tasas!$G$5:$G$36,A60)) -> 46275 | M60: =IF(COUNTIF(Precios!$E$5:$E$75,A60)>0,_xlfn.MAXIFS(Precios!$B$5:$B$75,Precios!$E$5:$E$75,A60),_xlfn.MAXIFS(Tasas!$B$5:$B$36,Tasas!$G$5:$G$36,A60)) -> 46309 | N60: =AND(H60=K60,E60=L60,F60=M60,D60="semilla",I60>=0,COUNTIFS(Entradas!$A$55:$A$56,B60,Entradas!$B$55:$B$56,C60)=1) -> TRUE
A61: C-TASAS | B61: Banco de México | C61: 1 | D61: semilla | E61: 46261 | F61: 46310 | G61: completa | H61: 32 | I61: 0 | J61: {} | K61: =COUNTIF(Precios!$E$5:$E$75,A61)+COUNTIF(Tasas!$G$5:$G$36,A61) -> 32 | L61: =IF(COUNTIF(Precios!$E$5:$E$75,A61)>0,_xlfn.MINIFS(Precios!$B$5:$B$75,Precios!$E$5:$E$75,A61),_xlfn.MINIFS(Tasas!$B$5:$B$36,Tasas!$G$5:$G$36,A61)) -> 46261 | M61: =IF(COUNTIF(Precios!$E$5:$E$75,A61)>0,_xlfn.MAXIFS(Precios!$B$5:$B$75,Precios!$E$5:$E$75,A61),_xlfn.MAXIFS(Tasas!$B$5:$B$36,Tasas!$G$5:$G$36,A61)) -> 46310 | N61: =AND(H61=K61,E61=L61,F61=M61,D61="semilla",I61>=0,COUNTIFS(Entradas!$A$55:$A$56,B61,Entradas!$B$55:$B$56,C61)=1) -> TRUE
A63: Días sin operaciones de 2026 (DOF 10/12/2025, CNBV, art. 1; Grupo BMV) | E63: Calendario completo: los 104 sábados y domingos de 2026 y los festivos de las fracciones I a VIII (el 12/12 cae en sábado), 114 fechas.
A64: fecha | B64: día | C64: tipo | D64: motivo
A65: 46023 | B65: jueves | C65: festivo | D65: Año Nuevo (art. 1, fr. I)
A66: 46025 | B66: sábado | C66: fin de semana | D66: Sábados y domingos (art. 1, fr. IX)
A67: 46026 | B67: domingo | C67: fin de semana | D67: Sábados y domingos (art. 1, fr. IX)
A68: 46032 | B68: sábado | C68: fin de semana | D68: Sábados y domingos (art. 1, fr. IX)
A69: 46033 | B69: domingo | C69: fin de semana | D69: Sábados y domingos (art. 1, fr. IX)
A70: 46039 | B70: sábado | C70: fin de semana | D70: Sábados y domingos (art. 1, fr. IX)
A71: 46040 | B71: domingo | C71: fin de semana | D71: Sábados y domingos (art. 1, fr. IX)
A72: 46046 | B72: sábado | C72: fin de semana | D72: Sábados y domingos (art. 1, fr. IX)
A73: 46047 | B73: domingo | C73: fin de semana | D73: Sábados y domingos (art. 1, fr. IX)
A74: 46053 | B74: sábado | C74: fin de semana | D74: Sábados y domingos (art. 1, fr. IX)
A75: 46054 | B75: domingo | C75: fin de semana | D75: Sábados y domingos (art. 1, fr. IX)
A76: 46055 | B76: lunes | C76: festivo | D76: Primer lunes de febrero, conmemoración del 5 de febrero (fr. II)
... A178: 46383 | B178: domingo | C178: fin de semana | D178: Sábados y domingos (art. 1, fr. IX)

Sheet Transacciones
A1: Transacciones (RF-05) y costo promedio por intermediario (RF-08)
A2: A–J: entradas (transaccion de 4.4). K–AF: fórmulas. El kardex (T–Z) procesa cada par portafolio|instrumento|intermediario en orden: fecha, compras antes que ventas (U = orden). Una venta no cambia el costo unitario; con saldo 0 se reinicia. AE–AF: la cuadrícula de Valuación diaria cubre el par y la fecha de la transacción (si se cambia un par a uno sin filas, AF da FALSO).
A4: ref | B4: portafolio_nombre | C4: intermediario_nombre | D4: instrumento_clave | E4: tipo | F4: fecha_concertacion | G4: cantidad | H4: precio | I4: importe_comisiones | J4: propósito | K4: clase_activo | L4: vencimiento | M4: signo | N4: cantidad con signo | O4: monto = títulos × precio | P4: costo por título (compra) | Q4: ingreso por título (venta) | R4: aportación A | S4: retiro R | T4: llave del par | U4: orden (fecha, compras antes que ventas) | V4: saldo previo del par | W4: saldo después | X4: orden de la transacción previa del par | Y4: costo unitario previo | Z4: costo unitario después | AA4: P de RF-26b ese día (CETES) | AB4: ¿precio = P? | AC4: días al vencimiento | AD4: ¿importe < monto? (venta) | AE4: títulos del par en Valuación diaria ese día | AF4: ¿cuadra con el historial?
A5: T01 | B5: Principal | C5: Casa A | D5: DEMOACC | E5: compra | F5: 46275 | G5: 200 | H5: 99.95 | I5: 57.97 | J5: OE-5 (DEMOACC con Casa A); su costo difiere del de Casa B | K5: =INDEX(Entradas!$C$40:$C$46,MATCH(D5,Entradas!$A$40:$A$46,0)) -> accion | L5: =IF(K5="cetes",INDEX(Entradas!$F$40:$F$46,MATCH(D5,Entradas!$A$40:$A$46,0)),"") | M5: =IF(E5="compra",1,-1) -> 1 | N5: =G5*M5 -> 200 | O5: =G5*H5 -> 19990 | P5: =IF(E5="compra",(O5+I5)/G5,"") -> 100.23985 | Q5: =IF(E5="venta",(O5-I5)/G5,"") | R5: =IF(E5="compra",O5+I5,0) -> 20047.97 | S5: =IF(E5="venta",O5-I5,0) -> 0 | T5: =B5&"|"&D5&"|"&C5 -> Principal|DEMOACC|Casa A | U5: =F5*1000+IF(E5="venta",500,0)+ROWS($A$5:A5) -> 46275001 | V5: =SUMIFS($N$5:$N$20,$T$5:$T$20,T5,$U$5:$U$20,"<"&U5) -> 0 | W5: =V5+N5 -> 200 | X5: =_xlfn.MAXIFS($U$5:$U$20,$T$5:$T$20,T5,$U$5:$U$20,"<"&U5) -> 0 | Y5: =IF(X5=0,0,INDEX($Z$4:Z4,MATCH(X5,$U$4:U4,0))) -> 0 | Z5: =IF(E5="compra",(V5*Y5+G5*P5)/W5,IF(W5=0,0,Y5)) -> 100.23985 | AA5: =IF(K5="cetes",SUMIFS(CETES!$AF$5:$AF$95,CETES!$A$5:$A$95,F5,CETES!$B$5:$B$95,D5),"") | AB5: =IF(K5="cetes",H5=AA5,"") | AC5: =IF(K5="cetes",L5-F5,"") | AD5: =IF(E5="venta",I5<O5,"") | AE5: =SUMIFS('Valuación diaria'!$I$5:$I$354,'Valuación diaria'!$E$5:$E$354,T5,'Valuación diaria'!$A$5:$A$354,F5) -> 200 | AF5: =AE5=SUMIFS($N$5:$N$20,$T$5:$T$20,T5,$F$5:$F$20,"<="&F5) -> TRUE
A6: T02 | B6: Principal | C6: Casa B | D6: DEMOETF | E6: compra | F6: 46275 | G6: 100 | H6: 50.05 | I6: 14.51 | J6: Saldo previo del caso de compra y venta el mismo dia (T11 y T12) | K6: =INDEX(Entradas!$C$40:$C$46,MATCH(D6,Entradas!$A$40:$A$46,0)) -> etf | L6: =IF(K6="cetes",INDEX(Entradas!$F$40:$F$46,MATCH(D6,Entradas!$A$40:$A$46,0)),"") | M6: =IF(E6="compra",1,-1) -> 1 | N6: =G6*M6 -> 100 | O6: =G6*H6 -> 5005 | P6: =IF(E6="compra",(O6+I6)/G6,"") -> 50.1951 | Q6: =IF(E6="venta",(O6-I6)/G6,"") | R6: =IF(E6="compra",O6+I6,0) -> 5019.51 | S6: =IF(E6="venta",O6-I6,0) -> 0 | T6: =B6&"|"&D6&"|"&C6 -> Principal|DEMOETF|Casa B | U6: =F6*1000+IF(E6="venta",500,0)+ROWS($A$5:A6) -> 46275002 | V6: =SUMIFS($N$5:$N$20,$T$5:$T$20,T6,$U$5:$U$20,"<"&U6) -> 0 | W6: =V6+N6 -> 100 | X6: =_xlfn.MAXIFS($U$5:$U$20,$T$5:$T$20,T6,$U$5:$U$20,"<"&U6) -> 0 | Y6: =IF(X6=0,0,INDEX($Z$4:Z5,MATCH(X6,$U$4:U5,0))) -> 0 | Z6: =IF(E6="compra",(V6*Y6+G6*P6)/W6,IF(W6=0,0,Y6)) -> 50.1951 | AA6: =IF(K6="cetes",SUMIFS(CETES!$AF$5:$AF$95,CETES!$A$5:$A$95,F6,CETES!$B$5:$B$95,D6),"") | AB6: =IF(K6="cetes",H6=AA6,"") | AC6: =IF(K6="cetes",L6-F6,"") | AD6: =IF(E6="venta",I6<O6,"") | AE6: =SUMIFS('Valuación diaria'!$I$5:$I$354,'Valuación diaria'!$E$5:$E$354,T6,'Valuación diaria'!$A$5:$A$354,F6) -> 100 | AF6: =AE6=SUMIFS($N$5:$N$20,$T$5:$T$20,T6,$F$5:$F$20,"<="&F6) -> TRUE
A7: T03 | B7: Principal | C7: Casa A | D7: BI261008 | E7: compra | F7: 46275 | G7: 1500 | H7: 9.951624 | I7: 0 | J7: CETES en dos intermediarios (Casa A); compra en mercado secundario concertada el 10/09 al P de RF-26b del dia (d = 28, nodo de la colocacion a 28 dias del 10/09) | K7: =INDEX(Entradas!$C$40:$C$46,MATCH(D7,Entradas!$A$40:$A$46,0)) -> cetes | L7: =IF(K7="cetes",INDEX(Entradas!$F$40:$F$46,MATCH(D7,Entradas!$A$40:$A$46,0)),"") -> 46303 | M7: =IF(E7="compra",1,-1) -> 1 | N7: =G7*M7 -> 1500 | O7: =G7*H7 -> 14927.436 | P7: =IF(E7="compra",(O7+I7)/G7,"") -> 9.951624 | Q7: =IF(E7="venta",(O7-I7)/G7,"") | R7: =IF(E7="compra",O7+I7,0) -> 14927.436 | S7: =IF(E7="venta",O7-I7,0) -> 0 | T7: =B7&"|"&D7&"|"&C7 -> Principal|BI261008|Casa A | U7: =F7*1000+IF(E7="venta",500,0)+ROWS($A$5:A7) -> 46275003 | V7: =SUMIFS($N$5:$N$20,$T$5:$T$20,T7,$U$5:$U$20,"<"&U7) -> 0 | W7: =V7+N7 -> 1500 | X7: =_xlfn.MAXIFS($U$5:$U$20,$T$5:$T$20,T7,$U$5:$U$20,"<"&U7) -> 0 | Y7: =IF(X7=0,0,INDEX($Z$4:Z6,MATCH(X7,$U$4:U6,0))) -> 0 | Z7: =IF(E7="compra",(V7*Y7+G7*P7)/W7,IF(W7=0,0,Y7)) -> 9.951624 | AA7: =IF(K7="cetes",SUMIFS(CETES!$AF$5:$AF$95,CETES!$A$5:$A$95,F7,CETES!$B$5:$B$95,D7),"") -> 9.951624 | AB7: =IF(K7="cetes",H7=AA7,"") -> TRUE | AC7: =IF(K7="cetes",L7-F7,"") -> 28 | AD7: =IF(E7="venta",I7<O7,"") | AE7: =SUMIFS('Valuación diaria'!$I$5:$I$354,'Valuación diaria'!$E$5:$E$354,T7,'Valuación diaria'!$A$5:$A$354,F7) -> 1500 | AF7: =AE7=SUMIFS($N$5:$N$20,$T$5:$T$20,T7,$F$5:$F$20,"<="&F7) -> TRUE
A8: T04 | B8: Principal | C8: Casa B | D8: BI261008 | E8: compra | F8: 46275 | G8: 1000 | H8: 9.951624 | I8: 0 | J8: CETES en dos intermediarios (Casa B); compra en mercado secundario concertada el 10/09 al P de RF-26b del dia (d = 28, nodo de la colocacion a 28 dias del 10/09) | K8: =INDEX(Entradas!$C$40:$C$46,MATCH(D8,Entradas!$A$40:$A$46,0)) -> cetes | L8: =IF(K8="cetes",INDEX(Entradas!$F$40:$F$46,MATCH(D8,Entradas!$A$40:$A$46,0)),"") -> 46303 | M8: =IF(E8="compra",1,-1) -> 1 | N8: =G8*M8 -> 1000 | O8: =G8*H8 -> 9951.624 | P8: =IF(E8="compra",(O8+I8)/G8,"") -> 9.951624 | Q8: =IF(E8="venta",(O8-I8)/G8,"") | R8: =IF(E8="compra",O8+I8,0) -> 9951.624 | S8: =IF(E8="venta",O8-I8,0) -> 0 | T8: =B8&"|"&D8&"|"&C8 -> Principal|BI261008|Casa B | U8: =F8*1000+IF(E8="venta",500,0)+ROWS($A$5:A8) -> 46275004 | V8: =SUMIFS($N$5:$N$20,$T$5:$T$20,T8,$U$5:$U$20,"<"&U8) -> 0 | W8: =V8+N8 -> 1000 | X8: =_xlfn.MAXIFS($U$5:$U$20,$T$5:$T$20,T8,$U$5:$U$20,"<"&U8) -> 0 | Y8: =IF(X8=0,0,INDEX($Z$4:Z7,MATCH(X8,$U$4:U7,0))) -> 0 | Z8: =IF(E8="compra",(V8*Y8+G8*P8)/W8,IF(W8=0,0,Y8)) -> 9.951624 | AA8: =IF(K8="cetes",SUMIFS(CETES!$AF$5:$AF$95,CETES!$A$5:$A$95,F8,CETES!$B$5:$B$95,D8),"") -> 9.951624 | AB8: =IF(K8="cetes",H8=AA8,"") -> TRUE | AC8: =IF(K8="cetes",L8-F8,"") -> 28 | AD8: =IF(E8="venta",I8<O8,"") | AE8: =SUMIFS('Valuación diaria'!$I$5:$I$354,'Valuación diaria'!$E$5:$E$354,T8,'Valuación diaria'!$A$5:$A$354,F8) -> 1000 | AF8: =AE8=SUMIFS($N$5:$N$20,$T$5:$T$20,T8,$F$5:$F$20,"<="&F8) -> TRUE
A9: T05 | B9: Principal | C9: Casa A | D9: DEMOFIB | E9: compra | F9: 46276 | G9: 400 | H9: 24.9825 | I9: 28.98 | J9: Primer flujo dentro del periodo | K9: =INDEX(Entradas!$C$40:$C$46,MATCH(D9,Entradas!$A$40:$A$46,0)) -> fibra | L9: =IF(K9="cetes",INDEX(Entradas!$F$40:$F$46,MATCH(D9,Entradas!$A$40:$A$46,0)),"") | M9: =IF(E9="compra",1,-1) -> 1 | N9: =G9*M9 -> 400 | O9: =G9*H9 -> 9993 | P9: =IF(E9="compra",(O9+I9)/G9,"") -> 25.05495 | Q9: =IF(E9="venta",(O9-I9)/G9,"") | R9: =IF(E9="compra",O9+I9,0) -> 10021.98 | S9: =IF(E9="venta",O9-I9,0) -> 0 | T9: =B9&"|"&D9&"|"&C9 -> Principal|DEMOFIB|Casa A | U9: =F9*1000+IF(E9="venta",500,0)+ROWS($A$5:A9) -> 46276005 | V9: =SUMIFS($N$5:$N$20,$T$5:$T$20,T9,$U$5:$U$20,"<"&U9) -> 0 | W9: =V9+N9 -> 400 | X9: =_xlfn.MAXIFS($U$5:$U$20,$T$5:$T$20,T9,$U$5:$U$20,"<"&U9) -> 0 | Y9: =IF(X9=0,0,INDEX($Z$4:Z8,MATCH(X9,$U$4:U8,0))) -> 0 | Z9: =IF(E9="compra",(V9*Y9+G9*P9)/W9,IF(W9=0,0,Y9)) -> 25.05495 | AA9: =IF(K9="cetes",SUMIFS(CETES!$AF$5:$AF$95,CETES!$A$5:$A$95,F9,CETES!$B$5:$B$95,D9),"") | AB9: =IF(K9="cetes",H9=AA9,"") | AC9: =IF(K9="cetes",L9-F9,"") | AD9: =IF(E9="venta",I9<O9,"") | AE9: =SUMIFS('Valuación diaria'!$I$5:$I$354,'Valuación diaria'!$E$5:$E$354,T9,'Valuación diaria'!$A$5:$A$354,F9) -> 400 | AF9: =AE9=SUMIFS($N$5:$N$20,$T$5:$T$20,T9,$F$5:$F$20,"<="&F9) -> TRUE
A10: T06 | B10: Principal | C10: Casa B | D10: DEMOACC | E10: compra | F10: 46279 | G10: 100 | H10: 103.1 | I10: 29.9 | J10: OE-5 (DEMOACC con Casa B) | K10: =INDEX(Entradas!$C$40:$C$46,MATCH(D10,Entradas!$A$40:$A$46,0)) -> accion | L10: =IF(K10="cetes",INDEX(Entradas!$F$40:$F$46,MATCH(D10,Entradas!$A$40:$A$46,0)),"") | M10: =IF(E10="compra",1,-1) -> 1 | N10: =G10*M10 -> 100 | O10: =G10*H10 -> 10310 | P10: =IF(E10="compra",(O10+I10)/G10,"") -> 103.399 | Q10: =IF(E10="venta",(O10-I10)/G10,"") | R10: =IF(E10="compra",O10+I10,0) -> 10339.9 | S10: =IF(E10="venta",O10-I10,0) -> 0 | T10: =B10&"|"&D10&"|"&C10 -> Principal|DEMOACC|Casa B | U10: =F10*1000+IF(E10="venta",500,0)+ROWS($A$5:A10) -> 46279006 | V10: =SUMIFS($N$5:$N$20,$T$5:$T$20,T10,$U$5:$U$20,"<"&U10) -> 0 | W10: =V10+N10 -> 100 | X10: =_xlfn.MAXIFS($U$5:$U$20,$T$5:$T$20,T10,$U$5:$U$20,"<"&U10) -> 0 | Y10: =IF(X10=0,0,INDEX($Z$4:Z9,MATCH(X10,$U$4:U9,0))) -> 0 | Z10: =IF(E10="compra",(V10*Y10+G10*P10)/W10,IF(W10=0,0,Y10)) -> 103.399 | AA10: =IF(K10="cetes",SUMIFS(CETES!$AF$5:$AF$95,CETES!$A$5:$A$95,F10,CETES!$B$5:$B$95,D10),"") | AB10: =IF(K10="cetes",H10=AA10,"") | AC10: =IF(K10="cetes",L10-F10,"") | AD10: =IF(E10="venta",I10<O10,"") | AE10: =SUMIFS('Valuación diaria'!$I$5:$I$354,'Valuación diaria'!$E$5:$E$354,T10,'Valuación diaria'!$A$5:$A$354,F10) -> 100 | AF10: =AE10=SUMIFS($N$5:$N$20,$T$5:$T$20,T10,$F$5:$F$20,"<="&F10) -> TRUE
A11: T07 | B11: Secundario | C11: Casa A | D11: DEMOACC | E11: compra | F11: 46279 | G11: 150 | H11: 103.6 | I11: 45.07 | J11: X-06: mismo instrumento e intermediario que en Principal, otro portafolio | K11: =INDEX(Entradas!$C$40:$C$46,MATCH(D11,Entradas!$A$40:$A$46,0)) -> accion | L11: =IF(K11="cetes",INDEX(Entradas!$F$40:$F$46,MATCH(D11,Entradas!$A$40:$A$46,0)),"") | M11: =IF(E11="compra",1,-1) -> 1 | N11: =G11*M11 -> 150 | O11: =G11*H11 -> 15540 | P11: =IF(E11="compra",(O11+I11)/G11,"") -> 103.90047 | Q11: =IF(E11="venta",(O11-I11)/G11,"") | R11: =IF(E11="compra",O11+I11,0) -> 15585.07 | S11: =IF(E11="venta",O11-I11,0) -> 0 | T11: =B11&"|"&D11&"|"&C11 -> Secundario|DEMOACC|Casa A | U11: =F11*1000+IF(E11="venta",500,0)+ROWS($A$5:A11) -> 46279007 | V11: =SUMIFS($N$5:$N$20,$T$5:$T$20,T11,$U$5:$U$20,"<"&U11) -> 0 | W11: =V11+N11 -> 150 | X11: =_xlfn.MAXIFS($U$5:$U$20,$T$5:$T$20,T11,$U$5:$U$20,"<"&U11) -> 0 | Y11: =IF(X11=0,0,INDEX($Z$4:Z10,MATCH(X11,$U$4:U10,0))) -> 0 | Z11: =IF(E11="compra",(V11*Y11+G11*P11)/W11,IF(W11=0,0,Y11)) -> 103.90047 | AA11: =IF(K11="cetes",SUMIFS(CETES!$AF$5:$AF$95,CETES!$A$5:$A$95,F11,CETES!$B$5:$B$95,D11),"") | AB11: =IF(K11="cetes",H11=AA11,"") | AC11: =IF(K11="cetes",L11-F11,"") | AD11: =IF(E11="venta",I11<O11,"") | AE11: =SUMIFS('Valuación diaria'!$I$5:$I$354,'Valuación diaria'!$E$5:$E$354,T11,'Valuación diaria'!$A$5:$A$354,F11) -> 150 | AF11: =AE11=SUMIFS($N$5:$N$20,$T$5:$T$20,T11,$F$5:$F$20,"<="&F11) -> TRUE
A12: T08 | B12: Principal | C12: Casa A | D12: BI261217 | E12: compra | F12: 46282 | G12: 1000 | H12: 9.8344372 | I12: 0 | J12: Interpolacion entre 28 y 91 dias; compra en mercado secundario concertada el 17/09 al P de RF-26b del dia (d = 91, nodo de la colocacion a 91 dias del 17/09) | K12: =INDEX(Entradas!$C$40:$C$46,MATCH(D12,Entradas!$A$40:$A$46,0)) -> cetes | L12: =IF(K12="cetes",INDEX(Entradas!$F$40:$F$46,MATCH(D12,Entradas!$A$40:$A$46,0)),"") -> 46373 | M12: =IF(E12="compra",1,-1) -> 1 | N12: =G12*M12 -> 1000 | O12: =G12*H12 -> 9834.4372 | P12: =IF(E12="compra",(O12+I12)/G12,"") -> 9.8344372 | Q12: =IF(E12="venta",(O12-I12)/G12,"") | R12: =IF(E12="compra",O12+I12,0) -> 9834.4372 | S12: =IF(E12="venta",O12-I12,0) -> 0 | T12: =B12&"|"&D12&"|"&C12 -> Principal|BI261217|Casa A | U12: =F12*1000+IF(E12="venta",500,0)+ROWS($A$5:A12) -> 46282008 | V12: =SUMIFS($N$5:$N$20,$T$5:$T$20,T12,$U$5:$U$20,"<"&U12) -> 0 | W12: =V12+N12 -> 1000 | X12: =_xlfn.MAXIFS($U$5:$U$20,$T$5:$T$20,T12,$U$5:$U$20,"<"&U12) -> 0 | Y12: =IF(X12=0,0,INDEX($Z$4:Z11,MATCH(X12,$U$4:U11,0))) -> 0 | Z12: =IF(E12="compra",(V12*Y12+G12*P12)/W12,IF(W12=0,0,Y12)) -> 9.8344372 | AA12: =IF(K12="cetes",SUMIFS(CETES!$AF$5:$AF$95,CETES!$A$5:$A$95,F12,CETES!$B$5:$B$95,D12),"") -> 9.8344372 | AB12: =IF(K12="cetes",H12=AA12,"") -> TRUE | AC12: =IF(K12="cetes",L12-F12,"") -> 91 | AD12: =IF(E12="venta",I12<O12,"") | AE12: =SUMIFS('Valuación diaria'!$I$5:$I$354,'Valuación diaria'!$E$5:$E$354,T12,'Valuación diaria'!$A$5:$A$354,F12) -> 1000 | AF12: =AE12=SUMIFS($N$5:$N$20,$T$5:$T$20,T12,$F$5:$F$20,"<="&F12) -> TRUE
A13: T09 | B13: Principal | C13: Casa B | D13: BI270318 | E13: compra | F13: 46282 | G13: 500 | H13: 9.662925 | I13: 0 | J13: Interpolacion entre 91 y 182 o 175 efectivos; compra en mercado secundario concertada el 17/09 al P de RF-26b del dia (d = 182, nodo de la colocacion a 182 dias del 17/09) | K13: =INDEX(Entradas!$C$40:$C$46,MATCH(D13,Entradas!$A$40:$A$46,0)) -> cetes | L13: =IF(K13="cetes",INDEX(Entradas!$F$40:$F$46,MATCH(D13,Entradas!$A$40:$A$46,0)),"") -> 46464 | M13: =IF(E13="compra",1,-1) -> 1 | N13: =G13*M13 -> 500 | O13: =G13*H13 -> 4831.4625 | P13: =IF(E13="compra",(O13+I13)/G13,"") -> 9.662925 | Q13: =IF(E13="venta",(O13-I13)/G13,"") | R13: =IF(E13="compra",O13+I13,0) -> 4831.4625 | S13: =IF(E13="venta",O13-I13,0) -> 0 | T13: =B13&"|"&D13&"|"&C13 -> Principal|BI270318|Casa B | U13: =F13*1000+IF(E13="venta",500,0)+ROWS($A$5:A13) -> 46282009 | V13: =SUMIFS($N$5:$N$20,$T$5:$T$20,T13,$U$5:$U$20,"<"&U13) -> 0 | W13: =V13+N13 -> 500 | X13: =_xlfn.MAXIFS($U$5:$U$20,$T$5:$T$20,T13,$U$5:$U$20,"<"&U13) -> 0 | Y13: =IF(X13=0,0,INDEX($Z$4:Z12,MATCH(X13,$U$4:U12,0))) -> 0 | Z13: =IF(E13="compra",(V13*Y13+G13*P13)/W13,IF(W13=0,0,Y13)) -> 9.662925 | AA13: =IF(K13="cetes",SUMIFS(CETES!$AF$5:$AF$95,CETES!$A$5:$A$95,F13,CETES!$B$5:$B$95,D13),"") -> 9.662925 | AB13: =IF(K13="cetes",H13=AA13,"") -> TRUE | AC13: =IF(K13="cetes",L13-F13,"") -> 182 | AD13: =IF(E13="venta",I13<O13,"") | AE13: =SUMIFS('Valuación diaria'!$I$5:$I$354,'Valuación diaria'!$E$5:$E$354,T13,'Valuación diaria'!$A$5:$A$354,F13) -> 500 | AF13: =AE13=SUMIFS($N$5:$N$20,$T$5:$T$20,T13,$F$5:$F$20,"<="&F13) -> TRUE
A14: T10 | B14: Principal | C14: Casa A | D14: DEMOFIB | E14: venta | F14: 46287 | G14: 400 | H14: 23.2075 | I14: 26.92 | J14: Venta total: el saldo queda en 0 y el costo se reinicia | K14: =INDEX(Entradas!$C$40:$C$46,MATCH(D14,Entradas!$A$40:$A$46,0)) -> fibra | L14: =IF(K14="cetes",INDEX(Entradas!$F$40:$F$46,MATCH(D14,Entradas!$A$40:$A$46,0)),"") | M14: =IF(E14="compra",1,-1) -> -1 | N14: =G14*M14 -> -400 | O14: =G14*H14 -> 9283 | P14: =IF(E14="compra",(O14+I14)/G14,"") | Q14: =IF(E14="venta",(O14-I14)/G14,"") -> 23.1402 | R14: =IF(E14="compra",O14+I14,0) -> 0 | S14: =IF(E14="venta",O14-I14,0) -> 9256.08 | T14: =B14&"|"&D14&"|"&C14 -> Principal|DEMOFIB|Casa A | U14: =F14*1000+IF(E14="venta",500,0)+ROWS($A$5:A14) -> 46287510 | V14: =SUMIFS($N$5:$N$20,$T$5:$T$20,T14,$U$5:$U$20,"<"&U14) -> 400 | W14: =V14+N14 -> 0 | X14: =_xlfn.MAXIFS($U$5:$U$20,$T$5:$T$20,T14,$U$5:$U$20,"<"&U14) -> 46276005 | Y14: =IF(X14=0,0,INDEX($Z$4:Z13,MATCH(X14,$U$4:U13,0))) -> 25.05495 | Z14: =IF(E14="compra",(V14*Y14+G14*P14)/W14,IF(W14=0,0,Y14)) -> 0 | AA14: =IF(K14="cetes",SUMIFS(CETES!$AF$5:$AF$95,CETES!$A$5:$A$95,F14,CETES!$B$5:$B$95,D14),"") | AB14: =IF(K14="cetes",H14=AA14,"") | AC14: =IF(K14="cetes",L14-F14,"") | AD14: =IF(E14="venta",I14<O14,"") -> TRUE | AE14: =SUMIFS('Valuación diaria'!$I$5:$I$354,'Valuación diaria'!$E$5:$E$354,T14,'Valuación diaria'!$A$5:$A$354,F14) -> 0 | AF14: =AE14=SUMIFS($N$5:$N$20,$T$5:$T$20,T14,$F$5:$F$20,"<="&F14) -> TRUE
A15: T11 | B15: Principal | C15: Casa B | D15: DEMOETF | E15: compra | F15: 46290 | G15: 60 | H15: 47.9 | I15: 8.33 | J15: Compra y venta el mismo dia (compras antes que ventas) | K15: =INDEX(Entradas!$C$40:$C$46,MATCH(D15,Entradas!$A$40:$A$46,0)) -> etf | L15: =IF(K15="cetes",INDEX(Entradas!$F$40:$F$46,MATCH(D15,Entradas!$A$40:$A$46,0)),"") | M15: =IF(E15="compra",1,-1) -> 1 | N15: =G15*M15 -> 60 | O15: =G15*H15 -> 2874 | P15: =IF(E15="compra",(O15+I15)/G15,"") -> 48.038833 | Q15: =IF(E15="venta",(O15-I15)/G15,"") | R15: =IF(E15="compra",O15+I15,0) -> 2882.33 | S15: =IF(E15="venta",O15-I15,0) -> 0 | T15: =B15&"|"&D15&"|"&C15 -> Principal|DEMOETF|Casa B | U15: =F15*1000+IF(E15="venta",500,0)+ROWS($A$5:A15) -> 46290011 | V15: =SUMIFS($N$5:$N$20,$T$5:$T$20,T15,$U$5:$U$20,"<"&U15) -> 100 | W15: =V15+N15 -> 160 | X15: =_xlfn.MAXIFS($U$5:$U$20,$T$5:$T$20,T15,$U$5:$U$20,"<"&U15) -> 46275002 | Y15: =IF(X15=0,0,INDEX($Z$4:Z14,MATCH(X15,$U$4:U14,0))) -> 50.1951 | Z15: =IF(E15="compra",(V15*Y15+G15*P15)/W15,IF(W15=0,0,Y15)) -> 49.3865 | AA15: =IF(K15="cetes",SUMIFS(CETES!$AF$5:$AF$95,CETES!$A$5:$A$95,F15,CETES!$B$5:$B$95,D15),"") | AB15: =IF(K15="cetes",H15=AA15,"") | AC15: =IF(K15="cetes",L15-F15,"") | AD15: =IF(E15="venta",I15<O15,"") | AE15: =SUMIFS('Valuación diaria'!$I$5:$I$354,'Valuación diaria'!$E$5:$E$354,T15,'Valuación diaria'!$A$5:$A$354,F15) -> 40 | AF15: =AE15=SUMIFS($N$5:$N$20,$T$5:$T$20,T15,$F$5:$F$20,"<="&F15) -> TRUE
A16: T12 | B16: Principal | C16: Casa B | D16: DEMOETF | E16: venta | F16: 46290 | G16: 120 | H16: 48.1 | I16: 16.74 | J16: Venta de 120 > saldo previo de 100; solo es valida aplicando antes T11 | K16: =INDEX(Entradas!$C$40:$C$46,MATCH(D16,Entradas!$A$40:$A$46,0)) -> etf | L16: =IF(K16="cetes",INDEX(Entradas!$F$40:$F$46,MATCH(D16,Entradas!$A$40:$A$46,0)),"") | M16: =IF(E16="compra",1,-1) -> -1 | N16: =G16*M16 -> -120 | O16: =G16*H16 -> 5772 | P16: =IF(E16="compra",(O16+I16)/G16,"") | Q16: =IF(E16="venta",(O16-I16)/G16,"") -> 47.9605 | R16: =IF(E16="compra",O16+I16,0) -> 0 | S16: =IF(E16="venta",O16-I16,0) -> 5755.26 | T16: =B16&"|"&D16&"|"&C16 -> Principal|DEMOETF|Casa B | U16: =F16*1000+IF(E16="venta",500,0)+ROWS($A$5:A16) -> 46290512 | V16: =SUMIFS($N$5:$N$20,$T$5:$T$20,T16,$U$5:$U$20,"<"&U16) -> 160 | W16: =V16+N16 -> 40 | X16: =_xlfn.MAXIFS($U$5:$U$20,$T$5:$T$20,T16,$U$5:$U$20,"<"&U16) -> 46290011 | Y16: =IF(X16=0,0,INDEX($Z$4:Z15,MATCH(X16,$U$4:U15,0))) -> 49.3865 | Z16: =IF(E16="compra",(V16*Y16+G16*P16)/W16,IF(W16=0,0,Y16)) -> 49.3865 | AA16: =IF(K16="cetes",SUMIFS(CETES!$AF$5:$AF$95,CETES!$A$5:$A$95,F16,CETES!$B$5:$B$95,D16),"") | AB16: =IF(K16="cetes",H16=AA16,"") | AC16: =IF(K16="cetes",L16-F16,"") | AD16: =IF(E16="venta",I16<O16,"") -> TRUE | AE16: =SUMIFS('Valuación diaria'!$I$5:$I$354,'Valuación diaria'!$E$5:$E$354,T16,'Valuación diaria'!$A$5:$A$354,F16) -> 40 | AF16: =AE16=SUMIFS($N$5:$N$20,$T$5:$T$20,T16,$F$5:$F$20,"<="&F16) -> TRUE
... A20: T16 | B20: Principal | C20: Casa B | D20: BI261105 | E20: compra | F20: 46303 | G20: 1000 | H20: 9.9528566 | I20: 0 | J20: Reinversion registrada como compra (S-14), en mercado secundario concertada el 08/10 al P de RF-26b del dia (d = 28, nodo de la colocacion a 28 dias del 08/10) | K20: =INDEX(Entradas!$C$40:$C$46,MATCH(D20,Entradas!$A$40:$A$46,0)) -> cetes | L20: =IF(K20="cetes",INDEX(Entradas!$F$40:$F$46,MATCH(D20,Entradas!$A$40:$A$46,0)),"") -> 46331 | M20: =IF(E20="compra",1,-1) -> 1 | N20: =G20*M20 -> 1000 | O20: =G20*H20 -> 9952.8566 | P20: =IF(E20="compra",(O20+I20)/G20,"") -> 9.9528566 | Q20: =IF(E20="venta",(O20-I20)/G20,"") | R20: =IF(E20="compra",O20+I20,0) -> 9952.8566 | S20: =IF(E20="venta",O20-I20,0) -> 0 | T20: =B20&"|"&D20&"|"&C20 -> Principal|BI261105|Casa B | U20: =F20*1000+IF(E20="venta",500,0)+ROWS($A$5:A20) -> 46303016 | V20: =SUMIFS($N$5:$N$20,$T$5:$T$20,T20,$U$5:$U$20,"<"&U20) -> 0 | W20: =V20+N20 -> 1000 | X20: =_xlfn.MAXIFS($U$5:$U$20,$T$5:$T$20,T20,$U$5:$U$20,"<"&U20) -> 0 | Y20: =IF(X20=0,0,INDEX($Z$4:Z19,MATCH(X20,$U$4:U19,0))) -> 0 | Z20: =IF(E20="compra",(V20*Y20+G20*P20)/W20,IF(W20=0,0,Y20)) -> 9.9528566 | AA20: =IF(K20="cetes",SUMIFS(CETES!$AF$5:$AF$95,CETES!$A$5:$A$95,F20,CETES!$B$5:$B$95,D20),"") -> 9.9528566 | AB20: =IF(K20="cetes",H20=AA20,"") -> TRUE | AC20: =IF(K20="cetes",L20-F20,"") -> 28 | AD20: =IF(E20="venta",I20<O20,"") | AE20: =SUMIFS('Valuación diaria'!$I$5:$I$354,'Valuación diaria'!$E$5:$E$354,T20,'Valuación diaria'!$A$5:$A$354,F20) -> 1000 | AF20: =AE20=SUMIFS($N$5:$N$20,$T$5:$T$20,T20,$F$5:$F$20,"<="&F20) -> TRUE

Sheet Precios
A1: Precios de cierre sintéticos (RF-07) y cierre usado cada día
A2: Fuente: semilla sintética de demostración del 077 (no son precios reales; R-04, R-05). Solo días con operaciones de 2026; DEMOFIB no tiene cierre el 08/10 a propósito. I–M: último cierre igual o anterior a cada día natural (criterio 4 de RF-08); I y J son rótulos de estructura (gris).
A4: instrumento_clave | B4: fecha | C4: precio | D4: fuente_nombre | E4: carga | F4: día de la semana (1 = lunes) | G4: ¿día con operaciones? | I4: fecha | J4: instrumento_clave | K4: fecha del cierre usado | L4: precio usado | M4: ¿sin cierre ese día?
A5: DEMOACC | B5: 46275 | C5: 100.2 | D5: Semilla sintetica de demostracion 077 | E5: C-PRECIOS | F5: =WEEKDAY(B5,2) -> 4 | G5: =AND(F5<=5,COUNTIF(Entradas!$A$65:$A$178,B5)=0) -> TRUE | I5: 46275 | J5: DEMOACC | K5: =_xlfn.MAXIFS($B$5:$B$75,$A$5:$A$75,J5,$B$5:$B$75,"<="&I5) -> 46275 | L5: =SUMIFS($C$5:$C$75,$A$5:$A$75,J5,$B$5:$B$75,K5) -> 100.2 | M5: =IF(K5<I5,"sí","no") -> no
A6: DEMOACC | B6: 46276 | C6: 101.85 | D6: Semilla sintetica de demostracion 077 | E6: C-PRECIOS | F6: =WEEKDAY(B6,2) -> 5 | G6: =AND(F6<=5,COUNTIF(Entradas!$A$65:$A$178,B6)=0) -> TRUE | I6: 46275 | J6: DEMOETF | K6: =_xlfn.MAXIFS($B$5:$B$75,$A$5:$A$75,J6,$B$5:$B$75,"<="&I6) -> 46275 | L6: =SUMIFS($C$5:$C$75,$A$5:$A$75,J6,$B$5:$B$75,K6) -> 50.1 | M6: =IF(K6<I6,"sí","no") -> no
A7: DEMOACC | B7: 46279 | C7: 103.4 | D7: Semilla sintetica de demostracion 077 | E7: C-PRECIOS | F7: =WEEKDAY(B7,2) -> 1 | G7: =AND(F7<=5,COUNTIF(Entradas!$A$65:$A$178,B7)=0) -> TRUE | I7: 46275 | J7: DEMOFIB | K7: =_xlfn.MAXIFS($B$5:$B$75,$A$5:$A$75,J7,$B$5:$B$75,"<="&I7) -> 46275 | L7: =SUMIFS($C$5:$C$75,$A$5:$A$75,J7,$B$5:$B$75,K7) -> 24.8 | M7: =IF(K7<I7,"sí","no") -> no
A8: DEMOACC | B8: 46280 | C8: 104.75 | D8: Semilla sintetica de demostracion 077 | E8: C-PRECIOS | F8: =WEEKDAY(B8,2) -> 2 | G8: =AND(F8<=5,COUNTIF(Entradas!$A$65:$A$178,B8)=0) -> TRUE | I8: 46276 | J8: DEMOACC | K8: =_xlfn.MAXIFS($B$5:$B$75,$A$5:$A$75,J8,$B$5:$B$75,"<="&I8) -> 46276 | L8: =SUMIFS($C$5:$C$75,$A$5:$A$75,J8,$B$5:$B$75,K8) -> 101.85 | M8: =IF(K8<I8,"sí","no") -> no
A9: DEMOACC | B9: 46282 | C9: 102.1 | D9: Semilla sintetica de demostracion 077 | E9: C-PRECIOS | F9: =WEEKDAY(B9,2) -> 4 | G9: =AND(F9<=5,COUNTIF(Entradas!$A$65:$A$178,B9)=0) -> TRUE | I9: 46276 | J9: DEMOETF | K9: =_xlfn.MAXIFS($B$5:$B$75,$A$5:$A$75,J9,$B$5:$B$75,"<="&I9) -> 46276 | L9: =SUMIFS($C$5:$C$75,$A$5:$A$75,J9,$B$5:$B$75,K9) -> 50.62 | M9: =IF(K9<I9,"sí","no") -> no
A10: DEMOACC | B10: 46283 | C10: 98.65 | D10: Semilla sintetica de demostracion 077 | E10: C-PRECIOS | F10: =WEEKDAY(B10,2) -> 5 | G10: =AND(F10<=5,COUNTIF(Entradas!$A$65:$A$178,B10)=0) -> TRUE | I10: 46276 | J10: DEMOFIB | K10: =_xlfn.MAXIFS($B$5:$B$75,$A$5:$A$75,J10,$B$5:$B$75,"<="&I10) -> 46276 | L10: =SUMIFS($C$5:$C$75,$A$5:$A$75,J10,$B$5:$B$75,K10) -> 25.015 | M10: =IF(K10<I10,"sí","no") -> no
A11: DEMOACC | B11: 46286 | C11: 95.3 | D11: Semilla sintetica de demostracion 077 | E11: C-PRECIOS | F11: =WEEKDAY(B11,2) -> 1 | G11: =AND(F11<=5,COUNTIF(Entradas!$A$65:$A$178,B11)=0) -> TRUE | I11: 46277 | J11: DEMOACC | K11: =_xlfn.MAXIFS($B$5:$B$75,$A$5:$A$75,J11,$B$5:$B$75,"<="&I11) -> 46276 | L11: =SUMIFS($C$5:$C$75,$A$5:$A$75,J11,$B$5:$B$75,K11) -> 101.85 | M11: =IF(K11<I11,"sí","no") -> sí
A12: DEMOACC | B12: 46287 | C12: 92.15 | D12: Semilla sintetica de demostracion 077 | E12: C-PRECIOS | F12: =WEEKDAY(B12,2) -> 2 | G12: =AND(F12<=5,COUNTIF(Entradas!$A$65:$A$178,B12)=0) -> TRUE | I12: 46277 | J12: DEMOETF | K12: =_xlfn.MAXIFS($B$5:$B$75,$A$5:$A$75,J12,$B$5:$B$75,"<="&I12) -> 46276 | L12: =SUMIFS($C$5:$C$75,$A$5:$A$75,J12,$B$5:$B$75,K12) -> 50.62 | M12: =IF(K12<I12,"sí","no") -> sí
A13: DEMOACC | B13: 46288 | C13: 90.425 | D13: Semilla sintetica de demostracion 077 | E13: C-PRECIOS | F13: =WEEKDAY(B13,2) -> 3 | G13: =AND(F13<=5,COUNTIF(Entradas!$A$65:$A$178,B13)=0) -> TRUE | I13: 46277 | J13: DEMOFIB | K13: =_xlfn.MAXIFS($B$5:$B$75,$A$5:$A$75,J13,$B$5:$B$75,"<="&I13) -> 46276 | L13: =SUMIFS($C$5:$C$75,$A$5:$A$75,J13,$B$5:$B$75,K13) -> 25.015 | M13: =IF(K13<I13,"sí","no") -> sí
A14: DEMOACC | B14: 46289 | C14: 92.8 | D14: Semilla sintetica de demostracion 077 | E14: C-PRECIOS | F14: =WEEKDAY(B14,2) -> 4 | G14: =AND(F14<=5,COUNTIF(Entradas!$A$65:$A$178,B14)=0) -> TRUE | I14: 46278 | J14: DEMOACC | K14: =_xlfn.MAXIFS($B$5:$B$75,$A$5:$A$75,J14,$B$5:$B$75,"<="&I14) -> 46276 | L14: =SUMIFS($C$5:$C$75,$A$5:$A$75,J14,$B$5:$B$75,K14) -> 101.85 | M14: =IF(K14<I14,"sí","no") -> sí
A15: DEMOACC | B15: 46290 | C15: 96.15 | D15: Semilla sintetica de demostracion 077 | E15: C-PRECIOS | F15: =WEEKDAY(B15,2) -> 5 | G15: =AND(F15<=5,COUNTIF(Entradas!$A$65:$A$178,B15)=0) -> TRUE | I15: 46278 | J15: DEMOETF | K15: =_xlfn.MAXIFS($B$5:$B$75,$A$5:$A$75,J15,$B$5:$B$75,"<="&I15) -> 46276 | L15: =SUMIFS($C$5:$C$75,$A$5:$A$75,J15,$B$5:$B$75,K15) -> 50.62 | M15: =IF(K15<I15,"sí","no") -> sí
A16: DEMOACC | B16: 46293 | C16: 99.7 | D16: Semilla sintetica de demostracion 077 | E16: C-PRECIOS | F16: =WEEKDAY(B16,2) -> 1 | G16: =AND(F16<=5,COUNTIF(Entradas!$A$65:$A$178,B16)=0) -> TRUE | I16: 46278 | J16: DEMOFIB | K16: =_xlfn.MAXIFS($B$5:$B$75,$A$5:$A$75,J16,$B$5:$B$75,"<="&I16) -> 46276 | L16: =SUMIFS($C$5:$C$75,$A$5:$A$75,J16,$B$5:$B$75,K16) -> 25.015 | M16: =IF(K16<I16,"sí","no") -> sí
... A75: DEMOFIB | B75: 46309 | C75: 25.6225 | D75: Semilla sintetica de demostracion 077 | E75: C-PRECIOS | F75: =WEEKDAY(B75,2) -> 3 | G75: =AND(F75<=5,COUNTIF(Entradas!$A$65:$A$178,B75)=0) -> TRUE | I75: 46298 | J75: DEMOETF | K75: =_xlfn.MAXIFS($B$5:$B$75,$A$5:$A$75,J75,$B$5:$B$75,"<="&I75) -> 46297 | L75: =SUMIFS($C$5:$C$75,$A$5:$A$75,J75,$B$5:$B$75,K75) -> 50.58 | M75: =IF(K75<I75,"sí","no") -> sí
I76: 46298 | J76: DEMOFIB | K76: =_xlfn.MAXIFS($B$5:$B$75,$A$5:$A$75,J76,$B$5:$B$75,"<="&I76) -> 46297 | L76: =SUMIFS($C$5:$C$75,$A$5:$A$75,J76,$B$5:$B$75,K76) -> 24.6125 | M76: =IF(K76<I76,"sí","no") -> sí
I77: 46299 | J77: DEMOACC | K77: =_xlfn.MAXIFS($B$5:$B$75,$A$5:$A$75,J77,$B$5:$B$75,"<="&I77) -> 46297 | L77: =SUMIFS($C$5:$C$75,$A$5:$A$75,J77,$B$5:$B$75,K77) -> 103.9 | M77: =IF(K77<I77,"sí","no") -> sí
I78: 46299 | J78: DEMOETF | K78: =_xlfn.MAXIFS($B$5:$B$75,$A$5:$A$75,J78,$B$5:$B$75,"<="&I78) -> 46297 | L78: =SUMIFS($C$5:$C$75,$A$5:$A$75,J78,$B$5:$B$75,K78) -> 50.58 | M78: =IF(K78<I78,"sí","no") -> sí
I79: 46299 | J79: DEMOFIB | K79: =_xlfn.MAXIFS($B$5:$B$75,$A$5:$A$75,J79,$B$5:$B$75,"<="&I79) -> 46297 | L79: =SUMIFS($C$5:$C$75,$A$5:$A$75,J79,$B$5:$B$75,K79) -> 24.6125 | M79: =IF(K79<I79,"sí","no") -> sí
I80: 46300 | J80: DEMOACC | K80: =_xlfn.MAXIFS($B$5:$B$75,$A$5:$A$75,J80,$B$5:$B$75,"<="&I80) -> 46300 | L80: =SUMIFS($C$5:$C$75,$A$5:$A$75,J80,$B$5:$B$75,K80) -> 101.65 | M80: =IF(K80<I80,"sí","no") -> no
I81: 46300 | J81: DEMOETF | K81: =_xlfn.MAXIFS($B$5:$B$75,$A$5:$A$75,J81,$B$5:$B$75,"<="&I81) -> 46300 | L81: =SUMIFS($C$5:$C$75,$A$5:$A$75,J81,$B$5:$B$75,K81) -> 49.83 | M81: =IF(K81<I81,"sí","no") -> no
I82: 46300 | J82: DEMOFIB | K82: =_xlfn.MAXIFS($B$5:$B$75,$A$5:$A$75,J82,$B$5:$B$75,"<="&I82) -> 46300 | L82: =SUMIFS($C$5:$C$75,$A$5:$A$75,J82,$B$5:$B$75,K82) -> 24.37 | M82: =IF(K82<I82,"sí","no") -> no
I83: 46301 | J83: DEMOACC | K83: =_xlfn.MAXIFS($B$5:$B$75,$A$5:$A$75,J83,$B$5:$B$75,"<="&I83) -> 46301 | L83: =SUMIFS($C$5:$C$75,$A$5:$A$75,J83,$B$5:$B$75,K83) -> 102.8 | M83: =IF(K83<I83,"sí","no") -> no
I84: 46301 | J84: DEMOETF | K84: =_xlfn.MAXIFS($B$5:$B$75,$A$5:$A$75,J84,$B$5:$B$75,"<="&I84) -> 46301 | L84: =SUMIFS($C$5:$C$75,$A$5:$A$75,J84,$B$5:$B$75,K84) -> 50.24 | M84: =IF(K84<I84,"sí","no") -> no
I85: 46301 | J85: DEMOFIB | K85: =_xlfn.MAXIFS($B$5:$B$75,$A$5:$A$75,J85,$B$5:$B$75,"<="&I85) -> 46301 | L85: =SUMIFS($C$5:$C$75,$A$5:$A$75,J85,$B$5:$B$75,K85) -> 24.515 | M85: =IF(K85<I85,"sí","no") -> no
I86: 46302 | J86: DEMOACC | K86: =_xlfn.MAXIFS($B$5:$B$75,$A$5:$A$75,J86,$B$5:$B$75,"<="&I86) -> 46302 | L86: =SUMIFS($C$5:$C$75,$A$5:$A$75,J86,$B$5:$B$75,K86) -> 104.95 | M86: =IF(K86<I86,"sí","no") -> no
I87: 46302 | J87: DEMOETF | K87: =_xlfn.MAXIFS($B$5:$B$75,$A$5:$A$75,J87,$B$5:$B$75,"<="&I87) -> 46302 | L87: =SUMIFS($C$5:$C$75,$A$5:$A$75,J87,$B$5:$B$75,K87) -> 50.96 | M87: =IF(K87<I87,"sí","no") -> no
... I109: 46309 | J109: DEMOFIB | K109: =_xlfn.MAXIFS($B$5:$B$75,$A$5:$A$75,J109,$B$5:$B$75,"<="&I109) -> 46309 | L109: =SUMIFS($C$5:$C$75,$A$5:$A$75,J109,$B$5:$B$75,K109) -> 25.6225 | M109: =IF(K109<I109,"sí","no") -> no

Sheet Tasas
A1: Tasas de las subastas primarias de CETES (RF-30; tasa_referencia de 4.4)
A2: Fuente: Banco de México, SIE, cuadro CF107 (https://www.banxico.org.mx). Series de tasa SF43936, SF43939, SF43942, SF43945 y SF349785; de plazo SF43935, SF43938, SF43941, SF43944 y SF349778. Consulta: 15/10/2026. Fecha = colocación (D-02, R-14).
A4: plazo_nominal | B4: fecha_colocacion | C4: valor | D4: unidad | E4: plazo_efectivo | F4: fuente_nombre | G4: carga | H4: serie de la tasa | I4: serie del plazo | J4: fuentes que coinciden (15/10/2026) | K4: valuaciones de CETES que la usan
A5: 28 | B5: 46261 | C5: 6.13 | D5: por ciento anual | E5: 28 | F5: Banco de México | G5: C-TASAS | H5: SF43936 | I5: SF43935 | J5: consultaSerieGrafica.do (JSON publico, 15 oct) | K5: =COUNTIFS(CETES!$Y$5:$Y$95,B5,CETES!$W$5:$W$95,A5)+COUNTIFS(CETES!$Z$5:$Z$95,B5,CETES!$X$5:$X$95,A5,CETES!$AC$5:$AC$95,"interpolación") -> 0
A6: 91 | B6: 46261 | C6: 6.6 | D6: por ciento anual | E6: 91 | F6: Banco de México | G6: C-TASAS | H6: SF43939 | I6: SF43938 | J6: consultaSerieGrafica.do (JSON publico, 15 oct) | K6: =COUNTIFS(CETES!$Y$5:$Y$95,B6,CETES!$W$5:$W$95,A6)+COUNTIFS(CETES!$Z$5:$Z$95,B6,CETES!$X$5:$X$95,A6,CETES!$AC$5:$AC$95,"interpolación") -> 0
A7: 182 | B7: 46261 | C7: 6.72 | D7: por ciento anual | E7: 175 | F7: Banco de México | G7: C-TASAS | H7: SF43942 | I7: SF43941 | J7: consultaSerieGrafica.do (JSON publico, 15 oct) | K7: =COUNTIFS(CETES!$Y$5:$Y$95,B7,CETES!$W$5:$W$95,A7)+COUNTIFS(CETES!$Z$5:$Z$95,B7,CETES!$X$5:$X$95,A7,CETES!$AC$5:$AC$95,"interpolación") -> 0
A8: 728 | B8: 46261 | C8: 7.87 | D8: por ciento anual | E8: 707 | F8: Banco de México | G8: C-TASAS | H8: SF349785 | I8: SF349778 | J8: consultaSerieGrafica.do (JSON publico, 15 oct) | K8: =COUNTIFS(CETES!$Y$5:$Y$95,B8,CETES!$W$5:$W$95,A8)+COUNTIFS(CETES!$Z$5:$Z$95,B8,CETES!$X$5:$X$95,A8,CETES!$AC$5:$AC$95,"interpolación") -> 0
A9: 28 | B9: 46268 | C9: 6.49 | D9: por ciento anual | E9: 28 | F9: Banco de México | G9: C-TASAS | H9: SF43936 | I9: SF43935 | J9: consultaSerieGrafica.do (JSON publico, 15 oct) | K9: =COUNTIFS(CETES!$Y$5:$Y$95,B9,CETES!$W$5:$W$95,A9)+COUNTIFS(CETES!$Z$5:$Z$95,B9,CETES!$X$5:$X$95,A9,CETES!$AC$5:$AC$95,"interpolación") -> 0
A10: 91 | B10: 46268 | C10: 6.54 | D10: por ciento anual | E10: 91 | F10: Banco de México | G10: C-TASAS | H10: SF43939 | I10: SF43938 | J10: consultaSerieGrafica.do (JSON publico, 15 oct) | K10: =COUNTIFS(CETES!$Y$5:$Y$95,B10,CETES!$W$5:$W$95,A10)+COUNTIFS(CETES!$Z$5:$Z$95,B10,CETES!$X$5:$X$95,A10,CETES!$AC$5:$AC$95,"interpolación") -> 0
A11: 182 | B11: 46268 | C11: 6.69 | D11: por ciento anual | E11: 182 | F11: Banco de México | G11: C-TASAS | H11: SF43942 | I11: SF43941 | J11: consultaSerieGrafica.do (JSON publico, 15 oct) | K11: =COUNTIFS(CETES!$Y$5:$Y$95,B11,CETES!$W$5:$W$95,A11)+COUNTIFS(CETES!$Z$5:$Z$95,B11,CETES!$X$5:$X$95,A11,CETES!$AC$5:$AC$95,"interpolación") -> 0
A12: 364 | B12: 46268 | C12: 7 | D12: por ciento anual | E12: 350 | F12: Banco de México | G12: C-TASAS | H12: SF43945 | I12: SF43944 | J12: consultaSerieGrafica.do (JSON publico, 15 oct) | K12: =COUNTIFS(CETES!$Y$5:$Y$95,B12,CETES!$W$5:$W$95,A12)+COUNTIFS(CETES!$Z$5:$Z$95,B12,CETES!$X$5:$X$95,A12,CETES!$AC$5:$AC$95,"interpolación") -> 0
A13: 28 | B13: 46275 | C13: 6.25 | D13: por ciento anual | E13: 28 | F13: Banco de México | G13: C-TASAS | H13: SF43936 | I13: SF43935 | J13: consultaSerieGrafica.do (JSON publico, 15 oct) | K13: =COUNTIFS(CETES!$Y$5:$Y$95,B13,CETES!$W$5:$W$95,A13)+COUNTIFS(CETES!$Z$5:$Z$95,B13,CETES!$X$5:$X$95,A13,CETES!$AC$5:$AC$95,"interpolación") -> 7
A14: 91 | B14: 46275 | C14: 6.56 | D14: por ciento anual | E14: 91 | F14: Banco de México | G14: C-TASAS | H14: SF43939 | I14: SF43938 | J14: consultaSerieGrafica.do (JSON publico, 15 oct) | K14: =COUNTIFS(CETES!$Y$5:$Y$95,B14,CETES!$W$5:$W$95,A14)+COUNTIFS(CETES!$Z$5:$Z$95,B14,CETES!$X$5:$X$95,A14,CETES!$AC$5:$AC$95,"interpolación") -> 0
A15: 182 | B15: 46275 | C15: 6.78 | D15: por ciento anual | E15: 175 | F15: Banco de México | G15: C-TASAS | H15: SF43942 | I15: SF43941 | J15: consultaSerieGrafica.do (JSON publico, 15 oct) | K15: =COUNTIFS(CETES!$Y$5:$Y$95,B15,CETES!$W$5:$W$95,A15)+COUNTIFS(CETES!$Z$5:$Z$95,B15,CETES!$X$5:$X$95,A15,CETES!$AC$5:$AC$95,"interpolación") -> 0
A16: 728 | B16: 46275 | C16: 7.94 | D16: por ciento anual | E16: 693 | F16: Banco de México | G16: C-TASAS | H16: SF349785 | I16: SF349778 | J16: consultaSerieGrafica.do (JSON publico, 15 oct) | K16: =COUNTIFS(CETES!$Y$5:$Y$95,B16,CETES!$W$5:$W$95,A16)+COUNTIFS(CETES!$Z$5:$Z$95,B16,CETES!$X$5:$X$95,A16,CETES!$AC$5:$AC$95,"interpolación") -> 0
... A36: 364 | B36: 46310 | C36: 7.11 | D36: por ciento anual | E36: 364 | F36: Banco de México | G36: C-TASAS | H36: SF43945 | I36: SF43944 | J36: cf107_15oct.html (pagina publica, 15 oct) | consultaSerieGrafica.do (JSON publico, 15 oct) | K36: =COUNTIFS(CETES!$Y$5:$Y$95,B36,CETES!$W$5:$W$95,A36)+COUNTIFS(CETES!$Z$5:$Z$95,B36,CETES!$X$5:$X$95,A36,CETES!$AC$5:$AC$95,"interpolación") -> 0

Sheet CETES
A1: Valuación de CETES antes del vencimiento (RF-26b)
A2: Para cada plazo nominal rige la última colocación con fecha igual o anterior a la de valuación (F–J). Se interpola linealmente por plazo efectivo entre los dos nodos que encierran d; fuera del rango, la tasa del extremo. r sin redondear; P = ROUND(VN / (1 + r/100 × d/360); 7), mitad alejándose de cero.
F3: Fecha de colocación vigente, por plazo nominal (días) | K3: Tasa vigente (% anual) | P3: Plazo efectivo (días)
A4: fecha | B4: instrumento_clave | C4: vencimiento | D4: valor nominal | E4: d (días por vencer) | F4: 28 | G4: 91 | H4: 182 | I4: 364 | J4: 728 | K4: 28 | L4: 91 | M4: 182 | N4: 364 | O4: 728 | P4: 28 | Q4: 91 | R4: 182 | S4: 364 | T4: 728 | U4: plazo efectivo inferior | V4: plazo efectivo superior | W4: plazo nominal inferior | X4: plazo nominal superior | Y4: colocación inferior | Z4: colocación superior | AA4: tasa inferior | AB4: tasa superior | AC4: caso | AD4: r (% anual, sin redondear) | AE4: P sin redondear | AF4: P (7 decimales) | AG4: llave
A5: 46275 | B5: BI261008 | C5: =INDEX(Entradas!$F$40:$F$46,MATCH(B5,Entradas!$A$40:$A$46,0)) -> 46303 | D5: =INDEX(Entradas!$G$40:$G$46,MATCH(B5,Entradas!$A$40:$A$46,0)) -> 10 | E5: =C5-A5 -> 28 | F5: =_xlfn.MAXIFS(Tasas!$B$5:$B$36,Tasas!$A$5:$A$36,F$4,Tasas!$B$5:$B$36,"<="&$A5) -> 46275 | G5: =_xlfn.MAXIFS(Tasas!$B$5:$B$36,Tasas!$A$5:$A$36,G$4,Tasas!$B$5:$B$36,"<="&$A5) -> 46275 | H5: =_xlfn.MAXIFS(Tasas!$B$5:$B$36,Tasas!$A$5:$A$36,H$4,Tasas!$B$5:$B$36,"<="&$A5) -> 46275 | I5: =_xlfn.MAXIFS(Tasas!$B$5:$B$36,Tasas!$A$5:$A$36,I$4,Tasas!$B$5:$B$36,"<="&$A5) -> 46268 | J5: =_xlfn.MAXIFS(Tasas!$B$5:$B$36,Tasas!$A$5:$A$36,J$4,Tasas!$B$5:$B$36,"<="&$A5) -> 46275 | K5: =SUMIFS(Tasas!$C$5:$C$36,Tasas!$A$5:$A$36,K$4,Tasas!$B$5:$B$36,F5) -> 6.25 | L5: =SUMIFS(Tasas!$C$5:$C$36,Tasas!$A$5:$A$36,L$4,Tasas!$B$5:$B$36,G5) -> 6.56 | M5: =SUMIFS(Tasas!$C$5:$C$36,Tasas!$A$5:$A$36,M$4,Tasas!$B$5:$B$36,H5) -> 6.78 | N5: =SUMIFS(Tasas!$C$5:$C$36,Tasas!$A$5:$A$36,N$4,Tasas!$B$5:$B$36,I5) -> 7 | O5: =SUMIFS(Tasas!$C$5:$C$36,Tasas!$A$5:$A$36,O$4,Tasas!$B$5:$B$36,J5) -> 7.94 | P5: =SUMIFS(Tasas!$E$5:$E$36,Tasas!$A$5:$A$36,P$4,Tasas!$B$5:$B$36,F5) -> 28 | Q5: =SUMIFS(Tasas!$E$5:$E$36,Tasas!$A$5:$A$36,Q$4,Tasas!$B$5:$B$36,G5) -> 91 | R5: =SUMIFS(Tasas!$E$5:$E$36,Tasas!$A$5:$A$36,R$4,Tasas!$B$5:$B$36,H5) -> 175 | S5: =SUMIFS(Tasas!$E$5:$E$36,Tasas!$A$5:$A$36,S$4,Tasas!$B$5:$B$36,I5) -> 350 | T5: =SUMIFS(Tasas!$E$5:$E$36,Tasas!$A$5:$A$36,T$4,Tasas!$B$5:$B$36,J5) -> 693 | U5: =IF($E5<=MIN($P5:$T5),MIN($P5:$T5),_xlfn.MAXIFS($P5:$T5,$P5:$T5,"<="&$E5)) -> 28 | V5: =IF($E5>=MAX($P5:$T5),MAX($P5:$T5),_xlfn.MINIFS($P5:$T5,$P5:$T5,">="&$E5)) -> 28 | W5: =INDEX($P$4:$T$4,MATCH(U5,$P5:$T5,0)) -> 28 | X5: =INDEX($P$4:$T$4,MATCH(V5,$P5:$T5,0)) -> 28 | Y5: =INDEX($F5:$J5,MATCH(U5,$P5:$T5,0)) -> 46275 | Z5: =INDEX($F5:$J5,MATCH(V5,$P5:$T5,0)) -> 46275 | AA5: =INDEX($K5:$O5,MATCH(U5,$P5:$T5,0)) -> 6.25 | AB5: =INDEX($K5:$O5,MATCH(V5,$P5:$T5,0)) -> 6.25 | AC5: =IF(E5<MIN($P5:$T5),"extremo inferior",IF(E5>MAX($P5:$T5),"extremo superior",IF(U5=V5,"nodo","interpolación"))) -> nodo | AD5: =IF(U5=V5,AA5,AA5+(AB5-AA5)*(E5-U5)/(V5-U5)) -> 6.25 | AE5: =D5/(1+AD5/100*E5/360) -> 9.951624 | AF5: =ROUND(AE5,7) -> 9.951624 | AG5: =A5&"|"&B5 -> 46275|BI261008
A6: 46276 | B6: BI261008 | C6: =INDEX(Entradas!$F$40:$F$46,MATCH(B6,Entradas!$A$40:$A$46,0)) -> 46303 | D6: =INDEX(Entradas!$G$40:$G$46,MATCH(B6,Entradas!$A$40:$A$46,0)) -> 10 | E6: =C6-A6 -> 27 | F6: =_xlfn.MAXIFS(Tasas!$B$5:$B$36,Tasas!$A$5:$A$36,F$4,Tasas!$B$5:$B$36,"<="&$A6) -> 46275 | G6: =_xlfn.MAXIFS(Tasas!$B$5:$B$36,Tasas!$A$5:$A$36,G$4,Tasas!$B$5:$B$36,"<="&$A6) -> 46275 | H6: =_xlfn.MAXIFS(Tasas!$B$5:$B$36,Tasas!$A$5:$A$36,H$4,Tasas!$B$5:$B$36,"<="&$A6) -> 46275 | I6: =_xlfn.MAXIFS(Tasas!$B$5:$B$36,Tasas!$A$5:$A$36,I$4,Tasas!$B$5:$B$36,"<="&$A6) -> 46268 | J6: =_xlfn.MAXIFS(Tasas!$B$5:$B$36,Tasas!$A$5:$A$36,J$4,Tasas!$B$5:$B$36,"<="&$A6) -> 46275 | K6: =SUMIFS(Tasas!$C$5:$C$36,Tasas!$A$5:$A$36,K$4,Tasas!$B$5:$B$36,F6) -> 6.25 | L6: =SUMIFS(Tasas!$C$5:$C$36,Tasas!$A$5:$A$36,L$4,Tasas!$B$5:$B$36,G6) -> 6.56 | M6: =SUMIFS(Tasas!$C$5:$C$36,Tasas!$A$5:$A$36,M$4,Tasas!$B$5:$B$36,H6) -> 6.78 | N6: =SUMIFS(Tasas!$C$5:$C$36,Tasas!$A$5:$A$36,N$4,Tasas!$B$5:$B$36,I6) -> 7 | O6: =SUMIFS(Tasas!$C$5:$C$36,Tasas!$A$5:$A$36,O$4,Tasas!$B$5:$B$36,J6) -> 7.94 | P6: =SUMIFS(Tasas!$E$5:$E$36,Tasas!$A$5:$A$36,P$4,Tasas!$B$5:$B$36,F6) -> 28 | Q6: =SUMIFS(Tasas!$E$5:$E$36,Tasas!$A$5:$A$36,Q$4,Tasas!$B$5:$B$36,G6) -> 91 | R6: =SUMIFS(Tasas!$E$5:$E$36,Tasas!$A$5:$A$36,R$4,Tasas!$B$5:$B$36,H6) -> 175 | S6: =SUMIFS(Tasas!$E$5:$E$36,Tasas!$A$5:$A$36,S$4,Tasas!$B$5:$B$36,I6) -> 350 | T6: =SUMIFS(Tasas!$E$5:$E$36,Tasas!$A$5:$A$36,T$4,Tasas!$B$5:$B$36,J6) -> 693 | U6: =IF($E6<=MIN($P6:$T6),MIN($P6:$T6),_xlfn.MAXIFS($P6:$T6,$P6:$T6,"<="&$E6)) -> 28 | V6: =IF($E6>=MAX($P6:$T6),MAX($P6:$T6),_xlfn.MINIFS($P6:$T6,$P6:$T6,">="&$E6)) -> 28 | W6: =INDEX($P$4:$T$4,MATCH(U6,$P6:$T6,0)) -> 28 | X6: =INDEX($P$4:$T$4,MATCH(V6,$P6:$T6,0)) -> 28 | Y6: =INDEX($F6:$J6,MATCH(U6,$P6:$T6,0)) -> 46275 | Z6: =INDEX($F6:$J6,MATCH(V6,$P6:$T6,0)) -> 46275 | AA6: =INDEX($K6:$O6,MATCH(U6,$P6:$T6,0)) -> 6.25 | AB6: =INDEX($K6:$O6,MATCH(V6,$P6:$T6,0)) -> 6.25 | AC6: =IF(E6<MIN($P6:$T6),"extremo inferior",IF(E6>MAX($P6:$T6),"extremo superior",IF(U6=V6,"nodo","interpolación"))) -> extremo inferior | AD6: =IF(U6=V6,AA6,AA6+(AB6-AA6)*(E6-U6)/(V6-U6)) -> 6.25 | AE6: =D6/(1+AD6/100*E6/360) -> 9.9533437 | AF6: =ROUND(AE6,7) -> 9.9533437 | AG6: =A6&"|"&B6 -> 46276|BI261008
A7: 46277 | B7: BI261008 | C7: =INDEX(Entradas!$F$40:$F$46,MATCH(B7,Entradas!$A$40:$A$46,0)) -> 46303 | D7: =INDEX(Entradas!$G$40:$G$46,MATCH(B7,Entradas!$A$40:$A$46,0)) -> 10 | E7: =C7-A7 -> 26 | F7: =_xlfn.MAXIFS(Tasas!$B$5:$B$36,Tasas!$A$5:$A$36,F$4,Tasas!$B$5:$B$36,"<="&$A7) -> 46275 | G7: =_xlfn.MAXIFS(Tasas!$B$5:$B$36,Tasas!$A$5:$A$36,G$4,Tasas!$B$5:$B$36,"<="&$A7) -> 46275 | H7: =_xlfn.MAXIFS(Tasas!$B$5:$B$36,Tasas!$A$5:$A$36,H$4,Tasas!$B$5:$B$36,"<="&$A7) -> 46275 | I7: =_xlfn.MAXIFS(Tasas!$B$5:$B$36,Tasas!$A$5:$A$36,I$4,Tasas!$B$5:$B$36,"<="&$A7) -> 46268 | J7: =_xlfn.MAXIFS(Tasas!$B$5:$B$36,Tasas!$A$5:$A$36,J$4,Tasas!$B$5:$B$36,"<="&$A7) -> 46275 | K7: =SUMIFS(Tasas!$C$5:$C$36,Tasas!$A$5:$A$36,K$4,Tasas!$B$5:$B$36,F7) -> 6.25 | L7: =SUMIFS(Tasas!$C$5:$C$36,Tasas!$A$5:$A$36,L$4,Tasas!$B$5:$B$36,G7) -> 6.56 | M7: =SUMIFS(Tasas!$C$5:$C$36,Tasas!$A$5:$A$36,M$4,Tasas!$B$5:$B$36,H7) -> 6.78 | N7: =SUMIFS(Tasas!$C$5:$C$36,Tasas!$A$5:$A$36,N$4,Tasas!$B$5:$B$36,I7) -> 7 | O7: =SUMIFS(Tasas!$C$5:$C$36,Tasas!$A$5:$A$36,O$4,Tasas!$B$5:$B$36,J7) -> 7.94 | P7: =SUMIFS(Tasas!$E$5:$E$36,Tasas!$A$5:$A$36,P$4,Tasas!$B$5:$B$36,F7) -> 28 | Q7: =SUMIFS(Tasas!$E$5:$E$36,Tasas!$A$5:$A$36,Q$4,Tasas!$B$5:$B$36,G7) -> 91 | R7: =SUMIFS(Tasas!$E$5:$E$36,Tasas!$A$5:$A$36,R$4,Tasas!$B$5:$B$36,H7) -> 175 | S7: =SUMIFS(Tasas!$E$5:$E$36,Tasas!$A$5:$A$36,S$4,Tasas!$B$5:$B$36,I7) -> 350 | T7: =SUMIFS(Tasas!$E$5:$E$36,Tasas!$A$5:$A$36,T$4,Tasas!$B$5:$B$36,J7) -> 693 | U7: =IF($E7<=MIN($P7:$T7),MIN($P7:$T7),_xlfn.MAXIFS($P7:$T7,$P7:$T7,"<="&$E7)) -> 28 | V7: =IF($E7>=MAX($P7:$T7),MAX($P7:$T7),_xlfn.MINIFS($P7:$T7,$P7:$T7,">="&$E7)) -> 28 | W7: =INDEX($P$4:$T$4,MATCH(U7,$P7:$T7,0)) -> 28 | X7: =INDEX($P$4:$T$4,MATCH(V7,$P7:$T7,0)) -> 28 | Y7: =INDEX($F7:$J7,MATCH(U7,$P7:$T7,0)) -> 46275 | Z7: =INDEX($F7:$J7,MATCH(V7,$P7:$T7,0)) -> 46275 | AA7: =INDEX($K7:$O7,MATCH(U7,$P7:$T7,0)) -> 6.25 | AB7: =INDEX($K7:$O7,MATCH(V7,$P7:$T7,0)) -> 6.25 | AC7: =IF(E7<MIN($P7:$T7),"extremo inferior",IF(E7>MAX($P7:$T7),"extremo superior",IF(U7=V7,"nodo","interpolación"))) -> extremo inferior | AD7: =IF(U7=V7,AA7,AA7+(AB7-AA7)*(E7-U7)/(V7-U7)) -> 6.25 | AE7: =D7/(1+AD7/100*E7/360) -> 9.9550639 | AF7: =ROUND(AE7,7) -> 9.9550639 | AG7: =A7&"|"&B7 -> 46277|BI261008
A8: 46278 | B8: BI261008 | C8: =INDEX(Entradas!$F$40:$F$46,MATCH(B8,Entradas!$A$40:$A$46,0)) -> 46303 | D8: =INDEX(Entradas!$G$40:$G$46,MATCH(B8,Entradas!$A$40:$A$46,0)) -> 10 | E8: =C8-A8 -> 25 | F8: =_xlfn.MAXIFS(Tasas!$B$5:$B$36,Tasas!$A$5:$A$36,F$4,Tasas!$B$5:$B$36,"<="&$A8) -> 46275 | G8: =_xlfn.MAXIFS(Tasas!$B$5:$B$36,Tasas!$A$5:$A$36,G$4,Tasas!$B$5:$B$36,"<="&$A8) -> 46275 | H8: =_xlfn.MAXIFS(Tasas!$B$5:$B$36,Tasas!$A$5:$A$36,H$4,Tasas!$B$5:$B$36,"<="&$A8) -> 46275 | I8: =_xlfn.MAXIFS(Tasas!$B$5:$B$36,Tasas!$A$5:$A$36,I$4,Tasas!$B$5:$B$36,"<="&$A8) -> 46268 | J8: =_xlfn.MAXIFS(Tasas!$B$5:$B$36,Tasas!$A$5:$A$36,J$4,Tasas!$B$5:$B$36,"<="&$A8) -> 46275 | K8: =SUMIFS(Tasas!$C$5:$C$36,Tasas!$A$5:$A$36,K$4,Tasas!$B$5:$B$36,F8) -> 6.25 | L8: =SUMIFS(Tasas!$C$5:$C$36,Tasas!$A$5:$A$36,L$4,Tasas!$B$5:$B$36,G8) -> 6.56 | M8: =SUMIFS(Tasas!$C$5:$C$36,Tasas!$A$5:$A$36,M$4,Tasas!$B$5:$B$36,H8) -> 6.78 | N8: =SUMIFS(Tasas!$C$5:$C$36,Tasas!$A$5:$A$36,N$4,Tasas!$B$5:$B$36,I8) -> 7 | O8: =SUMIFS(Tasas!$C$5:$C$36,Tasas!$A$5:$A$36,O$4,Tasas!$B$5:$B$36,J8) -> 7.94 | P8: =SUMIFS(Tasas!$E$5:$E$36,Tasas!$A$5:$A$36,P$4,Tasas!$B$5:$B$36,F8) -> 28 | Q8: =SUMIFS(Tasas!$E$5:$E$36,Tasas!$A$5:$A$36,Q$4,Tasas!$B$5:$B$36,G8) -> 91 | R8: =SUMIFS(Tasas!$E$5:$E$36,Tasas!$A$5:$A$36,R$4,Tasas!$B$5:$B$36,H8) -> 175 | S8: =SUMIFS(Tasas!$E$5:$E$36,Tasas!$A$5:$A$36,S$4,Tasas!$B$5:$B$36,I8) -> 350 | T8: =SUMIFS(Tasas!$E$5:$E$36,Tasas!$A$5:$A$36,T$4,Tasas!$B$5:$B$36,J8) -> 693 | U8: =IF($E8<=MIN($P8:$T8),MIN($P8:$T8),_xlfn.MAXIFS($P8:$T8,$P8:$T8,"<="&$E8)) -> 28 | V8: =IF($E8>=MAX($P8:$T8),MAX($P8:$T8),_xlfn.MINIFS($P8:$T8,$P8:$T8,">="&$E8)) -> 28 | W8: =INDEX($P$4:$T$4,MATCH(U8,$P8:$T8,0)) -> 28 | X8: =INDEX($P$4:$T$4,MATCH(V8,$P8:$T8,0)) -> 28 | Y8: =INDEX($F8:$J8,MATCH(U8,$P8:$T8,0)) -> 46275 | Z8: =INDEX($F8:$J8,MATCH(V8,$P8:$T8,0)) -> 46275 | AA8: =INDEX($K8:$O8,MATCH(U8,$P8:$T8,0)) -> 6.25 | AB8: =INDEX($K8:$O8,MATCH(V8,$P8:$T8,0)) -> 6.25 | AC8: =IF(E8<MIN($P8:$T8),"extremo inferior",IF(E8>MAX($P8:$T8),"extremo superior",IF(U8=V8,"nodo","interpolación"))) -> extremo inferior | AD8: =IF(U8=V8,AA8,AA8+(AB8-AA8)*(E8-U8)/(V8-U8)) -> 6.25 | AE8: =D8/(1+AD8/100*E8/360) -> 9.9567848 | AF8: =ROUND(AE8,7) -> 9.9567848 | AG8: =A8&"|"&B8 -> 46278|BI261008
A9: 46279 | B9: BI261008 | C9: =INDEX(Entradas!$F$40:$F$46,MATCH(B9,Entradas!$A$40:$A$46,0)) -> 46303 | D9: =INDEX(Entradas!$G$40:$G$46,MATCH(B9,Entradas!$A$40:$A$46,0)) -> 10 | E9: =C9-A9 -> 24 | F9: =_xlfn.MAXIFS(Tasas!$B$5:$B$36,Tasas!$A$5:$A$36,F$4,Tasas!$B$5:$B$36,"<="&$A9) -> 46275 | G9: =_xlfn.MAXIFS(Tasas!$B$5:$B$36,Tasas!$A$5:$A$36,G$4,Tasas!$B$5:$B$36,"<="&$A9) -> 46275 | H9: =_xlfn.MAXIFS(Tasas!$B$5:$B$36,Tasas!$A$5:$A$36,H$4,Tasas!$B$5:$B$36,"<="&$A9) -> 46275 | I9: =_xlfn.MAXIFS(Tasas!$B$5:$B$36,Tasas!$A$5:$A$36,I$4,Tasas!$B$5:$B$36,"<="&$A9) -> 46268 | J9: =_xlfn.MAXIFS(Tasas!$B$5:$B$36,Tasas!$A$5:$A$36,J$4,Tasas!$B$5:$B$36,"<="&$A9) -> 46275 | K9: =SUMIFS(Tasas!$C$5:$C$36,Tasas!$A$5:$A$36,K$4,Tasas!$B$5:$B$36,F9) -> 6.25 | L9: =SUMIFS(Tasas!$C$5:$C$36,Tasas!$A$5:$A$36,L$4,Tasas!$B$5:$B$36,G9) -> 6.56 | M9: =SUMIFS(Tasas!$C$5:$C$36,Tasas!$A$5:$A$36,M$4,Tasas!$B$5:$B$36,H9) -> 6.78 | N9: =SUMIFS(Tasas!$C$5:$C$36,Tasas!$A$5:$A$36,N$4,Tasas!$B$5:$B$36,I9) -> 7 | O9: =SUMIFS(Tasas!$C$5:$C$36,Tasas!$A$5:$A$36,O$4,Tasas!$B$5:$B$36,J9) -> 7.94 | P9: =SUMIFS(Tasas!$E$5:$E$36,Tasas!$A$5:$A$36,P$4,Tasas!$B$5:$B$36,F9) -> 28 | Q9: =SUMIFS(Tasas!$E$5:$E$36,Tasas!$A$5:$A$36,Q$4,Tasas!$B$5:$B$36,G9) -> 91 | R9: =SUMIFS(Tasas!$E$5:$E$36,Tasas!$A$5:$A$36,R$4,Tasas!$B$5:$B$36,H9) -> 175 | S9: =SUMIFS(Tasas!$E$5:$E$36,Tasas!$A$5:$A$36,S$4,Tasas!$B$5:$B$36,I9) -> 350 | T9: =SUMIFS(Tasas!$E$5:$E$36,Tasas!$A$5:$A$36,T$4,Tasas!$B$5:$B$36,J9) -> 693 | U9: =IF($E9<=MIN($P9:$T9),MIN($P9:$T9),_xlfn.MAXIFS($P9:$T9,$P9:$T9,"<="&$E9)) -> 28 | V9: =IF($E9>=MAX($P9:$T9),MAX($P9:$T9),_xlfn.MINIFS($P9:$T9,$P9:$T9,">="&$E9)) -> 28 | W9: =INDEX($P$4:$T$4,MATCH(U9,$P9:$T9,0)) -> 28 | X9: =INDEX($P$4:$T$4,MATCH(V9,$P9:$T9,0)) -> 28 | Y9: =INDEX($F9:$J9,MATCH(U9,$P9:$T9,0)) -> 46275 | Z9: =INDEX($F9:$J9,MATCH(V9,$P9:$T9,0)) -> 46275 | AA9: =INDEX($K9:$O9,MATCH(U9,$P9:$T9,0)) -> 6.25 | AB9: =INDEX($K9:$O9,MATCH(V9,$P9:$T9,0)) -> 6.25 | AC9: =IF(E9<MIN($P9:$T9),"extremo inferior",IF(E9>MAX($P9:$T9),"extremo superior",IF(U9=V9,"nodo","interpolación"))) -> extremo inferior | AD9: =IF(U9=V9,AA9,AA9+(AB9-AA9)*(E9-U9)/(V9-U9)) -> 6.25 | AE9: =D9/(1+AD9/100*E9/360) -> 9.9585062 | AF9: =ROUND(AE9,7) -> 9.9585062 | AG9: =A9&"|"&B9 -> 46279|BI261008
A10: 46280 | B10: BI261008 | C10: =INDEX(Entradas!$F$40:$F$46,MATCH(B10,Entradas!$A$40:$A$46,0)) -> 46303 | D10: =INDEX(Entradas!$G$40:$G$46,MATCH(B10,Entradas!$A$40:$A$46,0)) -> 10 | E10: =C10-A10 -> 23 | F10: =_xlfn.MAXIFS(Tasas!$B$5:$B$36,Tasas!$A$5:$A$36,F$4,Tasas!$B$5:$B$36,"<="&$A10) -> 46275 | G10: =_xlfn.MAXIFS(Tasas!$B$5:$B$36,Tasas!$A$5:$A$36,G$4,Tasas!$B$5:$B$36,"<="&$A10) -> 46275 | H10: =_xlfn.MAXIFS(Tasas!$B$5:$B$36,Tasas!$A$5:$A$36,H$4,Tasas!$B$5:$B$36,"<="&$A10) -> 46275 | I10: =_xlfn.MAXIFS(Tasas!$B$5:$B$36,Tasas!$A$5:$A$36,I$4,Tasas!$B$5:$B$36,"<="&$A10) -> 46268 | J10: =_xlfn.MAXIFS(Tasas!$B$5:$B$36,Tasas!$A$5:$A$36,J$4,Tasas!$B$5:$B$36,"<="&$A10) -> 46275 | K10: =SUMIFS(Tasas!$C$5:$C$36,Tasas!$A$5:$A$36,K$4,Tasas!$B$5:$B$36,F10) -> 6.25 | L10: =SUMIFS(Tasas!$C$5:$C$36,Tasas!$A$5:$A$36,L$4,Tasas!$B$5:$B$36,G10) -> 6.56 | M10: =SUMIFS(Tasas!$C$5:$C$36,Tasas!$A$5:$A$36,M$4,Tasas!$B$5:$B$36,H10) -> 6.78 | N10: =SUMIFS(Tasas!$C$5:$C$36,Tasas!$A$5:$A$36,N$4,Tasas!$B$5:$B$36,I10) -> 7 | O10: =SUMIFS(Tasas!$C$5:$C$36,Tasas!$A$5:$A$36,O$4,Tasas!$B$5:$B$36,J10) -> 7.94 | P10: =SUMIFS(Tasas!$E$5:$E$36,Tasas!$A$5:$A$36,P$4,Tasas!$B$5:$B$36,F10) -> 28 | Q10: =SUMIFS(Tasas!$E$5:$E$36,Tasas!$A$5:$A$36,Q$4,Tasas!$B$5:$B$36,G10) -> 91 | R10: =SUMIFS(Tasas!$E$5:$E$36,Tasas!$A$5:$A$36,R$4,Tasas!$B$5:$B$36,H10) -> 175 | S10: =SUMIFS(Tasas!$E$5:$E$36,Tasas!$A$5:$A$36,S$4,Tasas!$B$5:$B$36,I10) -> 350 | T10: =SUMIFS(Tasas!$E$5:$E$36,Tasas!$A$5:$A$36,T$4,Tasas!$B$5:$B$36,J10) -> 693 | U10: =IF($E10<=MIN($P10:$T10),MIN($P10:$T10),_xlfn.MAXIFS($P10:$T10,$P10:$T10,"<="&$E10)) -> 28 | V10: =IF($E10>=MAX($P10:$T10),MAX($P10:$T10),_xlfn.MINIFS($P10:$T10,$P10:$T10,">="&$E10)) -> 28 | W10: =INDEX($P$4:$T$4,MATCH(U10,$P10:$T10,0)) -> 28 | X10: =INDEX($P$4:$T$4,MATCH(V10,$P10:$T10,0)) -> 28 | Y10: =INDEX($F10:$J10,MATCH(U10,$P10:$T10,0)) -> 46275 | Z10: =INDEX($F10:$J10,MATCH(V10,$P10:$T10,0)) -> 46275 | AA10: =INDEX($K10:$O10,MATCH(U10,$P10:$T10,0)) -> 6.25 | AB10: =INDEX($K10:$O10,MATCH(V10,$P10:$T10,0)) -> 6.25 | AC10: =IF(E10<MIN($P10:$T10),"extremo inferior",IF(E10>MAX($P10:$T10),"extremo superior",IF(U10=V10,"nodo","interpolación"))) -> extremo inferior | AD10: =IF(U10=V10,AA10,AA10+(AB10-AA10)*(E10-U10)/(V10-U10)) -> 6.25 | AE10: =D10/(1+AD10/100*E10/360) -> 9.9602283 | AF10: =ROUND(AE10,7) -> 9.9602283 | AG10: =A10&"|"&B10 -> 46280|BI261008
A11: 46281 | B11: BI261008 | C11: =INDEX(Entradas!$F$40:$F$46,MATCH(B11,Entradas!$A$40:$A$46,0)) -> 46303 | D11: =INDEX(Entradas!$G$40:$G$46,MATCH(B11,Entradas!$A$40:$A$46,0)) -> 10 | E11: =C11-A11 -> 22 | F11: =_xlfn.MAXIFS(Tasas!$B$5:$B$36,Tasas!$A$5:$A$36,F$4,Tasas!$B$5:$B$36,"<="&$A11) -> 46275 | G11: =_xlfn.MAXIFS(Tasas!$B$5:$B$36,Tasas!$A$5:$A$36,G$4,Tasas!$B$5:$B$36,"<="&$A11) -> 46275 | H11: =_xlfn.MAXIFS(Tasas!$B$5:$B$36,Tasas!$A$5:$A$36,H$4,Tasas!$B$5:$B$36,"<="&$A11) -> 46275 | I11: =_xlfn.MAXIFS(Tasas!$B$5:$B$36,Tasas!$A$5:$A$36,I$4,Tasas!$B$5:$B$36,"<="&$A11) -> 46268 | J11: =_xlfn.MAXIFS(Tasas!$B$5:$B$36,Tasas!$A$5:$A$36,J$4,Tasas!$B$5:$B$36,"<="&$A11) -> 46275 | K11: =SUMIFS(Tasas!$C$5:$C$36,Tasas!$A$5:$A$36,K$4,Tasas!$B$5:$B$36,F11) -> 6.25 | L11: =SUMIFS(Tasas!$C$5:$C$36,Tasas!$A$5:$A$36,L$4,Tasas!$B$5:$B$36,G11) -> 6.56 | M11: =SUMIFS(Tasas!$C$5:$C$36,Tasas!$A$5:$A$36,M$4,Tasas!$B$5:$B$36,H11) -> 6.78 | N11: =SUMIFS(Tasas!$C$5:$C$36,Tasas!$A$5:$A$36,N$4,Tasas!$B$5:$B$36,I11) -> 7 | O11: =SUMIFS(Tasas!$C$5:$C$36,Tasas!$A$5:$A$36,O$4,Tasas!$B$5:$B$36,J11) -> 7.94 | P11: =SUMIFS(Tasas!$E$5:$E$36,Tasas!$A$5:$A$36,P$4,Tasas!$B$5:$B$36,F11) -> 28 | Q11: =SUMIFS(Tasas!$E$5:$E$36,Tasas!$A$5:$A$36,Q$4,Tasas!$B$5:$B$36,G11) -> 91 | R11: =SUMIFS(Tasas!$E$5:$E$36,Tasas!$A$5:$A$36,R$4,Tasas!$B$5:$B$36,H11) -> 175 | S11: =SUMIFS(Tasas!$E$5:$E$36,Tasas!$A$5:$A$36,S$4,Tasas!$B$5:$B$36,I11) -> 350 | T11: =SUMIFS(Tasas!$E$5:$E$36,Tasas!$A$5:$A$36,T$4,Tasas!$B$5:$B$36,J11) -> 693 | U11: =IF($E11<=MIN($P11:$T11),MIN($P11:$T11),_xlfn.MAXIFS($P11:$T11,$P11:$T11,"<="&$E11)) -> 28 | V11: =IF($E11>=MAX($P11:$T11),MAX($P11:$T11),_xlfn.MINIFS($P11:$T11,$P11:$T11,">="&$E11)) -> 28 | W11: =INDEX($P$4:$T$4,MATCH(U11,$P11:$T11,0)) -> 28 | X11: =INDEX($P$4:$T$4,MATCH(V11,$P11:$T11,0)) -> 28 | Y11: =INDEX($F11:$J11,MATCH(U11,$P11:$T11,0)) -> 46275 | Z11: =INDEX($F11:$J11,MATCH(V11,$P11:$T11,0)) -> 46275 | AA11: =INDEX($K11:$O11,MATCH(U11,$P11:$T11,0)) -> 6.25 | AB11: =INDEX($K11:$O11,MATCH(V11,$P11:$T11,0)) -> 6.25 | AC11: =IF(E11<MIN($P11:$T11),"extremo inferior",IF(E11>MAX($P11:$T11),"extremo superior",IF(U11=V11,"nodo","interpolación"))) -> extremo inferior | AD11: =IF(U11=V11,AA11,AA11+(AB11-AA11)*(E11-U11)/(V11-U11)) -> 6.25 | AE11: =D11/(1+AD11/100*E11/360) -> 9.9619509 | AF11: =ROUND(AE11,7) -> 9.9619509 | AG11: =A11&"|"&B11 -> 46281|BI261008
A12: 46282 | B12: BI261008 | C12: =INDEX(Entradas!$F$40:$F$46,MATCH(B12,Entradas!$A$40:$A$46,0)) -> 46303 | D12: =INDEX(Entradas!$G$40:$G$46,MATCH(B12,Entradas!$A$40:$A$46,0)) -> 10 | E12: =C12-A12 -> 21 | F12: =_xlfn.MAXIFS(Tasas!$B$5:$B$36,Tasas!$A$5:$A$36,F$4,Tasas!$B$5:$B$36,"<="&$A12) -> 46282 | G12: =_xlfn.MAXIFS(Tasas!$B$5:$B$36,Tasas!$A$5:$A$36,G$4,Tasas!$B$5:$B$36,"<="&$A12) -> 46282 | H12: =_xlfn.MAXIFS(Tasas!$B$5:$B$36,Tasas!$A$5:$A$36,H$4,Tasas!$B$5:$B$36,"<="&$A12) -> 46282 | I12: =_xlfn.MAXIFS(Tasas!$B$5:$B$36,Tasas!$A$5:$A$36,I$4,Tasas!$B$5:$B$36,"<="&$A12) -> 46282 | J12: =_xlfn.MAXIFS(Tasas!$B$5:$B$36,Tasas!$A$5:$A$36,J$4,Tasas!$B$5:$B$36,"<="&$A12) -> 46275 | K12: =SUMIFS(Tasas!$C$5:$C$36,Tasas!$A$5:$A$36,K$4,Tasas!$B$5:$B$36,F12) -> 6.25 | L12: =SUMIFS(Tasas!$C$5:$C$36,Tasas!$A$5:$A$36,L$4,Tasas!$B$5:$B$36,G12) -> 6.66 | M12: =SUMIFS(Tasas!$C$5:$C$36,Tasas!$A$5:$A$36,M$4,Tasas!$B$5:$B$36,H12) -> 6.9 | N12: =SUMIFS(Tasas!$C$5:$C$36,Tasas!$A$5:$A$36,N$4,Tasas!$B$5:$B$36,I12) -> 7.24 | O12: =SUMIFS(Tasas!$C$5:$C$36,Tasas!$A$5:$A$36,O$4,Tasas!$B$5:$B$36,J12) -> 7.94 | P12: =SUMIFS(Tasas!$E$5:$E$36,Tasas!$A$5:$A$36,P$4,Tasas!$B$5:$B$36,F12) -> 28 | Q12: =SUMIFS(Tasas!$E$5:$E$36,Tasas!$A$5:$A$36,Q$4,Tasas!$B$5:$B$36,G12) -> 91 | R12: =SUMIFS(Tasas!$E$5:$E$36,Tasas!$A$5:$A$36,R$4,Tasas!$B$5:$B$36,H12) -> 182 | S12: =SUMIFS(Tasas!$E$5:$E$36,Tasas!$A$5:$A$36,S$4,Tasas!$B$5:$B$36,I12) -> 363 | T12: =SUMIFS(Tasas!$E$5:$E$36,Tasas!$A$5:$A$36,T$4,Tasas!$B$5:$B$36,J12) -> 693 | U12: =IF($E12<=MIN($P12:$T12),MIN($P12:$T12),_xlfn.MAXIFS($P12:$T12,$P12:$T12,"<="&$E12)) -> 28 | V12: =IF($E12>=MAX($P12:$T12),MAX($P12:$T12),_xlfn.MINIFS($P12:$T12,$P12:$T12,">="&$E12)) -> 28 | W12: =INDEX($P$4:$T$4,MATCH(U12,$P12:$T12,0)) -> 28 | X12: =INDEX($P$4:$T$4,MATCH(V12,$P12:$T12,0)) -> 28 | Y12: =INDEX($F12:$J12,MATCH(U12,$P12:$T12,0)) -> 46282 | Z12: =INDEX($F12:$J12,MATCH(V12,$P12:$T12,0)) -> 46282 | AA12: =INDEX($K12:$O12,MATCH(U12,$P12:$T12,0)) -> 6.25 | AB12: =INDEX($K12:$O12,MATCH(V12,$P12:$T12,0)) -> 6.25 | AC12: =IF(E12<MIN($P12:$T12),"extremo inferior",IF(E12>MAX($P12:$T12),"extremo superior",IF(U12=V12,"nodo","interpolación"))) -> extremo inferior | AD12: =IF(U12=V12,AA12,AA12+(AB12-AA12)*(E12-U12)/(V12-U12)) -> 6.25 | AE12: =D12/(1+AD12/100*E12/360) -> 9.9636741 | AF12: =ROUND(AE12,7) -> 9.9636741 | AG12: =A12&"|"&B12 -> 46282|BI261008
A13: 46283 | B13: BI261008 | C13: =INDEX(Entradas!$F$40:$F$46,MATCH(B13,Entradas!$A$40:$A$46,0)) -> 46303 | D13: =INDEX(Entradas!$G$40:$G$46,MATCH(B13,Entradas!$A$40:$A$46,0)) -> 10 | E13: =C13-A13 -> 20 | F13: =_xlfn.MAXIFS(Tasas!$B$5:$B$36,Tasas!$A$5:$A$36,F$4,Tasas!$B$5:$B$36,"<="&$A13) -> 46282 | G13: =_xlfn.MAXIFS(Tasas!$B$5:$B$36,Tasas!$A$5:$A$36,G$4,Tasas!$B$5:$B$36,"<="&$A13) -> 46282 | H13: =_xlfn.MAXIFS(Tasas!$B$5:$B$36,Tasas!$A$5:$A$36,H$4,Tasas!$B$5:$B$36,"<="&$A13) -> 46282 | I13: =_xlfn.MAXIFS(Tasas!$B$5:$B$36,Tasas!$A$5:$A$36,I$4,Tasas!$B$5:$B$36,"<="&$A13) -> 46282 | J13: =_xlfn.MAXIFS(Tasas!$B$5:$B$36,Tasas!$A$5:$A$36,J$4,Tasas!$B$5:$B$36,"<="&$A13) -> 46275 | K13: =SUMIFS(Tasas!$C$5:$C$36,Tasas!$A$5:$A$36,K$4,Tasas!$B$5:$B$36,F13) -> 6.25 | L13: =SUMIFS(Tasas!$C$5:$C$36,Tasas!$A$5:$A$36,L$4,Tasas!$B$5:$B$36,G13) -> 6.66 | M13: =SUMIFS(Tasas!$C$5:$C$36,Tasas!$A$5:$A$36,M$4,Tasas!$B$5:$B$36,H13) -> 6.9 | N13: =SUMIFS(Tasas!$C$5:$C$36,Tasas!$A$5:$A$36,N$4,Tasas!$B$5:$B$36,I13) -> 7.24 | O13: =SUMIFS(Tasas!$C$5:$C$36,Tasas!$A$5:$A$36,O$4,Tasas!$B$5:$B$36,J13) -> 7.94 | P13: =SUMIFS(Tasas!$E$5:$E$36,Tasas!$A$5:$A$36,P$4,Tasas!$B$5:$B$36,F13) -> 28 | Q13: =SUMIFS(Tasas!$E$5:$E$36,Tasas!$A$5:$A$36,Q$4,Tasas!$B$5:$B$36,G13) -> 91 | R13: =SUMIFS(Tasas!$E$5:$E$36,Tasas!$A$5:$A$36,R$4,Tasas!$B$5:$B$36,H13) -> 182 | S13: =SUMIFS(Tasas!$E$5:$E$36,Tasas!$A$5:$A$36,S$4,Tasas!$B$5:$B$36,I13) -> 363 | T13: =SUMIFS(Tasas!$E$5:$E$36,Tasas!$A$5:$A$36,T$4,Tasas!$B$5:$B$36,J13) -> 693 | U13: =IF($E13<=MIN($P13:$T13),MIN($P13:$T13),_xlfn.MAXIFS($P13:$T13,$P13:$T13,"<="&$E13)) -> 28 | V13: =IF($E13>=MAX($P13:$T13),MAX($P13:$T13),_xlfn.MINIFS($P13:$T13,$P13:$T13,">="&$E13)) -> 28 | W13: =INDEX($P$4:$T$4,MATCH(U13,$P13:$T13,0)) -> 28 | X13: =INDEX($P$4:$T$4,MATCH(V13,$P13:$T13,0)) -> 28 | Y13: =INDEX($F13:$J13,MATCH(U13,$P13:$T13,0)) -> 46282 | Z13: =INDEX($F13:$J13,MATCH(V13,$P13:$T13,0)) -> 46282 | AA13: =INDEX($K13:$O13,MATCH(U13,$P13:$T13,0)) -> 6.25 | AB13: =INDEX($K13:$O13,MATCH(V13,$P13:$T13,0)) -> 6.25 | AC13: =IF(E13<MIN($P13:$T13),"extremo inferior",IF(E13>MAX($P13:$T13),"extremo superior",IF(U13=V13,"nodo","interpolación"))) -> extremo inferior | AD13: =IF(U13=V13,AA13,AA13+(AB13-AA13)*(E13-U13)/(V13-U13)) -> 6.25 | AE13: =D13/(1+AD13/100*E13/360) -> 9.9653979 | AF13: =ROUND(AE13,7) -> 9.9653979 | AG13: =A13&"|"&B13 -> 46283|BI261008
A14: 46284 | B14: BI261008 | C14: =INDEX(Entradas!$F$40:$F$46,MATCH(B14,Entradas!$A$40:$A$46,0)) -> 46303 | D14: =INDEX(Entradas!$G$40:$G$46,MATCH(B14,Entradas!$A$40:$A$46,0)) -> 10 | E14: =C14-A14 -> 19 | F14: =_xlfn.MAXIFS(Tasas!$B$5:$B$36,Tasas!$A$5:$A$36,F$4,Tasas!$B$5:$B$36,"<="&$A14) -> 46282 | G14: =_xlfn.MAXIFS(Tasas!$B$5:$B$36,Tasas!$A$5:$A$36,G$4,Tasas!$B$5:$B$36,"<="&$A14) -> 46282 | H14: =_xlfn.MAXIFS(Tasas!$B$5:$B$36,Tasas!$A$5:$A$36,H$4,Tasas!$B$5:$B$36,"<="&$A14) -> 46282 | I14: =_xlfn.MAXIFS(Tasas!$B$5:$B$36,Tasas!$A$5:$A$36,I$4,Tasas!$B$5:$B$36,"<="&$A14) -> 46282 | J14: =_xlfn.MAXIFS(Tasas!$B$5:$B$36,Tasas!$A$5:$A$36,J$4,Tasas!$B$5:$B$36,"<="&$A14) -> 46275 | K14: =SUMIFS(Tasas!$C$5:$C$36,Tasas!$A$5:$A$36,K$4,Tasas!$B$5:$B$36,F14) -> 6.25 | L14: =SUMIFS(Tasas!$C$5:$C$36,Tasas!$A$5:$A$36,L$4,Tasas!$B$5:$B$36,G14) -> 6.66 | M14: =SUMIFS(Tasas!$C$5:$C$36,Tasas!$A$5:$A$36,M$4,Tasas!$B$5:$B$36,H14) -> 6.9 | N14: =SUMIFS(Tasas!$C$5:$C$36,Tasas!$A$5:$A$36,N$4,Tasas!$B$5:$B$36,I14) -> 7.24 | O14: =SUMIFS(Tasas!$C$5:$C$36,Tasas!$A$5:$A$36,O$4,Tasas!$B$5:$B$36,J14) -> 7.94 | P14: =SUMIFS(Tasas!$E$5:$E$36,Tasas!$A$5:$A$36,P$4,Tasas!$B$5:$B$36,F14) -> 28 | Q14: =SUMIFS(Tasas!$E$5:$E$36,Tasas!$A$5:$A$36,Q$4,Tasas!$B$5:$B$36,G14) -> 91 | R14: =SUMIFS(Tasas!$E$5:$E$36,Tasas!$A$5:$A$36,R$4,Tasas!$B$5:$B$36,H14) -> 182 | S14: =SUMIFS(Tasas!$E$5:$E$36,Tasas!$A$5:$A$36,S$4,Tasas!$B$5:$B$36,I14) -> 363 | T14: =SUMIFS(Tasas!$E$5:$E$36,Tasas!$A$5:$A$36,T$4,Tasas!$B$5:$B$36,J14) -> 693 | U14: =IF($E14<=MIN($P14:$T14),MIN($P14:$T14),_xlfn.MAXIFS($P14:$T14,$P14:$T14,"<="&$E14)) -> 28 | V14: =IF($E14>=MAX($P14:$T14),MAX($P14:$T14),_xlfn.MINIFS($P14:$T14,$P14:$T14,">="&$E14)) -> 28 | W14: =INDEX($P$4:$T$4,MATCH(U14,$P14:$T14,0)) -> 28 | X14: =INDEX($P$4:$T$4,MATCH(V14,$P14:$T14,0)) -> 28 | Y14: =INDEX($F14:$J14,MATCH(U14,$P14:$T14,0)) -> 46282 | Z14: =INDEX($F14:$J14,MATCH(V14,$P14:$T14,0)) -> 46282 | AA14: =INDEX($K14:$O14,MATCH(U14,$P14:$T14,0)) -> 6.25 | AB14: =INDEX($K14:$O14,MATCH(V14,$P14:$T14,0)) -> 6.25 | AC14: =IF(E14<MIN($P14:$T14),"extremo inferior",IF(E14>MAX($P14:$T14),"extremo superior",IF(U14=V14,"nodo","interpolación"))) -> extremo inferior | AD14: =IF(U14=V14,AA14,AA14+(AB14-AA14)*(E14-U14)/(V14-U14)) -> 6.25 | AE14: =D14/(1+AD14/100*E14/360) -> 9.9671223 | AF14: =ROUND(AE14,7) -> 9.9671223 | AG14: =A14&"|"&B14 -> 46284|BI261008
A15: 46285 | B15: BI261008 | C15: =INDEX(Entradas!$F$40:$F$46,MATCH(B15,Entradas!$A$40:$A$46,0)) -> 46303 | D15: =INDEX(Entradas!$G$40:$G$46,MATCH(B15,Entradas!$A$40:$A$46,0)) -> 10 | E15: =C15-A15 -> 18 | F15: =_xlfn.MAXIFS(Tasas!$B$5:$B$36,Tasas!$A$5:$A$36,F$4,Tasas!$B$5:$B$36,"<="&$A15) -> 46282 | G15: =_xlfn.MAXIFS(Tasas!$B$5:$B$36,Tasas!$A$5:$A$36,G$4,Tasas!$B$5:$B$36,"<="&$A15) -> 46282 | H15: =_xlfn.MAXIFS(Tasas!$B$5:$B$36,Tasas!$A$5:$A$36,H$4,Tasas!$B$5:$B$36,"<="&$A15) -> 46282 | I15: =_xlfn.MAXIFS(Tasas!$B$5:$B$36,Tasas!$A$5:$A$36,I$4,Tasas!$B$5:$B$36,"<="&$A15) -> 46282 | J15: =_xlfn.MAXIFS(Tasas!$B$5:$B$36,Tasas!$A$5:$A$36,J$4,Tasas!$B$5:$B$36,"<="&$A15) -> 46275 | K15: =SUMIFS(Tasas!$C$5:$C$36,Tasas!$A$5:$A$36,K$4,Tasas!$B$5:$B$36,F15) -> 6.25 | L15: =SUMIFS(Tasas!$C$5:$C$36,Tasas!$A$5:$A$36,L$4,Tasas!$B$5:$B$36,G15) -> 6.66 | M15: =SUMIFS(Tasas!$C$5:$C$36,Tasas!$A$5:$A$36,M$4,Tasas!$B$5:$B$36,H15) -> 6.9 | N15: =SUMIFS(Tasas!$C$5:$C$36,Tasas!$A$5:$A$36,N$4,Tasas!$B$5:$B$36,I15) -> 7.24 | O15: =SUMIFS(Tasas!$C$5:$C$36,Tasas!$A$5:$A$36,O$4,Tasas!$B$5:$B$36,J15) -> 7.94 | P15: =SUMIFS(Tasas!$E$5:$E$36,Tasas!$A$5:$A$36,P$4,Tasas!$B$5:$B$36,F15) -> 28 | Q15: =SUMIFS(Tasas!$E$5:$E$36,Tasas!$A$5:$A$36,Q$4,Tasas!$B$5:$B$36,G15) -> 91 | R15: =SUMIFS(Tasas!$E$5:$E$36,Tasas!$A$5:$A$36,R$4,Tasas!$B$5:$B$36,H15) -> 182 | S15: =SUMIFS(Tasas!$E$5:$E$36,Tasas!$A$5:$A$36,S$4,Tasas!$B$5:$B$36,I15) -> 363 | T15: =SUMIFS(Tasas!$E$5:$E$36,Tasas!$A$5:$A$36,T$4,Tasas!$B$5:$B$36,J15) -> 693 | U15: =IF($E15<=MIN($P15:$T15),MIN($P15:$T15),_xlfn.MAXIFS($P15:$T15,$P15:$T15,"<="&$E15)) -> 28 | V15: =IF($E15>=MAX($P15:$T15),MAX($P15:$T15),_xlfn.MINIFS($P15:$T15,$P15:$T15,">="&$E15)) -> 28 | W15: =INDEX($P$4:$T$4,MATCH(U15,$P15:$T15,0)) -> 28 | X15: =INDEX($P$4:$T$4,MATCH(V15,$P15:$T15,0)) -> 28 | Y15: =INDEX($F15:$J15,MATCH(U15,$P15:$T15,0)) -> 46282 | Z15: =INDEX($F15:$J15,MATCH(V15,$P15:$T15,0)) -> 46282 | AA15: =INDEX($K15:$O15,MATCH(U15,$P15:$T15,0)) -> 6.25 | AB15: =INDEX($K15:$O15,MATCH(V15,$P15:$T15,0)) -> 6.25 | AC15: =IF(E15<MIN($P15:$T15),"extremo inferior",IF(E15>MAX($P15:$T15),"extremo superior",IF(U15=V15,"nodo","interpolación"))) -> extremo inferior | AD15: =IF(U15=V15,AA15,AA15+(AB15-AA15)*(E15-U15)/(V15-U15)) -> 6.25 | AE15: =D15/(1+AD15/100*E15/360) -> 9.9688474 | AF15: =ROUND(AE15,7) -> 9.9688474 | AG15: =A15&"|"&B15 -> 46285|BI261008
A16: 46286 | B16: BI261008 | C16: =INDEX(Entradas!$F$40:$F$46,MATCH(B16,Entradas!$A$40:$A$46,0)) -> 46303 | D16: =INDEX(Entradas!$G$40:$G$46,MATCH(B16,Entradas!$A$40:$A$46,0)) -> 10 | E16: =C16-A16 -> 17 | F16: =_xlfn.MAXIFS(Tasas!$B$5:$B$36,Tasas!$A$5:$A$36,F$4,Tasas!$B$5:$B$36,"<="&$A16) -> 46282 | G16: =_xlfn.MAXIFS(Tasas!$B$5:$B$36,Tasas!$A$5:$A$36,G$4,Tasas!$B$5:$B$36,"<="&$A16) -> 46282 | H16: =_xlfn.MAXIFS(Tasas!$B$5:$B$36,Tasas!$A$5:$A$36,H$4,Tasas!$B$5:$B$36,"<="&$A16) -> 46282 | I16: =_xlfn.MAXIFS(Tasas!$B$5:$B$36,Tasas!$A$5:$A$36,I$4,Tasas!$B$5:$B$36,"<="&$A16) -> 46282 | J16: =_xlfn.MAXIFS(Tasas!$B$5:$B$36,Tasas!$A$5:$A$36,J$4,Tasas!$B$5:$B$36,"<="&$A16) -> 46275 | K16: =SUMIFS(Tasas!$C$5:$C$36,Tasas!$A$5:$A$36,K$4,Tasas!$B$5:$B$36,F16) -> 6.25 | L16: =SUMIFS(Tasas!$C$5:$C$36,Tasas!$A$5:$A$36,L$4,Tasas!$B$5:$B$36,G16) -> 6.66 | M16: =SUMIFS(Tasas!$C$5:$C$36,Tasas!$A$5:$A$36,M$4,Tasas!$B$5:$B$36,H16) -> 6.9 | N16: =SUMIFS(Tasas!$C$5:$C$36,Tasas!$A$5:$A$36,N$4,Tasas!$B$5:$B$36,I16) -> 7.24 | O16: =SUMIFS(Tasas!$C$5:$C$36,Tasas!$A$5:$A$36,O$4,Tasas!$B$5:$B$36,J16) -> 7.94 | P16: =SUMIFS(Tasas!$E$5:$E$36,Tasas!$A$5:$A$36,P$4,Tasas!$B$5:$B$36,F16) -> 28 | Q16: =SUMIFS(Tasas!$E$5:$E$36,Tasas!$A$5:$A$36,Q$4,Tasas!$B$5:$B$36,G16) -> 91 | R16: =SUMIFS(Tasas!$E$5:$E$36,Tasas!$A$5:$A$36,R$4,Tasas!$B$5:$B$36,H16) -> 182 | S16: =SUMIFS(Tasas!$E$5:$E$36,Tasas!$A$5:$A$36,S$4,Tasas!$B$5:$B$36,I16) -> 363 | T16: =SUMIFS(Tasas!$E$5:$E$36,Tasas!$A$5:$A$36,T$4,Tasas!$B$5:$B$36,J16) -> 693 | U16: =IF($E16<=MIN($P16:$T16),MIN($P16:$T16),_xlfn.MAXIFS($P16:$T16,$P16:$T16,"<="&$E16)) -> 28 | V16: =IF($E16>=MAX($P16:$T16),MAX($P16:$T16),_xlfn.MINIFS($P16:$T16,$P16:$T16,">="&$E16)) -> 28 | W16: =INDEX($P$4:$T$4,MATCH(U16,$P16:$T16,0)) -> 28 | X16: =INDEX($P$4:$T$4,MATCH(V16,$P16:$T16,0)) -> 28 | Y16: =INDEX($F16:$J16,MATCH(U16,$P16:$T16,0)) -> 46282 | Z16: =INDEX($F16:$J16,MATCH(V16,$P16:$T16,0)) -> 46282 | AA16: =INDEX($K16:$O16,MATCH(U16,$P16:$T16,0)) -> 6.25 | AB16: =INDEX($K16:$O16,MATCH(V16,$P16:$T16,0)) -> 6.25 | AC16: =IF(E16<MIN($P16:$T16),"extremo inferior",IF(E16>MAX($P16:$T16),"extremo superior",IF(U16=V16,"nodo","interpolación"))) -> extremo inferior | AD16: =IF(U16=V16,AA16,AA16+(AB16-AA16)*(E16-U16)/(V16-U16)) -> 6.25 | AE16: =D16/(1+AD16/100*E16/360) -> 9.970573 | AF16: =ROUND(AE16,7) -> 9.970573 | AG16: =A16&"|"&B16 -> 46286|BI261008
... A95: 46309 | B95: BI270318 | C95: =INDEX(Entradas!$F$40:$F$46,MATCH(B95,Entradas!$A$40:$A$46,0)) -> 46464 | D95: =INDEX(Entradas!$G$40:$G$46,MATCH(B95,Entradas!$A$40:$A$46,0)) -> 10 | E95: =C95-A95 -> 155 | F95: =_xlfn.MAXIFS(Tasas!$B$5:$B$36,Tasas!$A$5:$A$36,F$4,Tasas!$B$5:$B$36,"<="&$A95) -> 46303 | G95: =_xlfn.MAXIFS(Tasas!$B$5:$B$36,Tasas!$A$5:$A$36,G$4,Tasas!$B$5:$B$36,"<="&$A95) -> 46303 | H95: =_xlfn.MAXIFS(Tasas!$B$5:$B$36,Tasas!$A$5:$A$36,H$4,Tasas!$B$5:$B$36,"<="&$A95) -> 46303 | I95: =_xlfn.MAXIFS(Tasas!$B$5:$B$36,Tasas!$A$5:$A$36,I$4,Tasas!$B$5:$B$36,"<="&$A95) -> 46296 | J95: =_xlfn.MAXIFS(Tasas!$B$5:$B$36,Tasas!$A$5:$A$36,J$4,Tasas!$B$5:$B$36,"<="&$A95) -> 46303 | K95: =SUMIFS(Tasas!$C$5:$C$36,Tasas!$A$5:$A$36,K$4,Tasas!$B$5:$B$36,F95) -> 6.09 | L95: =SUMIFS(Tasas!$C$5:$C$36,Tasas!$A$5:$A$36,L$4,Tasas!$B$5:$B$36,G95) -> 6.78 | M95: =SUMIFS(Tasas!$C$5:$C$36,Tasas!$A$5:$A$36,M$4,Tasas!$B$5:$B$36,H95) -> 6.91 | N95: =SUMIFS(Tasas!$C$5:$C$36,Tasas!$A$5:$A$36,N$4,Tasas!$B$5:$B$36,I95) -> 7.44 | O95: =SUMIFS(Tasas!$C$5:$C$36,Tasas!$A$5:$A$36,O$4,Tasas!$B$5:$B$36,J95) -> 7.98 | P95: =SUMIFS(Tasas!$E$5:$E$36,Tasas!$A$5:$A$36,P$4,Tasas!$B$5:$B$36,F95) -> 28 | Q95: =SUMIFS(Tasas!$E$5:$E$36,Tasas!$A$5:$A$36,Q$4,Tasas!$B$5:$B$36,G95) -> 91 | R95: =SUMIFS(Tasas!$E$5:$E$36,Tasas!$A$5:$A$36,R$4,Tasas!$B$5:$B$36,H95) -> 175 | S95: =SUMIFS(Tasas!$E$5:$E$36,Tasas!$A$5:$A$36,S$4,Tasas!$B$5:$B$36,I95) -> 349 | T95: =SUMIFS(Tasas!$E$5:$E$36,Tasas!$A$5:$A$36,T$4,Tasas!$B$5:$B$36,J95) -> 721 | U95: =IF($E95<=MIN($P95:$T95),MIN($P95:$T95),_xlfn.MAXIFS($P95:$T95,$P95:$T95,"<="&$E95)) -> 91 | V95: =IF($E95>=MAX($P95:$T95),MAX($P95:$T95),_xlfn.MINIFS($P95:$T95,$P95:$T95,">="&$E95)) -> 175 | W95: =INDEX($P$4:$T$4,MATCH(U95,$P95:$T95,0)) -> 91 | X95: =INDEX($P$4:$T$4,MATCH(V95,$P95:$T95,0)) -> 182 | Y95: =INDEX($F95:$J95,MATCH(U95,$P95:$T95,0)) -> 46303 | Z95: =INDEX($F95:$J95,MATCH(V95,$P95:$T95,0)) -> 46303 | AA95: =INDEX($K95:$O95,MATCH(U95,$P95:$T95,0)) -> 6.78 | AB95: =INDEX($K95:$O95,MATCH(V95,$P95:$T95,0)) -> 6.91 | AC95: =IF(E95<MIN($P95:$T95),"extremo inferior",IF(E95>MAX($P95:$T95),"extremo superior",IF(U95=V95,"nodo","interpolación"))) -> interpolación | AD95: =IF(U95=V95,AA95,AA95+(AB95-AA95)*(E95-U95)/(V95-U95)) -> 6.8790476 | AE95: =D95/(1+AD95/100*E95/360) -> 9.7123388 | AF95: =ROUND(AE95,7) -> 9.7123388 | AG95: =A95&"|"&B95 -> 46309|BI270318

Sheet Valuación diaria
A1: Valuación diaria por portafolio, instrumento e intermediario (RF-06, RF-08, RF-26a, RF-26b)
A2: A–D: rótulos de la fila. Títulos: suma de cantidades con signo hasta la fecha, inclusive (corte inclusivo); 0 desde el vencimiento. Costo unitario: el del kardex tras la última transacción del par. Precio: último cierre igual o anterior, o P de la hoja CETES. Q: liquidación al valor nominal el día del vencimiento (retiro, sin ISR).
A4: fecha | B4: portafolio | C4: instrumento | D4: intermediario | E4: llave del par | F4: clase_activo | G4: vencimiento | H4: valor nominal | I4: títulos | J4: orden de la última transacción | K4: costo unitario promedio | L4: costo total | M4: fecha del precio | N4: precio usado (cierre o P) | O4: valor de mercado | P4: resultado no realizado | Q4: liquidación por vencimiento (retiro) | R4: ¿corte? | S4: llave de la fila
A5: 46275 | B5: Principal | C5: DEMOACC | D5: Casa A | E5: =B5&"|"&C5&"|"&D5 -> Principal|DEMOACC|Casa A | F5: =INDEX(Entradas!$C$40:$C$46,MATCH(C5,Entradas!$A$40:$A$46,0)) -> accion | G5: =IF(F5="cetes",INDEX(Entradas!$F$40:$F$46,MATCH(C5,Entradas!$A$40:$A$46,0)),"") | H5: =IF(F5="cetes",INDEX(Entradas!$G$40:$G$46,MATCH(C5,Entradas!$A$40:$A$46,0)),"") | I5: =IF(F5="cetes",IF(A5>=G5,0,SUMIFS(Transacciones!$N$5:$N$20,Transacciones!$T$5:$T$20,E5,Transacciones!$F$5:$F$20,"<="&A5)),SUMIFS(Transacciones!$N$5:$N$20,Transacciones!$T$5:$T$20,E5,Transacciones!$F$5:$F$20,"<="&A5)) -> 200 | J5: =_xlfn.MAXIFS(Transacciones!$U$5:$U$20,Transacciones!$T$5:$T$20,E5,Transacciones!$F$5:$F$20,"<="&A5) -> 46275001 | K5: =IF(I5=0,0,INDEX(Transacciones!$Z$5:$Z$20,MATCH(J5,Transacciones!$U$5:$U$20,0))) -> 100.23985 | L5: =I5*K5 -> 20047.97 | M5: =IF(F5="cetes",IF(COUNTIFS(CETES!$A$5:$A$95,A5,CETES!$B$5:$B$95,C5)=0,"",A5),SUMIFS(Precios!$K$5:$K$109,Precios!$I$5:$I$109,A5,Precios!$J$5:$J$109,C5)) -> 46275 | N5: =IF(F5="cetes",IF(COUNTIFS(CETES!$A$5:$A$95,A5,CETES!$B$5:$B$95,C5)=0,"",SUMIFS(CETES!$AF$5:$AF$95,CETES!$A$5:$A$95,A5,CETES!$B$5:$B$95,C5)),SUMIFS(Precios!$L$5:$L$109,Precios!$I$5:$I$109,A5,Precios!$J$5:$J$109,C5)) -> 100.2 | O5: =IF(I5=0,0,I5*N5) -> 20040 | P5: =O5-L5 -> -7.97 | Q5: =IF(F5="cetes",IF(A5=G5,SUMIFS(Transacciones!$N$5:$N$20,Transacciones!$T$5:$T$20,E5,Transacciones!$F$5:$F$20,"<"&A5)*H5,0),0) -> 0 | R5: =IF(COUNTIF(Entradas!$A$14:$A$17,A5)>0,"sí","") | S5: =A5&"|"&E5 -> 46275|Principal|DEMOACC|Casa A
A6: 46275 | B6: Principal | C6: DEMOACC | D6: Casa B | E6: =B6&"|"&C6&"|"&D6 -> Principal|DEMOACC|Casa B | F6: =INDEX(Entradas!$C$40:$C$46,MATCH(C6,Entradas!$A$40:$A$46,0)) -> accion | G6: =IF(F6="cetes",INDEX(Entradas!$F$40:$F$46,MATCH(C6,Entradas!$A$40:$A$46,0)),"") | H6: =IF(F6="cetes",INDEX(Entradas!$G$40:$G$46,MATCH(C6,Entradas!$A$40:$A$46,0)),"") | I6: =IF(F6="cetes",IF(A6>=G6,0,SUMIFS(Transacciones!$N$5:$N$20,Transacciones!$T$5:$T$20,E6,Transacciones!$F$5:$F$20,"<="&A6)),SUMIFS(Transacciones!$N$5:$N$20,Transacciones!$T$5:$T$20,E6,Transacciones!$F$5:$F$20,"<="&A6)) -> 0 | J6: =_xlfn.MAXIFS(Transacciones!$U$5:$U$20,Transacciones!$T$5:$T$20,E6,Transacciones!$F$5:$F$20,"<="&A6) -> 0 | K6: =IF(I6=0,0,INDEX(Transacciones!$Z$5:$Z$20,MATCH(J6,Transacciones!$U$5:$U$20,0))) -> 0 | L6: =I6*K6 -> 0 | M6: =IF(F6="cetes",IF(COUNTIFS(CETES!$A$5:$A$95,A6,CETES!$B$5:$B$95,C6)=0,"",A6),SUMIFS(Precios!$K$5:$K$109,Precios!$I$5:$I$109,A6,Precios!$J$5:$J$109,C6)) -> 46275 | N6: =IF(F6="cetes",IF(COUNTIFS(CETES!$A$5:$A$95,A6,CETES!$B$5:$B$95,C6)=0,"",SUMIFS(CETES!$AF$5:$AF$95,CETES!$A$5:$A$95,A6,CETES!$B$5:$B$95,C6)),SUMIFS(Precios!$L$5:$L$109,Precios!$I$5:$I$109,A6,Precios!$J$5:$J$109,C6)) -> 100.2 | O6: =IF(I6=0,0,I6*N6) -> 0 | P6: =O6-L6 -> 0 | Q6: =IF(F6="cetes",IF(A6=G6,SUMIFS(Transacciones!$N$5:$N$20,Transacciones!$T$5:$T$20,E6,Transacciones!$F$5:$F$20,"<"&A6)*H6,0),0) -> 0 | R6: =IF(COUNTIF(Entradas!$A$14:$A$17,A6)>0,"sí","") | S6: =A6&"|"&E6 -> 46275|Principal|DEMOACC|Casa B
A7: 46275 | B7: Principal | C7: DEMOETF | D7: Casa B | E7: =B7&"|"&C7&"|"&D7 -> Principal|DEMOETF|Casa B | F7: =INDEX(Entradas!$C$40:$C$46,MATCH(C7,Entradas!$A$40:$A$46,0)) -> etf | G7: =IF(F7="cetes",INDEX(Entradas!$F$40:$F$46,MATCH(C7,Entradas!$A$40:$A$46,0)),"") | H7: =IF(F7="cetes",INDEX(Entradas!$G$40:$G$46,MATCH(C7,Entradas!$A$40:$A$46,0)),"") | I7: =IF(F7="cetes",IF(A7>=G7,0,SUMIFS(Transacciones!$N$5:$N$20,Transacciones!$T$5:$T$20,E7,Transacciones!$F$5:$F$20,"<="&A7)),SUMIFS(Transacciones!$N$5:$N$20,Transacciones!$T$5:$T$20,E7,Transacciones!$F$5:$F$20,"<="&A7)) -> 100 | J7: =_xlfn.MAXIFS(Transacciones!$U$5:$U$20,Transacciones!$T$5:$T$20,E7,Transacciones!$F$5:$F$20,"<="&A7) -> 46275002 | K7: =IF(I7=0,0,INDEX(Transacciones!$Z$5:$Z$20,MATCH(J7,Transacciones!$U$5:$U$20,0))) -> 50.1951 | L7: =I7*K7 -> 5019.51 | M7: =IF(F7="cetes",IF(COUNTIFS(CETES!$A$5:$A$95,A7,CETES!$B$5:$B$95,C7)=0,"",A7),SUMIFS(Precios!$K$5:$K$109,Precios!$I$5:$I$109,A7,Precios!$J$5:$J$109,C7)) -> 46275 | N7: =IF(F7="cetes",IF(COUNTIFS(CETES!$A$5:$A$95,A7,CETES!$B$5:$B$95,C7)=0,"",SUMIFS(CETES!$AF$5:$AF$95,CETES!$A$5:$A$95,A7,CETES!$B$5:$B$95,C7)),SUMIFS(Precios!$L$5:$L$109,Precios!$I$5:$I$109,A7,Precios!$J$5:$J$109,C7)) -> 50.1 | O7: =IF(I7=0,0,I7*N7) -> 5010 | P7: =O7-L7 -> -9.51 | Q7: =IF(F7="cetes",IF(A7=G7,SUMIFS(Transacciones!$N$5:$N$20,Transacciones!$T$5:$T$20,E7,Transacciones!$F$5:$F$20,"<"&A7)*H7,0),0) -> 0 | R7: =IF(COUNTIF(Entradas!$A$14:$A$17,A7)>0,"sí","") | S7: =A7&"|"&E7 -> 46275|Principal|DEMOETF|Casa B
A8: 46275 | B8: Principal | C8: DEMOFIB | D8: Casa A | E8: =B8&"|"&C8&"|"&D8 -> Principal|DEMOFIB|Casa A | F8: =INDEX(Entradas!$C$40:$C$46,MATCH(C8,Entradas!$A$40:$A$46,0)) -> fibra | G8: =IF(F8="cetes",INDEX(Entradas!$F$40:$F$46,MATCH(C8,Entradas!$A$40:$A$46,0)),"") | H8: =IF(F8="cetes",INDEX(Entradas!$G$40:$G$46,MATCH(C8,Entradas!$A$40:$A$46,0)),"") | I8: =IF(F8="cetes",IF(A8>=G8,0,SUMIFS(Transacciones!$N$5:$N$20,Transacciones!$T$5:$T$20,E8,Transacciones!$F$5:$F$20,"<="&A8)),SUMIFS(Transacciones!$N$5:$N$20,Transacciones!$T$5:$T$20,E8,Transacciones!$F$5:$F$20,"<="&A8)) -> 0 | J8: =_xlfn.MAXIFS(Transacciones!$U$5:$U$20,Transacciones!$T$5:$T$20,E8,Transacciones!$F$5:$F$20,"<="&A8) -> 0 | K8: =IF(I8=0,0,INDEX(Transacciones!$Z$5:$Z$20,MATCH(J8,Transacciones!$U$5:$U$20,0))) -> 0 | L8: =I8*K8 -> 0 | M8: =IF(F8="cetes",IF(COUNTIFS(CETES!$A$5:$A$95,A8,CETES!$B$5:$B$95,C8)=0,"",A8),SUMIFS(Precios!$K$5:$K$109,Precios!$I$5:$I$109,A8,Precios!$J$5:$J$109,C8)) -> 46275 | N8: =IF(F8="cetes",IF(COUNTIFS(CETES!$A$5:$A$95,A8,CETES!$B$5:$B$95,C8)=0,"",SUMIFS(CETES!$AF$5:$AF$95,CETES!$A$5:$A$95,A8,CETES!$B$5:$B$95,C8)),SUMIFS(Precios!$L$5:$L$109,Precios!$I$5:$I$109,A8,Precios!$J$5:$J$109,C8)) -> 24.8 | O8: =IF(I8=0,0,I8*N8) -> 0 | P8: =O8-L8 -> 0 | Q8: =IF(F8="cetes",IF(A8=G8,SUMIFS(Transacciones!$N$5:$N$20,Transacciones!$T$5:$T$20,E8,Transacciones!$F$5:$F$20,"<"&A8)*H8,0),0) -> 0 | R8: =IF(COUNTIF(Entradas!$A$14:$A$17,A8)>0,"sí","") | S8: =A8&"|"&E8 -> 46275|Principal|DEMOFIB|Casa A
A9: 46275 | B9: Principal | C9: BI261008 | D9: Casa A | E9: =B9&"|"&C9&"|"&D9 -> Principal|BI261008|Casa A | F9: =INDEX(Entradas!$C$40:$C$46,MATCH(C9,Entradas!$A$40:$A$46,0)) -> cetes | G9: =IF(F9="cetes",INDEX(Entradas!$F$40:$F$46,MATCH(C9,Entradas!$A$40:$A$46,0)),"") -> 46303 | H9: =IF(F9="cetes",INDEX(Entradas!$G$40:$G$46,MATCH(C9,Entradas!$A$40:$A$46,0)),"") -> 10 | I9: =IF(F9="cetes",IF(A9>=G9,0,SUMIFS(Transacciones!$N$5:$N$20,Transacciones!$T$5:$T$20,E9,Transacciones!$F$5:$F$20,"<="&A9)),SUMIFS(Transacciones!$N$5:$N$20,Transacciones!$T$5:$T$20,E9,Transacciones!$F$5:$F$20,"<="&A9)) -> 1500 | J9: =_xlfn.MAXIFS(Transacciones!$U$5:$U$20,Transacciones!$T$5:$T$20,E9,Transacciones!$F$5:$F$20,"<="&A9) -> 46275003 | K9: =IF(I9=0,0,INDEX(Transacciones!$Z$5:$Z$20,MATCH(J9,Transacciones!$U$5:$U$20,0))) -> 9.951624 | L9: =I9*K9 -> 14927.436 | M9: =IF(F9="cetes",IF(COUNTIFS(CETES!$A$5:$A$95,A9,CETES!$B$5:$B$95,C9)=0,"",A9),SUMIFS(Precios!$K$5:$K$109,Precios!$I$5:$I$109,A9,Precios!$J$5:$J$109,C9)) -> 46275 | N9: =IF(F9="cetes",IF(COUNTIFS(CETES!$A$5:$A$95,A9,CETES!$B$5:$B$95,C9)=0,"",SUMIFS(CETES!$AF$5:$AF$95,CETES!$A$5:$A$95,A9,CETES!$B$5:$B$95,C9)),SUMIFS(Precios!$L$5:$L$109,Precios!$I$5:$I$109,A9,Precios!$J$5:$J$109,C9)) -> 9.951624 | O9: =IF(I9=0,0,I9*N9) -> 14927.436 | P9: =O9-L9 -> 0 | Q9: =IF(F9="cetes",IF(A9=G9,SUMIFS(Transacciones!$N$5:$N$20,Transacciones!$T$5:$T$20,E9,Transacciones!$F$5:$F$20,"<"&A9)*H9,0),0) -> 0 | R9: =IF(COUNTIF(Entradas!$A$14:$A$17,A9)>0,"sí","") | S9: =A9&"|"&E9 -> 46275|Principal|BI261008|Casa A
A10: 46275 | B10: Principal | C10: BI261008 | D10: Casa B | E10: =B10&"|"&C10&"|"&D10 -> Principal|BI261008|Casa B | F10: =INDEX(Entradas!$C$40:$C$46,MATCH(C10,Entradas!$A$40:$A$46,0)) -> cetes | G10: =IF(F10="cetes",INDEX(Entradas!$F$40:$F$46,MATCH(C10,Entradas!$A$40:$A$46,0)),"") -> 46303 | H10: =IF(F10="cetes",INDEX(Entradas!$G$40:$G$46,MATCH(C10,Entradas!$A$40:$A$46,0)),"") -> 10 | I10: =IF(F10="cetes",IF(A10>=G10,0,SUMIFS(Transacciones!$N$5:$N$20,Transacciones!$T$5:$T$20,E10,Transacciones!$F$5:$F$20,"<="&A10)),SUMIFS(Transacciones!$N$5:$N$20,Transacciones!$T$5:$T$20,E10,Transacciones!$F$5:$F$20,"<="&A10)) -> 1000 | J10: =_xlfn.MAXIFS(Transacciones!$U$5:$U$20,Transacciones!$T$5:$T$20,E10,Transacciones!$F$5:$F$20,"<="&A10) -> 46275004 | K10: =IF(I10=0,0,INDEX(Transacciones!$Z$5:$Z$20,MATCH(J10,Transacciones!$U$5:$U$20,0))) -> 9.951624 | L10: =I10*K10 -> 9951.624 | M10: =IF(F10="cetes",IF(COUNTIFS(CETES!$A$5:$A$95,A10,CETES!$B$5:$B$95,C10)=0,"",A10),SUMIFS(Precios!$K$5:$K$109,Precios!$I$5:$I$109,A10,Precios!$J$5:$J$109,C10)) -> 46275 | N10: =IF(F10="cetes",IF(COUNTIFS(CETES!$A$5:$A$95,A10,CETES!$B$5:$B$95,C10)=0,"",SUMIFS(CETES!$AF$5:$AF$95,CETES!$A$5:$A$95,A10,CETES!$B$5:$B$95,C10)),SUMIFS(Precios!$L$5:$L$109,Precios!$I$5:$I$109,A10,Precios!$J$5:$J$109,C10)) -> 9.951624 | O10: =IF(I10=0,0,I10*N10) -> 9951.624 | P10: =O10-L10 -> 0 | Q10: =IF(F10="cetes",IF(A10=G10,SUMIFS(Transacciones!$N$5:$N$20,Transacciones!$T$5:$T$20,E10,Transacciones!$F$5:$F$20,"<"&A10)*H10,0),0) -> 0 | R10: =IF(COUNTIF(Entradas!$A$14:$A$17,A10)>0,"sí","") | S10: =A10&"|"&E10 -> 46275|Principal|BI261008|Casa B
A11: 46275 | B11: Principal | C11: BI261105 | D11: Casa B | E11: =B11&"|"&C11&"|"&D11 -> Principal|BI261105|Casa B | F11: =INDEX(Entradas!$C$40:$C$46,MATCH(C11,Entradas!$A$40:$A$46,0)) -> cetes | G11: =IF(F11="cetes",INDEX(Entradas!$F$40:$F$46,MATCH(C11,Entradas!$A$40:$A$46,0)),"") -> 46331 | H11: =IF(F11="cetes",INDEX(Entradas!$G$40:$G$46,MATCH(C11,Entradas!$A$40:$A$46,0)),"") -> 10 | I11: =IF(F11="cetes",IF(A11>=G11,0,SUMIFS(Transacciones!$N$5:$N$20,Transacciones!$T$5:$T$20,E11,Transacciones!$F$5:$F$20,"<="&A11)),SUMIFS(Transacciones!$N$5:$N$20,Transacciones!$T$5:$T$20,E11,Transacciones!$F$5:$F$20,"<="&A11)) -> 0 | J11: =_xlfn.MAXIFS(Transacciones!$U$5:$U$20,Transacciones!$T$5:$T$20,E11,Transacciones!$F$5:$F$20,"<="&A11) -> 0 | K11: =IF(I11=0,0,INDEX(Transacciones!$Z$5:$Z$20,MATCH(J11,Transacciones!$U$5:$U$20,0))) -> 0 | L11: =I11*K11 -> 0 | M11: =IF(F11="cetes",IF(COUNTIFS(CETES!$A$5:$A$95,A11,CETES!$B$5:$B$95,C11)=0,"",A11),SUMIFS(Precios!$K$5:$K$109,Precios!$I$5:$I$109,A11,Precios!$J$5:$J$109,C11)) | N11: =IF(F11="cetes",IF(COUNTIFS(CETES!$A$5:$A$95,A11,CETES!$B$5:$B$95,C11)=0,"",SUMIFS(CETES!$AF$5:$AF$95,CETES!$A$5:$A$95,A11,CETES!$B$5:$B$95,C11)),SUMIFS(Precios!$L$5:$L$109,Precios!$I$5:$I$109,A11,Precios!$J$5:$J$109,C11)) | O11: =IF(I11=0,0,I11*N11) -> 0 | P11: =O11-L11 -> 0 | Q11: =IF(F11="cetes",IF(A11=G11,SUMIFS(Transacciones!$N$5:$N$20,Transacciones!$T$5:$T$20,E11,Transacciones!$F$5:$F$20,"<"&A11)*H11,0),0) -> 0 | R11: =IF(COUNTIF(Entradas!$A$14:$A$17,A11)>0,"sí","") | S11: =A11&"|"&E11 -> 46275|Principal|BI261105|Casa B
A12: 46275 | B12: Principal | C12: BI261217 | D12: Casa A | E12: =B12&"|"&C12&"|"&D12 -> Principal|BI261217|Casa A | F12: =INDEX(Entradas!$C$40:$C$46,MATCH(C12,Entradas!$A$40:$A$46,0)) -> cetes | G12: =IF(F12="cetes",INDEX(Entradas!$F$40:$F$46,MATCH(C12,Entradas!$A$40:$A$46,0)),"") -> 46373 | H12: =IF(F12="cetes",INDEX(Entradas!$G$40:$G$46,MATCH(C12,Entradas!$A$40:$A$46,0)),"") -> 10 | I12: =IF(F12="cetes",IF(A12>=G12,0,SUMIFS(Transacciones!$N$5:$N$20,Transacciones!$T$5:$T$20,E12,Transacciones!$F$5:$F$20,"<="&A12)),SUMIFS(Transacciones!$N$5:$N$20,Transacciones!$T$5:$T$20,E12,Transacciones!$F$5:$F$20,"<="&A12)) -> 0 | J12: =_xlfn.MAXIFS(Transacciones!$U$5:$U$20,Transacciones!$T$5:$T$20,E12,Transacciones!$F$5:$F$20,"<="&A12) -> 0 | K12: =IF(I12=0,0,INDEX(Transacciones!$Z$5:$Z$20,MATCH(J12,Transacciones!$U$5:$U$20,0))) -> 0 | L12: =I12*K12 -> 0 | M12: =IF(F12="cetes",IF(COUNTIFS(CETES!$A$5:$A$95,A12,CETES!$B$5:$B$95,C12)=0,"",A12),SUMIFS(Precios!$K$5:$K$109,Precios!$I$5:$I$109,A12,Precios!$J$5:$J$109,C12)) | N12: =IF(F12="cetes",IF(COUNTIFS(CETES!$A$5:$A$95,A12,CETES!$B$5:$B$95,C12)=0,"",SUMIFS(CETES!$AF$5:$AF$95,CETES!$A$5:$A$95,A12,CETES!$B$5:$B$95,C12)),SUMIFS(Precios!$L$5:$L$109,Precios!$I$5:$I$109,A12,Precios!$J$5:$J$109,C12)) | O12: =IF(I12=0,0,I12*N12) -> 0 | P12: =O12-L12 -> 0 | Q12: =IF(F12="cetes",IF(A12=G12,SUMIFS(Transacciones!$N$5:$N$20,Transacciones!$T$5:$T$20,E12,Transacciones!$F$5:$F$20,"<"&A12)*H12,0),0) -> 0 | R12: =IF(COUNTIF(Entradas!$A$14:$A$17,A12)>0,"sí","") | S12: =A12&"|"&E12 -> 46275|Principal|BI261217|Casa A
A13: 46275 | B13: Principal | C13: BI270318 | D13: Casa B | E13: =B13&"|"&C13&"|"&D13 -> Principal|BI270318|Casa B | F13: =INDEX(Entradas!$C$40:$C$46,MATCH(C13,Entradas!$A$40:$A$46,0)) -> cetes | G13: =IF(F13="cetes",INDEX(Entradas!$F$40:$F$46,MATCH(C13,Entradas!$A$40:$A$46,0)),"") -> 46464 | H13: =IF(F13="cetes",INDEX(Entradas!$G$40:$G$46,MATCH(C13,Entradas!$A$40:$A$46,0)),"") -> 10 | I13: =IF(F13="cetes",IF(A13>=G13,0,SUMIFS(Transacciones!$N$5:$N$20,Transacciones!$T$5:$T$20,E13,Transacciones!$F$5:$F$20,"<="&A13)),SUMIFS(Transacciones!$N$5:$N$20,Transacciones!$T$5:$T$20,E13,Transacciones!$F$5:$F$20,"<="&A13)) -> 0 | J13: =_xlfn.MAXIFS(Transacciones!$U$5:$U$20,Transacciones!$T$5:$T$20,E13,Transacciones!$F$5:$F$20,"<="&A13) -> 0 | K13: =IF(I13=0,0,INDEX(Transacciones!$Z$5:$Z$20,MATCH(J13,Transacciones!$U$5:$U$20,0))) -> 0 | L13: =I13*K13 -> 0 | M13: =IF(F13="cetes",IF(COUNTIFS(CETES!$A$5:$A$95,A13,CETES!$B$5:$B$95,C13)=0,"",A13),SUMIFS(Precios!$K$5:$K$109,Precios!$I$5:$I$109,A13,Precios!$J$5:$J$109,C13)) | N13: =IF(F13="cetes",IF(COUNTIFS(CETES!$A$5:$A$95,A13,CETES!$B$5:$B$95,C13)=0,"",SUMIFS(CETES!$AF$5:$AF$95,CETES!$A$5:$A$95,A13,CETES!$B$5:$B$95,C13)),SUMIFS(Precios!$L$5:$L$109,Precios!$I$5:$I$109,A13,Precios!$J$5:$J$109,C13)) | O13: =IF(I13=0,0,I13*N13) -> 0 | P13: =O13-L13 -> 0 | Q13: =IF(F13="cetes",IF(A13=G13,SUMIFS(Transacciones!$N$5:$N$20,Transacciones!$T$5:$T$20,E13,Transacciones!$F$5:$F$20,"<"&A13)*H13,0),0) -> 0 | R13: =IF(COUNTIF(Entradas!$A$14:$A$17,A13)>0,"sí","") | S13: =A13&"|"&E13 -> 46275|Principal|BI270318|Casa B
A14: 46275 | B14: Secundario | C14: DEMOACC | D14: Casa A | E14: =B14&"|"&C14&"|"&D14 -> Secundario|DEMOACC|Casa A | F14: =INDEX(Entradas!$C$40:$C$46,MATCH(C14,Entradas!$A$40:$A$46,0)) -> accion | G14: =IF(F14="cetes",INDEX(Entradas!$F$40:$F$46,MATCH(C14,Entradas!$A$40:$A$46,0)),"") | H14: =IF(F14="cetes",INDEX(Entradas!$G$40:$G$46,MATCH(C14,Entradas!$A$40:$A$46,0)),"") | I14: =IF(F14="cetes",IF(A14>=G14,0,SUMIFS(Transacciones!$N$5:$N$20,Transacciones!$T$5:$T$20,E14,Transacciones!$F$5:$F$20,"<="&A14)),SUMIFS(Transacciones!$N$5:$N$20,Transacciones!$T$5:$T$20,E14,Transacciones!$F$5:$F$20,"<="&A14)) -> 0 | J14: =_xlfn.MAXIFS(Transacciones!$U$5:$U$20,Transacciones!$T$5:$T$20,E14,Transacciones!$F$5:$F$20,"<="&A14) -> 0 | K14: =IF(I14=0,0,INDEX(Transacciones!$Z$5:$Z$20,MATCH(J14,Transacciones!$U$5:$U$20,0))) -> 0 | L14: =I14*K14 -> 0 | M14: =IF(F14="cetes",IF(COUNTIFS(CETES!$A$5:$A$95,A14,CETES!$B$5:$B$95,C14)=0,"",A14),SUMIFS(Precios!$K$5:$K$109,Precios!$I$5:$I$109,A14,Precios!$J$5:$J$109,C14)) -> 46275 | N14: =IF(F14="cetes",IF(COUNTIFS(CETES!$A$5:$A$95,A14,CETES!$B$5:$B$95,C14)=0,"",SUMIFS(CETES!$AF$5:$AF$95,CETES!$A$5:$A$95,A14,CETES!$B$5:$B$95,C14)),SUMIFS(Precios!$L$5:$L$109,Precios!$I$5:$I$109,A14,Precios!$J$5:$J$109,C14)) -> 100.2 | O14: =IF(I14=0,0,I14*N14) -> 0 | P14: =O14-L14 -> 0 | Q14: =IF(F14="cetes",IF(A14=G14,SUMIFS(Transacciones!$N$5:$N$20,Transacciones!$T$5:$T$20,E14,Transacciones!$F$5:$F$20,"<"&A14)*H14,0),0) -> 0 | R14: =IF(COUNTIF(Entradas!$A$14:$A$17,A14)>0,"sí","") | S14: =A14&"|"&E14 -> 46275|Secundario|DEMOACC|Casa A
A15: 46276 | B15: Principal | C15: DEMOACC | D15: Casa A | E15: =B15&"|"&C15&"|"&D15 -> Principal|DEMOACC|Casa A | F15: =INDEX(Entradas!$C$40:$C$46,MATCH(C15,Entradas!$A$40:$A$46,0)) -> accion | G15: =IF(F15="cetes",INDEX(Entradas!$F$40:$F$46,MATCH(C15,Entradas!$A$40:$A$46,0)),"") | H15: =IF(F15="cetes",INDEX(Entradas!$G$40:$G$46,MATCH(C15,Entradas!$A$40:$A$46,0)),"") | I15: =IF(F15="cetes",IF(A15>=G15,0,SUMIFS(Transacciones!$N$5:$N$20,Transacciones!$T$5:$T$20,E15,Transacciones!$F$5:$F$20,"<="&A15)),SUMIFS(Transacciones!$N$5:$N$20,Transacciones!$T$5:$T$20,E15,Transacciones!$F$5:$F$20,"<="&A15)) -> 200 | J15: =_xlfn.MAXIFS(Transacciones!$U$5:$U$20,Transacciones!$T$5:$T$20,E15,Transacciones!$F$5:$F$20,"<="&A15) -> 46275001 | K15: =IF(I15=0,0,INDEX(Transacciones!$Z$5:$Z$20,MATCH(J15,Transacciones!$U$5:$U$20,0))) -> 100.23985 | L15: =I15*K15 -> 20047.97 | M15: =IF(F15="cetes",IF(COUNTIFS(CETES!$A$5:$A$95,A15,CETES!$B$5:$B$95,C15)=0,"",A15),SUMIFS(Precios!$K$5:$K$109,Precios!$I$5:$I$109,A15,Precios!$J$5:$J$109,C15)) -> 46276 | N15: =IF(F15="cetes",IF(COUNTIFS(CETES!$A$5:$A$95,A15,CETES!$B$5:$B$95,C15)=0,"",SUMIFS(CETES!$AF$5:$AF$95,CETES!$A$5:$A$95,A15,CETES!$B$5:$B$95,C15)),SUMIFS(Precios!$L$5:$L$109,Precios!$I$5:$I$109,A15,Precios!$J$5:$J$109,C15)) -> 101.85 | O15: =IF(I15=0,0,I15*N15) -> 20370 | P15: =O15-L15 -> 322.03 | Q15: =IF(F15="cetes",IF(A15=G15,SUMIFS(Transacciones!$N$5:$N$20,Transacciones!$T$5:$T$20,E15,Transacciones!$F$5:$F$20,"<"&A15)*H15,0),0) -> 0 | R15: =IF(COUNTIF(Entradas!$A$14:$A$17,A15)>0,"sí","") | S15: =A15&"|"&E15 -> 46276|Principal|DEMOACC|Casa A
A16: 46276 | B16: Principal | C16: DEMOACC | D16: Casa B | E16: =B16&"|"&C16&"|"&D16 -> Principal|DEMOACC|Casa B | F16: =INDEX(Entradas!$C$40:$C$46,MATCH(C16,Entradas!$A$40:$A$46,0)) -> accion | G16: =IF(F16="cetes",INDEX(Entradas!$F$40:$F$46,MATCH(C16,Entradas!$A$40:$A$46,0)),"") | H16: =IF(F16="cetes",INDEX(Entradas!$G$40:$G$46,MATCH(C16,Entradas!$A$40:$A$46,0)),"") | I16: =IF(F16="cetes",IF(A16>=G16,0,SUMIFS(Transacciones!$N$5:$N$20,Transacciones!$T$5:$T$20,E16,Transacciones!$F$5:$F$20,"<="&A16)),SUMIFS(Transacciones!$N$5:$N$20,Transacciones!$T$5:$T$20,E16,Transacciones!$F$5:$F$20,"<="&A16)) -> 0 | J16: =_xlfn.MAXIFS(Transacciones!$U$5:$U$20,Transacciones!$T$5:$T$20,E16,Transacciones!$F$5:$F$20,"<="&A16) -> 0 | K16: =IF(I16=0,0,INDEX(Transacciones!$Z$5:$Z$20,MATCH(J16,Transacciones!$U$5:$U$20,0))) -> 0 | L16: =I16*K16 -> 0 | M16: =IF(F16="cetes",IF(COUNTIFS(CETES!$A$5:$A$95,A16,CETES!$B$5:$B$95,C16)=0,"",A16),SUMIFS(Precios!$K$5:$K$109,Precios!$I$5:$I$109,A16,Precios!$J$5:$J$109,C16)) -> 46276 | N16: =IF(F16="cetes",IF(COUNTIFS(CETES!$A$5:$A$95,A16,CETES!$B$5:$B$95,C16)=0,"",SUMIFS(CETES!$AF$5:$AF$95,CETES!$A$5:$A$95,A16,CETES!$B$5:$B$95,C16)),SUMIFS(Precios!$L$5:$L$109,Precios!$I$5:$I$109,A16,Precios!$J$5:$J$109,C16)) -> 101.85 | O16: =IF(I16=0,0,I16*N16) -> 0 | P16: =O16-L16 -> 0 | Q16: =IF(F16="cetes",IF(A16=G16,SUMIFS(Transacciones!$N$5:$N$20,Transacciones!$T$5:$T$20,E16,Transacciones!$F$5:$F$20,"<"&A16)*H16,0),0) -> 0 | R16: =IF(COUNTIF(Entradas!$A$14:$A$17,A16)>0,"sí","") | S16: =A16&"|"&E16 -> 46276|Principal|DEMOACC|Casa B
... A354: 46309 | B354: Secundario | C354: DEMOACC | D354: Casa A | E354: =B354&"|"&C354&"|"&D354 -> Secundario|DEMOACC|Casa A | F354: =INDEX(Entradas!$C$40:$C$46,MATCH(C354,Entradas!$A$40:$A$46,0)) -> accion | G354: =IF(F354="cetes",INDEX(Entradas!$F$40:$F$46,MATCH(C354,Entradas!$A$40:$A$46,0)),"") | H354: =IF(F354="cetes",INDEX(Entradas!$G$40:$G$46,MATCH(C354,Entradas!$A$40:$A$46,0)),"") | I354: =IF(F354="cetes",IF(A354>=G354,0,SUMIFS(Transacciones!$N$5:$N$20,Transacciones!$T$5:$T$20,E354,Transacciones!$F$5:$F$20,"<="&A354)),SUMIFS(Transacciones!$N$5:$N$20,Transacciones!$T$5:$T$20,E354,Transacciones!$F$5:$F$20,"<="&A354)) -> 150 | J354: =_xlfn.MAXIFS(Transacciones!$U$5:$U$20,Transacciones!$T$5:$T$20,E354,Transacciones!$F$5:$F$20,"<="&A354) -> 46279007 | K354: =IF(I354=0,0,INDEX(Transacciones!$Z$5:$Z$20,MATCH(J354,Transacciones!$U$5:$U$20,0))) -> 103.90047 | L354: =I354*K354 -> 15585.07 | M354: =IF(F354="cetes",IF(COUNTIFS(CETES!$A$5:$A$95,A354,CETES!$B$5:$B$95,C354)=0,"",A354),SUMIFS(Precios!$K$5:$K$109,Precios!$I$5:$I$109,A354,Precios!$J$5:$J$109,C354)) -> 46309 | N354: =IF(F354="cetes",IF(COUNTIFS(CETES!$A$5:$A$95,A354,CETES!$B$5:$B$95,C354)=0,"",SUMIFS(CETES!$AF$5:$AF$95,CETES!$A$5:$A$95,A354,CETES!$B$5:$B$95,C354)),SUMIFS(Precios!$L$5:$L$109,Precios!$I$5:$I$109,A354,Precios!$J$5:$J$109,C354)) -> 111.05 | O354: =IF(I354=0,0,I354*N354) -> 16657.5 | P354: =O354-L354 -> 1072.43 | Q354: =IF(F354="cetes",IF(A354=G354,SUMIFS(Transacciones!$N$5:$N$20,Transacciones!$T$5:$T$20,E354,Transacciones!$F$5:$F$20,"<"&A354)*H354,0),0) -> 0 | R354: =IF(COUNTIF(Entradas!$A$14:$A$17,A354)>0,"sí","") -> sí | S354: =A354&"|"&E354 -> 46309|Secundario|DEMOACC|Casa A

Sheet Posiciones
A1: Posiciones en cada fecha de corte (RF-06, RF-08, RF-26b, RF-31)
A2: Tres tablas: por intermediario (cada par portafolio-instrumento-intermediario), consolidado por instrumento (suma de intermediarios) y totales del portafolio, comparados con V(t) de la Serie. Se incluyen los renglones en cero.
A3: Por intermediario
A4: fecha_corte | B4: portafolio | C4: instrumento | D4: intermediario | E4: fila en Valuación diaria | F4: ¿tiene transacciones al corte? | G4: títulos | H4: costo unitario promedio | I4: costo total | J4: precio usado | K4: fecha del precio (cierre usado) | L4: ¿hay valuación de CETES? | M4: d | N4: r (% anual) | O4: colocación inferior | P4: colocación superior | Q4: valor de mercado | R4: resultado no realizado
A5: 46278 | B5: Principal | C5: DEMOACC | D5: Casa A | E5: =MATCH(A5&"|"&B5&"|"&C5&"|"&D5,'Valuación diaria'!$S$5:$S$354,0) -> 31 | F5: =IF(COUNTIFS(Transacciones!$T$5:$T$20,B5&"|"&C5&"|"&D5,Transacciones!$F$5:$F$20,"<="&A5)>0,"sí","no") -> sí | G5: =INDEX('Valuación diaria'!$I$5:$I$354,E5) -> 200 | H5: =INDEX('Valuación diaria'!$K$5:$K$354,E5) -> 100.23985 | I5: =INDEX('Valuación diaria'!$L$5:$L$354,E5) -> 20047.97 | J5: =INDEX('Valuación diaria'!$N$5:$N$354,E5) -> 101.85 | K5: =INDEX('Valuación diaria'!$M$5:$M$354,E5) -> 46276 | L5: =COUNTIFS(CETES!$A$5:$A$95,A5,CETES!$B$5:$B$95,C5) -> 0 | M5: =IF(L5=0,"",INDEX(CETES!$E$5:$E$95,MATCH(A5&"|"&C5,CETES!$AG$5:$AG$95,0))) | N5: =IF(L5=0,"",INDEX(CETES!$AD$5:$AD$95,MATCH(A5&"|"&C5,CETES!$AG$5:$AG$95,0))) | O5: =IF(L5=0,"",INDEX(CETES!$Y$5:$Y$95,MATCH(A5&"|"&C5,CETES!$AG$5:$AG$95,0))) | P5: =IF(L5=0,"",INDEX(CETES!$Z$5:$Z$95,MATCH(A5&"|"&C5,CETES!$AG$5:$AG$95,0))) | Q5: =INDEX('Valuación diaria'!$O$5:$O$354,E5) -> 20370 | R5: =INDEX('Valuación diaria'!$P$5:$P$354,E5) -> 322.03
A6: 46278 | B6: Principal | C6: DEMOACC | D6: Casa B | E6: =MATCH(A6&"|"&B6&"|"&C6&"|"&D6,'Valuación diaria'!$S$5:$S$354,0) -> 32 | F6: =IF(COUNTIFS(Transacciones!$T$5:$T$20,B6&"|"&C6&"|"&D6,Transacciones!$F$5:$F$20,"<="&A6)>0,"sí","no") -> no | G6: =INDEX('Valuación diaria'!$I$5:$I$354,E6) -> 0 | H6: =INDEX('Valuación diaria'!$K$5:$K$354,E6) -> 0 | I6: =INDEX('Valuación diaria'!$L$5:$L$354,E6) -> 0 | J6: =INDEX('Valuación diaria'!$N$5:$N$354,E6) -> 101.85 | K6: =INDEX('Valuación diaria'!$M$5:$M$354,E6) -> 46276 | L6: =COUNTIFS(CETES!$A$5:$A$95,A6,CETES!$B$5:$B$95,C6) -> 0 | M6: =IF(L6=0,"",INDEX(CETES!$E$5:$E$95,MATCH(A6&"|"&C6,CETES!$AG$5:$AG$95,0))) | N6: =IF(L6=0,"",INDEX(CETES!$AD$5:$AD$95,MATCH(A6&"|"&C6,CETES!$AG$5:$AG$95,0))) | O6: =IF(L6=0,"",INDEX(CETES!$Y$5:$Y$95,MATCH(A6&"|"&C6,CETES!$AG$5:$AG$95,0))) | P6: =IF(L6=0,"",INDEX(CETES!$Z$5:$Z$95,MATCH(A6&"|"&C6,CETES!$AG$5:$AG$95,0))) | Q6: =INDEX('Valuación diaria'!$O$5:$O$354,E6) -> 0 | R6: =INDEX('Valuación diaria'!$P$5:$P$354,E6) -> 0
A7: 46278 | B7: Principal | C7: DEMOETF | D7: Casa B | E7: =MATCH(A7&"|"&B7&"|"&C7&"|"&D7,'Valuación diaria'!$S$5:$S$354,0) -> 33 | F7: =IF(COUNTIFS(Transacciones!$T$5:$T$20,B7&"|"&C7&"|"&D7,Transacciones!$F$5:$F$20,"<="&A7)>0,"sí","no") -> sí | G7: =INDEX('Valuación diaria'!$I$5:$I$354,E7) -> 100 | H7: =INDEX('Valuación diaria'!$K$5:$K$354,E7) -> 50.1951 | I7: =INDEX('Valuación diaria'!$L$5:$L$354,E7) -> 5019.51 | J7: =INDEX('Valuación diaria'!$N$5:$N$354,E7) -> 50.62 | K7: =INDEX('Valuación diaria'!$M$5:$M$354,E7) -> 46276 | L7: =COUNTIFS(CETES!$A$5:$A$95,A7,CETES!$B$5:$B$95,C7) -> 0 | M7: =IF(L7=0,"",INDEX(CETES!$E$5:$E$95,MATCH(A7&"|"&C7,CETES!$AG$5:$AG$95,0))) | N7: =IF(L7=0,"",INDEX(CETES!$AD$5:$AD$95,MATCH(A7&"|"&C7,CETES!$AG$5:$AG$95,0))) | O7: =IF(L7=0,"",INDEX(CETES!$Y$5:$Y$95,MATCH(A7&"|"&C7,CETES!$AG$5:$AG$95,0))) | P7: =IF(L7=0,"",INDEX(CETES!$Z$5:$Z$95,MATCH(A7&"|"&C7,CETES!$AG$5:$AG$95,0))) | Q7: =INDEX('Valuación diaria'!$O$5:$O$354,E7) -> 5062 | R7: =INDEX('Valuación diaria'!$P$5:$P$354,E7) -> 42.49
A8: 46278 | B8: Principal | C8: DEMOFIB | D8: Casa A | E8: =MATCH(A8&"|"&B8&"|"&C8&"|"&D8,'Valuación diaria'!$S$5:$S$354,0) -> 34 | F8: =IF(COUNTIFS(Transacciones!$T$5:$T$20,B8&"|"&C8&"|"&D8,Transacciones!$F$5:$F$20,"<="&A8)>0,"sí","no") -> sí | G8: =INDEX('Valuación diaria'!$I$5:$I$354,E8) -> 400 | H8: =INDEX('Valuación diaria'!$K$5:$K$354,E8) -> 25.05495 | I8: =INDEX('Valuación diaria'!$L$5:$L$354,E8) -> 10021.98 | J8: =INDEX('Valuación diaria'!$N$5:$N$354,E8) -> 25.015 | K8: =INDEX('Valuación diaria'!$M$5:$M$354,E8) -> 46276 | L8: =COUNTIFS(CETES!$A$5:$A$95,A8,CETES!$B$5:$B$95,C8) -> 0 | M8: =IF(L8=0,"",INDEX(CETES!$E$5:$E$95,MATCH(A8&"|"&C8,CETES!$AG$5:$AG$95,0))) | N8: =IF(L8=0,"",INDEX(CETES!$AD$5:$AD$95,MATCH(A8&"|"&C8,CETES!$AG$5:$AG$95,0))) | O8: =IF(L8=0,"",INDEX(CETES!$Y$5:$Y$95,MATCH(A8&"|"&C8,CETES!$AG$5:$AG$95,0))) | P8: =IF(L8=0,"",INDEX(CETES!$Z$5:$Z$95,MATCH(A8&"|"&C8,CETES!$AG$5:$AG$95,0))) | Q8: =INDEX('Valuación diaria'!$O$5:$O$354,E8) -> 10006 | R8: =INDEX('Valuación diaria'!$P$5:$P$354,E8) -> -15.98
A9: 46278 | B9: Principal | C9: BI261008 | D9: Casa A | E9: =MATCH(A9&"|"&B9&"|"&C9&"|"&D9,'Valuación diaria'!$S$5:$S$354,0) -> 35 | F9: =IF(COUNTIFS(Transacciones!$T$5:$T$20,B9&"|"&C9&"|"&D9,Transacciones!$F$5:$F$20,"<="&A9)>0,"sí","no") -> sí | G9: =INDEX('Valuación diaria'!$I$5:$I$354,E9) -> 1500 | H9: =INDEX('Valuación diaria'!$K$5:$K$354,E9) -> 9.951624 | I9: =INDEX('Valuación diaria'!$L$5:$L$354,E9) -> 14927.436 | J9: =INDEX('Valuación diaria'!$N$5:$N$354,E9) -> 9.9567848 | K9: =INDEX('Valuación diaria'!$M$5:$M$354,E9) -> 46278 | L9: =COUNTIFS(CETES!$A$5:$A$95,A9,CETES!$B$5:$B$95,C9) -> 1 | M9: =IF(L9=0,"",INDEX(CETES!$E$5:$E$95,MATCH(A9&"|"&C9,CETES!$AG$5:$AG$95,0))) -> 25 | N9: =IF(L9=0,"",INDEX(CETES!$AD$5:$AD$95,MATCH(A9&"|"&C9,CETES!$AG$5:$AG$95,0))) -> 6.25 | O9: =IF(L9=0,"",INDEX(CETES!$Y$5:$Y$95,MATCH(A9&"|"&C9,CETES!$AG$5:$AG$95,0))) -> 46275 | P9: =IF(L9=0,"",INDEX(CETES!$Z$5:$Z$95,MATCH(A9&"|"&C9,CETES!$AG$5:$AG$95,0))) -> 46275 | Q9: =INDEX('Valuación diaria'!$O$5:$O$354,E9) -> 14935.177 | R9: =INDEX('Valuación diaria'!$P$5:$P$354,E9) -> 7.7412
A10: 46278 | B10: Principal | C10: BI261008 | D10: Casa B | E10: =MATCH(A10&"|"&B10&"|"&C10&"|"&D10,'Valuación diaria'!$S$5:$S$354,0) -> 36 | F10: =IF(COUNTIFS(Transacciones!$T$5:$T$20,B10&"|"&C10&"|"&D10,Transacciones!$F$5:$F$20,"<="&A10)>0,"sí","no") -> sí | G10: =INDEX('Valuación diaria'!$I$5:$I$354,E10) -> 1000 | H10: =INDEX('Valuación diaria'!$K$5:$K$354,E10) -> 9.951624 | I10: =INDEX('Valuación diaria'!$L$5:$L$354,E10) -> 9951.624 | J10: =INDEX('Valuación diaria'!$N$5:$N$354,E10) -> 9.9567848 | K10: =INDEX('Valuación diaria'!$M$5:$M$354,E10) -> 46278 | L10: =COUNTIFS(CETES!$A$5:$A$95,A10,CETES!$B$5:$B$95,C10) -> 1 | M10: =IF(L10=0,"",INDEX(CETES!$E$5:$E$95,MATCH(A10&"|"&C10,CETES!$AG$5:$AG$95,0))) -> 25 | N10: =IF(L10=0,"",INDEX(CETES!$AD$5:$AD$95,MATCH(A10&"|"&C10,CETES!$AG$5:$AG$95,0))) -> 6.25 | O10: =IF(L10=0,"",INDEX(CETES!$Y$5:$Y$95,MATCH(A10&"|"&C10,CETES!$AG$5:$AG$95,0))) -> 46275 | P10: =IF(L10=0,"",INDEX(CETES!$Z$5:$Z$95,MATCH(A10&"|"&C10,CETES!$AG$5:$AG$95,0))) -> 46275 | Q10: =INDEX('Valuación diaria'!$O$5:$O$354,E10) -> 9956.7848 | R10: =INDEX('Valuación diaria'!$P$5:$P$354,E10) -> 5.1608
A11: 46278 | B11: Principal | C11: BI261105 | D11: Casa B | E11: =MATCH(A11&"|"&B11&"|"&C11&"|"&D11,'Valuación diaria'!$S$5:$S$354,0) -> 37 | F11: =IF(COUNTIFS(Transacciones!$T$5:$T$20,B11&"|"&C11&"|"&D11,Transacciones!$F$5:$F$20,"<="&A11)>0,"sí","no") -> no | G11: =INDEX('Valuación diaria'!$I$5:$I$354,E11) -> 0 | H11: =INDEX('Valuación diaria'!$K$5:$K$354,E11) -> 0 | I11: =INDEX('Valuación diaria'!$L$5:$L$354,E11) -> 0 | J11: =INDEX('Valuación diaria'!$N$5:$N$354,E11) | K11: =INDEX('Valuación diaria'!$M$5:$M$354,E11) | L11: =COUNTIFS(CETES!$A$5:$A$95,A11,CETES!$B$5:$B$95,C11) -> 0 | M11: =IF(L11=0,"",INDEX(CETES!$E$5:$E$95,MATCH(A11&"|"&C11,CETES!$AG$5:$AG$95,0))) | N11: =IF(L11=0,"",INDEX(CETES!$AD$5:$AD$95,MATCH(A11&"|"&C11,CETES!$AG$5:$AG$95,0))) | O11: =IF(L11=0,"",INDEX(CETES!$Y$5:$Y$95,MATCH(A11&"|"&C11,CETES!$AG$5:$AG$95,0))) | P11: =IF(L11=0,"",INDEX(CETES!$Z$5:$Z$95,MATCH(A11&"|"&C11,CETES!$AG$5:$AG$95,0))) | Q11: =INDEX('Valuación diaria'!$O$5:$O$354,E11) -> 0 | R11: =INDEX('Valuación diaria'!$P$5:$P$354,E11) -> 0
A12: 46278 | B12: Principal | C12: BI261217 | D12: Casa A | E12: =MATCH(A12&"|"&B12&"|"&C12&"|"&D12,'Valuación diaria'!$S$5:$S$354,0) -> 38 | F12: =IF(COUNTIFS(Transacciones!$T$5:$T$20,B12&"|"&C12&"|"&D12,Transacciones!$F$5:$F$20,"<="&A12)>0,"sí","no") -> no | G12: =INDEX('Valuación diaria'!$I$5:$I$354,E12) -> 0 | H12: =INDEX('Valuación diaria'!$K$5:$K$354,E12) -> 0 | I12: =INDEX('Valuación diaria'!$L$5:$L$354,E12) -> 0 | J12: =INDEX('Valuación diaria'!$N$5:$N$354,E12) | K12: =INDEX('Valuación diaria'!$M$5:$M$354,E12) | L12: =COUNTIFS(CETES!$A$5:$A$95,A12,CETES!$B$5:$B$95,C12) -> 0 | M12: =IF(L12=0,"",INDEX(CETES!$E$5:$E$95,MATCH(A12&"|"&C12,CETES!$AG$5:$AG$95,0))) | N12: =IF(L12=0,"",INDEX(CETES!$AD$5:$AD$95,MATCH(A12&"|"&C12,CETES!$AG$5:$AG$95,0))) | O12: =IF(L12=0,"",INDEX(CETES!$Y$5:$Y$95,MATCH(A12&"|"&C12,CETES!$AG$5:$AG$95,0))) | P12: =IF(L12=0,"",INDEX(CETES!$Z$5:$Z$95,MATCH(A12&"|"&C12,CETES!$AG$5:$AG$95,0))) | Q12: =INDEX('Valuación diaria'!$O$5:$O$354,E12) -> 0 | R12: =INDEX('Valuación diaria'!$P$5:$P$354,E12) -> 0
A13: 46278 | B13: Principal | C13: BI270318 | D13: Casa B | E13: =MATCH(A13&"|"&B13&"|"&C13&"|"&D13,'Valuación diaria'!$S$5:$S$354,0) -> 39 | F13: =IF(COUNTIFS(Transacciones!$T$5:$T$20,B13&"|"&C13&"|"&D13,Transacciones!$F$5:$F$20,"<="&A13)>0,"sí","no") -> no | G13: =INDEX('Valuación diaria'!$I$5:$I$354,E13) -> 0 | H13: =INDEX('Valuación diaria'!$K$5:$K$354,E13) -> 0 | I13: =INDEX('Valuación diaria'!$L$5:$L$354,E13) -> 0 | J13: =INDEX('Valuación diaria'!$N$5:$N$354,E13) | K13: =INDEX('Valuación diaria'!$M$5:$M$354,E13) | L13: =COUNTIFS(CETES!$A$5:$A$95,A13,CETES!$B$5:$B$95,C13) -> 0 | M13: =IF(L13=0,"",INDEX(CETES!$E$5:$E$95,MATCH(A13&"|"&C13,CETES!$AG$5:$AG$95,0))) | N13: =IF(L13=0,"",INDEX(CETES!$AD$5:$AD$95,MATCH(A13&"|"&C13,CETES!$AG$5:$AG$95,0))) | O13: =IF(L13=0,"",INDEX(CETES!$Y$5:$Y$95,MATCH(A13&"|"&C13,CETES!$AG$5:$AG$95,0))) | P13: =IF(L13=0,"",INDEX(CETES!$Z$5:$Z$95,MATCH(A13&"|"&C13,CETES!$AG$5:$AG$95,0))) | Q13: =INDEX('Valuación diaria'!$O$5:$O$354,E13) -> 0 | R13: =INDEX('Valuación diaria'!$P$5:$P$354,E13) -> 0
A14: 46278 | B14: Secundario | C14: DEMOACC | D14: Casa A | E14: =MATCH(A14&"|"&B14&"|"&C14&"|"&D14,'Valuación diaria'!$S$5:$S$354,0) -> 40 | F14: =IF(COUNTIFS(Transacciones!$T$5:$T$20,B14&"|"&C14&"|"&D14,Transacciones!$F$5:$F$20,"<="&A14)>0,"sí","no") -> no | G14: =INDEX('Valuación diaria'!$I$5:$I$354,E14) -> 0 | H14: =INDEX('Valuación diaria'!$K$5:$K$354,E14) -> 0 | I14: =INDEX('Valuación diaria'!$L$5:$L$354,E14) -> 0 | J14: =INDEX('Valuación diaria'!$N$5:$N$354,E14) -> 101.85 | K14: =INDEX('Valuación diaria'!$M$5:$M$354,E14) -> 46276 | L14: =COUNTIFS(CETES!$A$5:$A$95,A14,CETES!$B$5:$B$95,C14) -> 0 | M14: =IF(L14=0,"",INDEX(CETES!$E$5:$E$95,MATCH(A14&"|"&C14,CETES!$AG$5:$AG$95,0))) | N14: =IF(L14=0,"",INDEX(CETES!$AD$5:$AD$95,MATCH(A14&"|"&C14,CETES!$AG$5:$AG$95,0))) | O14: =IF(L14=0,"",INDEX(CETES!$Y$5:$Y$95,MATCH(A14&"|"&C14,CETES!$AG$5:$AG$95,0))) | P14: =IF(L14=0,"",INDEX(CETES!$Z$5:$Z$95,MATCH(A14&"|"&C14,CETES!$AG$5:$AG$95,0))) | Q14: =INDEX('Valuación diaria'!$O$5:$O$354,E14) -> 0 | R14: =INDEX('Valuación diaria'!$P$5:$P$354,E14) -> 0
A15: 46281 | B15: Principal | C15: DEMOACC | D15: Casa A | E15: =MATCH(A15&"|"&B15&"|"&C15&"|"&D15,'Valuación diaria'!$S$5:$S$354,0) -> 61 | F15: =IF(COUNTIFS(Transacciones!$T$5:$T$20,B15&"|"&C15&"|"&D15,Transacciones!$F$5:$F$20,"<="&A15)>0,"sí","no") -> sí | G15: =INDEX('Valuación diaria'!$I$5:$I$354,E15) -> 200 | H15: =INDEX('Valuación diaria'!$K$5:$K$354,E15) -> 100.23985 | I15: =INDEX('Valuación diaria'!$L$5:$L$354,E15) -> 20047.97 | J15: =INDEX('Valuación diaria'!$N$5:$N$354,E15) -> 104.75 | K15: =INDEX('Valuación diaria'!$M$5:$M$354,E15) -> 46280 | L15: =COUNTIFS(CETES!$A$5:$A$95,A15,CETES!$B$5:$B$95,C15) -> 0 | M15: =IF(L15=0,"",INDEX(CETES!$E$5:$E$95,MATCH(A15&"|"&C15,CETES!$AG$5:$AG$95,0))) | N15: =IF(L15=0,"",INDEX(CETES!$AD$5:$AD$95,MATCH(A15&"|"&C15,CETES!$AG$5:$AG$95,0))) | O15: =IF(L15=0,"",INDEX(CETES!$Y$5:$Y$95,MATCH(A15&"|"&C15,CETES!$AG$5:$AG$95,0))) | P15: =IF(L15=0,"",INDEX(CETES!$Z$5:$Z$95,MATCH(A15&"|"&C15,CETES!$AG$5:$AG$95,0))) | Q15: =INDEX('Valuación diaria'!$O$5:$O$354,E15) -> 20950 | R15: =INDEX('Valuación diaria'!$P$5:$P$354,E15) -> 902.03
A16: 46281 | B16: Principal | C16: DEMOACC | D16: Casa B | E16: =MATCH(A16&"|"&B16&"|"&C16&"|"&D16,'Valuación diaria'!$S$5:$S$354,0) -> 62 | F16: =IF(COUNTIFS(Transacciones!$T$5:$T$20,B16&"|"&C16&"|"&D16,Transacciones!$F$5:$F$20,"<="&A16)>0,"sí","no") -> sí | G16: =INDEX('Valuación diaria'!$I$5:$I$354,E16) -> 100 | H16: =INDEX('Valuación diaria'!$K$5:$K$354,E16) -> 103.399 | I16: =INDEX('Valuación diaria'!$L$5:$L$354,E16) -> 10339.9 | J16: =INDEX('Valuación diaria'!$N$5:$N$354,E16) -> 104.75 | K16: =INDEX('Valuación diaria'!$M$5:$M$354,E16) -> 46280 | L16: =COUNTIFS(CETES!$A$5:$A$95,A16,CETES!$B$5:$B$95,C16) -> 0 | M16: =IF(L16=0,"",INDEX(CETES!$E$5:$E$95,MATCH(A16&"|"&C16,CETES!$AG$5:$AG$95,0))) | N16: =IF(L16=0,"",INDEX(CETES!$AD$5:$AD$95,MATCH(A16&"|"&C16,CETES!$AG$5:$AG$95,0))) | O16: =IF(L16=0,"",INDEX(CETES!$Y$5:$Y$95,MATCH(A16&"|"&C16,CETES!$AG$5:$AG$95,0))) | P16: =IF(L16=0,"",INDEX(CETES!$Z$5:$Z$95,MATCH(A16&"|"&C16,CETES!$AG$5:$AG$95,0))) | Q16: =INDEX('Valuación diaria'!$O$5:$O$354,E16) -> 10475 | R16: =INDEX('Valuación diaria'!$P$5:$P$354,E16) -> 135.1
... A44: 46309 | B44: Secundario | C44: DEMOACC | D44: Casa A | E44: =MATCH(A44&"|"&B44&"|"&C44&"|"&D44,'Valuación diaria'!$S$5:$S$354,0) -> 350 | F44: =IF(COUNTIFS(Transacciones!$T$5:$T$20,B44&"|"&C44&"|"&D44,Transacciones!$F$5:$F$20,"<="&A44)>0,"sí","no") -> sí | G44: =INDEX('Valuación diaria'!$I$5:$I$354,E44) -> 150 | H44: =INDEX('Valuación diaria'!$K$5:$K$354,E44) -> 103.90047 | I44: =INDEX('Valuación diaria'!$L$5:$L$354,E44) -> 15585.07 | J44: =INDEX('Valuación diaria'!$N$5:$N$354,E44) -> 111.05 | K44: =INDEX('Valuación diaria'!$M$5:$M$354,E44) -> 46309 | L44: =COUNTIFS(CETES!$A$5:$A$95,A44,CETES!$B$5:$B$95,C44) -> 0 | M44: =IF(L44=0,"",INDEX(CETES!$E$5:$E$95,MATCH(A44&"|"&C44,CETES!$AG$5:$AG$95,0))) | N44: =IF(L44=0,"",INDEX(CETES!$AD$5:$AD$95,MATCH(A44&"|"&C44,CETES!$AG$5:$AG$95,0))) | O44: =IF(L44=0,"",INDEX(CETES!$Y$5:$Y$95,MATCH(A44&"|"&C44,CETES!$AG$5:$AG$95,0))) | P44: =IF(L44=0,"",INDEX(CETES!$Z$5:$Z$95,MATCH(A44&"|"&C44,CETES!$AG$5:$AG$95,0))) | Q44: =INDEX('Valuación diaria'!$O$5:$O$354,E44) -> 16657.5 | R44: =INDEX('Valuación diaria'!$P$5:$P$354,E44) -> 1072.43
A46: Consolidado por instrumento (suma de intermediarios)
A47: fecha_corte | B47: portafolio | C47: instrumento | D47: títulos | E47: costo total | F47: valor de mercado | G47: resultado no realizado | H47: intermediarios con saldo
A48: 46278 | B48: Principal | C48: DEMOACC | D48: =SUMIFS(Posiciones!$G$5:$G$44,Posiciones!$A$5:$A$44,A48,Posiciones!$B$5:$B$44,B48,Posiciones!$C$5:$C$44,C48) -> 200 | E48: =SUMIFS(Posiciones!$I$5:$I$44,Posiciones!$A$5:$A$44,A48,Posiciones!$B$5:$B$44,B48,Posiciones!$C$5:$C$44,C48) -> 20047.97 | F48: =SUMIFS(Posiciones!$Q$5:$Q$44,Posiciones!$A$5:$A$44,A48,Posiciones!$B$5:$B$44,B48,Posiciones!$C$5:$C$44,C48) -> 20370 | G48: =SUMIFS(Posiciones!$R$5:$R$44,Posiciones!$A$5:$A$44,A48,Posiciones!$B$5:$B$44,B48,Posiciones!$C$5:$C$44,C48) -> 322.03 | H48: =COUNTIFS(Posiciones!$A$5:$A$44,A48,Posiciones!$B$5:$B$44,B48,Posiciones!$C$5:$C$44,C48,Posiciones!$G$5:$G$44,">0") -> 1
A49: 46278 | B49: Principal | C49: DEMOETF | D49: =SUMIFS(Posiciones!$G$5:$G$44,Posiciones!$A$5:$A$44,A49,Posiciones!$B$5:$B$44,B49,Posiciones!$C$5:$C$44,C49) -> 100 | E49: =SUMIFS(Posiciones!$I$5:$I$44,Posiciones!$A$5:$A$44,A49,Posiciones!$B$5:$B$44,B49,Posiciones!$C$5:$C$44,C49) -> 5019.51 | F49: =SUMIFS(Posiciones!$Q$5:$Q$44,Posiciones!$A$5:$A$44,A49,Posiciones!$B$5:$B$44,B49,Posiciones!$C$5:$C$44,C49) -> 5062 | G49: =SUMIFS(Posiciones!$R$5:$R$44,Posiciones!$A$5:$A$44,A49,Posiciones!$B$5:$B$44,B49,Posiciones!$C$5:$C$44,C49) -> 42.49 | H49: =COUNTIFS(Posiciones!$A$5:$A$44,A49,Posiciones!$B$5:$B$44,B49,Posiciones!$C$5:$C$44,C49,Posiciones!$G$5:$G$44,">0") -> 1
A50: 46278 | B50: Principal | C50: DEMOFIB | D50: =SUMIFS(Posiciones!$G$5:$G$44,Posiciones!$A$5:$A$44,A50,Posiciones!$B$5:$B$44,B50,Posiciones!$C$5:$C$44,C50) -> 400 | E50: =SUMIFS(Posiciones!$I$5:$I$44,Posiciones!$A$5:$A$44,A50,Posiciones!$B$5:$B$44,B50,Posiciones!$C$5:$C$44,C50) -> 10021.98 | F50: =SUMIFS(Posiciones!$Q$5:$Q$44,Posiciones!$A$5:$A$44,A50,Posiciones!$B$5:$B$44,B50,Posiciones!$C$5:$C$44,C50) -> 10006 | G50: =SUMIFS(Posiciones!$R$5:$R$44,Posiciones!$A$5:$A$44,A50,Posiciones!$B$5:$B$44,B50,Posiciones!$C$5:$C$44,C50) -> -15.98 | H50: =COUNTIFS(Posiciones!$A$5:$A$44,A50,Posiciones!$B$5:$B$44,B50,Posiciones!$C$5:$C$44,C50,Posiciones!$G$5:$G$44,">0") -> 1
A51: 46278 | B51: Principal | C51: BI261008 | D51: =SUMIFS(Posiciones!$G$5:$G$44,Posiciones!$A$5:$A$44,A51,Posiciones!$B$5:$B$44,B51,Posiciones!$C$5:$C$44,C51) -> 2500 | E51: =SUMIFS(Posiciones!$I$5:$I$44,Posiciones!$A$5:$A$44,A51,Posiciones!$B$5:$B$44,B51,Posiciones!$C$5:$C$44,C51) -> 24879.06 | F51: =SUMIFS(Posiciones!$Q$5:$Q$44,Posiciones!$A$5:$A$44,A51,Posiciones!$B$5:$B$44,B51,Posiciones!$C$5:$C$44,C51) -> 24891.962 | G51: =SUMIFS(Posiciones!$R$5:$R$44,Posiciones!$A$5:$A$44,A51,Posiciones!$B$5:$B$44,B51,Posiciones!$C$5:$C$44,C51) -> 12.902 | H51: =COUNTIFS(Posiciones!$A$5:$A$44,A51,Posiciones!$B$5:$B$44,B51,Posiciones!$C$5:$C$44,C51,Posiciones!$G$5:$G$44,">0") -> 2
A52: 46278 | B52: Principal | C52: BI261105 | D52: =SUMIFS(Posiciones!$G$5:$G$44,Posiciones!$A$5:$A$44,A52,Posiciones!$B$5:$B$44,B52,Posiciones!$C$5:$C$44,C52) -> 0 | E52: =SUMIFS(Posiciones!$I$5:$I$44,Posiciones!$A$5:$A$44,A52,Posiciones!$B$5:$B$44,B52,Posiciones!$C$5:$C$44,C52) -> 0 | F52: =SUMIFS(Posiciones!$Q$5:$Q$44,Posiciones!$A$5:$A$44,A52,Posiciones!$B$5:$B$44,B52,Posiciones!$C$5:$C$44,C52) -> 0 | G52: =SUMIFS(Posiciones!$R$5:$R$44,Posiciones!$A$5:$A$44,A52,Posiciones!$B$5:$B$44,B52,Posiciones!$C$5:$C$44,C52) -> 0 | H52: =COUNTIFS(Posiciones!$A$5:$A$44,A52,Posiciones!$B$5:$B$44,B52,Posiciones!$C$5:$C$44,C52,Posiciones!$G$5:$G$44,">0") -> 0
A53: 46278 | B53: Principal | C53: BI261217 | D53: =SUMIFS(Posiciones!$G$5:$G$44,Posiciones!$A$5:$A$44,A53,Posiciones!$B$5:$B$44,B53,Posiciones!$C$5:$C$44,C53) -> 0 | E53: =SUMIFS(Posiciones!$I$5:$I$44,Posiciones!$A$5:$A$44,A53,Posiciones!$B$5:$B$44,B53,Posiciones!$C$5:$C$44,C53) -> 0 | F53: =SUMIFS(Posiciones!$Q$5:$Q$44,Posiciones!$A$5:$A$44,A53,Posiciones!$B$5:$B$44,B53,Posiciones!$C$5:$C$44,C53) -> 0 | G53: =SUMIFS(Posiciones!$R$5:$R$44,Posiciones!$A$5:$A$44,A53,Posiciones!$B$5:$B$44,B53,Posiciones!$C$5:$C$44,C53) -> 0 | H53: =COUNTIFS(Posiciones!$A$5:$A$44,A53,Posiciones!$B$5:$B$44,B53,Posiciones!$C$5:$C$44,C53,Posiciones!$G$5:$G$44,">0") -> 0
A54: 46278 | B54: Principal | C54: BI270318 | D54: =SUMIFS(Posiciones!$G$5:$G$44,Posiciones!$A$5:$A$44,A54,Posiciones!$B$5:$B$44,B54,Posiciones!$C$5:$C$44,C54) -> 0 | E54: =SUMIFS(Posiciones!$I$5:$I$44,Posiciones!$A$5:$A$44,A54,Posiciones!$B$5:$B$44,B54,Posiciones!$C$5:$C$44,C54) -> 0 | F54: =SUMIFS(Posiciones!$Q$5:$Q$44,Posiciones!$A$5:$A$44,A54,Posiciones!$B$5:$B$44,B54,Posiciones!$C$5:$C$44,C54) -> 0 | G54: =SUMIFS(Posiciones!$R$5:$R$44,Posiciones!$A$5:$A$44,A54,Posiciones!$B$5:$B$44,B54,Posiciones!$C$5:$C$44,C54) -> 0 | H54: =COUNTIFS(Posiciones!$A$5:$A$44,A54,Posiciones!$B$5:$B$44,B54,Posiciones!$C$5:$C$44,C54,Posiciones!$G$5:$G$44,">0") -> 0
A55: 46278 | B55: Secundario | C55: DEMOACC | D55: =SUMIFS(Posiciones!$G$5:$G$44,Posiciones!$A$5:$A$44,A55,Posiciones!$B$5:$B$44,B55,Posiciones!$C$5:$C$44,C55) -> 0 | E55: =SUMIFS(Posiciones!$I$5:$I$44,Posiciones!$A$5:$A$44,A55,Posiciones!$B$5:$B$44,B55,Posiciones!$C$5:$C$44,C55) -> 0 | F55: =SUMIFS(Posiciones!$Q$5:$Q$44,Posiciones!$A$5:$A$44,A55,Posiciones!$B$5:$B$44,B55,Posiciones!$C$5:$C$44,C55) -> 0 | G55: =SUMIFS(Posiciones!$R$5:$R$44,Posiciones!$A$5:$A$44,A55,Posiciones!$B$5:$B$44,B55,Posiciones!$C$5:$C$44,C55) -> 0 | H55: =COUNTIFS(Posiciones!$A$5:$A$44,A55,Posiciones!$B$5:$B$44,B55,Posiciones!$C$5:$C$44,C55,Posiciones!$G$5:$G$44,">0") -> 0
A56: 46281 | B56: Principal | C56: DEMOACC | D56: =SUMIFS(Posiciones!$G$5:$G$44,Posiciones!$A$5:$A$44,A56,Posiciones!$B$5:$B$44,B56,Posiciones!$C$5:$C$44,C56) -> 300 | E56: =SUMIFS(Posiciones!$I$5:$I$44,Posiciones!$A$5:$A$44,A56,Posiciones!$B$5:$B$44,B56,Posiciones!$C$5:$C$44,C56) -> 30387.87 | F56: =SUMIFS(Posiciones!$Q$5:$Q$44,Posiciones!$A$5:$A$44,A56,Posiciones!$B$5:$B$44,B56,Posiciones!$C$5:$C$44,C56) -> 31425 | G56: =SUMIFS(Posiciones!$R$5:$R$44,Posiciones!$A$5:$A$44,A56,Posiciones!$B$5:$B$44,B56,Posiciones!$C$5:$C$44,C56) -> 1037.13 | H56: =COUNTIFS(Posiciones!$A$5:$A$44,A56,Posiciones!$B$5:$B$44,B56,Posiciones!$C$5:$C$44,C56,Posiciones!$G$5:$G$44,">0") -> 2
A57: 46281 | B57: Principal | C57: DEMOETF | D57: =SUMIFS(Posiciones!$G$5:$G$44,Posiciones!$A$5:$A$44,A57,Posiciones!$B$5:$B$44,B57,Posiciones!$C$5:$C$44,C57) -> 100 | E57: =SUMIFS(Posiciones!$I$5:$I$44,Posiciones!$A$5:$A$44,A57,Posiciones!$B$5:$B$44,B57,Posiciones!$C$5:$C$44,C57) -> 5019.51 | F57: =SUMIFS(Posiciones!$Q$5:$Q$44,Posiciones!$A$5:$A$44,A57,Posiciones!$B$5:$B$44,B57,Posiciones!$C$5:$C$44,C57) -> 5148 | G57: =SUMIFS(Posiciones!$R$5:$R$44,Posiciones!$A$5:$A$44,A57,Posiciones!$B$5:$B$44,B57,Posiciones!$C$5:$C$44,C57) -> 128.49 | H57: =COUNTIFS(Posiciones!$A$5:$A$44,A57,Posiciones!$B$5:$B$44,B57,Posiciones!$C$5:$C$44,C57,Posiciones!$G$5:$G$44,">0") -> 1
A58: 46281 | B58: Principal | C58: DEMOFIB | D58: =SUMIFS(Posiciones!$G$5:$G$44,Posiciones!$A$5:$A$44,A58,Posiciones!$B$5:$B$44,B58,Posiciones!$C$5:$C$44,C58) -> 400 | E58: =SUMIFS(Posiciones!$I$5:$I$44,Posiciones!$A$5:$A$44,A58,Posiciones!$B$5:$B$44,B58,Posiciones!$C$5:$C$44,C58) -> 10021.98 | F58: =SUMIFS(Posiciones!$Q$5:$Q$44,Posiciones!$A$5:$A$44,A58,Posiciones!$B$5:$B$44,B58,Posiciones!$C$5:$C$44,C58) -> 10164 | G58: =SUMIFS(Posiciones!$R$5:$R$44,Posiciones!$A$5:$A$44,A58,Posiciones!$B$5:$B$44,B58,Posiciones!$C$5:$C$44,C58) -> 142.02 | H58: =COUNTIFS(Posiciones!$A$5:$A$44,A58,Posiciones!$B$5:$B$44,B58,Posiciones!$C$5:$C$44,C58,Posiciones!$G$5:$G$44,">0") -> 1
A59: 46281 | B59: Principal | C59: BI261008 | D59: =SUMIFS(Posiciones!$G$5:$G$44,Posiciones!$A$5:$A$44,A59,Posiciones!$B$5:$B$44,B59,Posiciones!$C$5:$C$44,C59) -> 2500 | E59: =SUMIFS(Posiciones!$I$5:$I$44,Posiciones!$A$5:$A$44,A59,Posiciones!$B$5:$B$44,B59,Posiciones!$C$5:$C$44,C59) -> 24879.06 | F59: =SUMIFS(Posiciones!$Q$5:$Q$44,Posiciones!$A$5:$A$44,A59,Posiciones!$B$5:$B$44,B59,Posiciones!$C$5:$C$44,C59) -> 24904.877 | G59: =SUMIFS(Posiciones!$R$5:$R$44,Posiciones!$A$5:$A$44,A59,Posiciones!$B$5:$B$44,B59,Posiciones!$C$5:$C$44,C59) -> 25.81725 | H59: =COUNTIFS(Posiciones!$A$5:$A$44,A59,Posiciones!$B$5:$B$44,B59,Posiciones!$C$5:$C$44,C59,Posiciones!$G$5:$G$44,">0") -> 2
... A79: 46309 | B79: Secundario | C79: DEMOACC | D79: =SUMIFS(Posiciones!$G$5:$G$44,Posiciones!$A$5:$A$44,A79,Posiciones!$B$5:$B$44,B79,Posiciones!$C$5:$C$44,C79) -> 150 | E79: =SUMIFS(Posiciones!$I$5:$I$44,Posiciones!$A$5:$A$44,A79,Posiciones!$B$5:$B$44,B79,Posiciones!$C$5:$C$44,C79) -> 15585.07 | F79: =SUMIFS(Posiciones!$Q$5:$Q$44,Posiciones!$A$5:$A$44,A79,Posiciones!$B$5:$B$44,B79,Posiciones!$C$5:$C$44,C79) -> 16657.5 | G79: =SUMIFS(Posiciones!$R$5:$R$44,Posiciones!$A$5:$A$44,A79,Posiciones!$B$5:$B$44,B79,Posiciones!$C$5:$C$44,C79) -> 1072.43 | H79: =COUNTIFS(Posiciones!$A$5:$A$44,A79,Posiciones!$B$5:$B$44,B79,Posiciones!$C$5:$C$44,C79,Posiciones!$G$5:$G$44,">0") -> 1
A81: Totales del portafolio (comprobación: suma por intermediario = suma consolidada = V(t) de la Serie)
A82: fecha_corte | B82: portafolio | C82: costo total | D82: valor (suma por intermediario) | E82: resultado no realizado | F82: valor (suma consolidada) | G82: V(t) de la Serie | H82: ¿iguales?
A83: 46278 | B83: Principal | C83: =SUMIFS(Posiciones!$I$5:$I$44,Posiciones!$A$5:$A$44,A83,Posiciones!$B$5:$B$44,B83) -> 59968.52 | D83: =SUMIFS(Posiciones!$Q$5:$Q$44,Posiciones!$A$5:$A$44,A83,Posiciones!$B$5:$B$44,B83) -> 60329.962 | E83: =SUMIFS(Posiciones!$R$5:$R$44,Posiciones!$A$5:$A$44,A83,Posiciones!$B$5:$B$44,B83) -> 361.442 | F83: =SUMIFS(Posiciones!$F$48:$F$79,Posiciones!$A$48:$A$79,A83,Posiciones!$B$48:$B$79,B83) -> 60329.962 | G83: =SUMIFS(Serie!$D$5:$D$74,Serie!$A$5:$A$74,A83,Serie!$B$5:$B$74,B83) -> 60329.962 | H83: =AND(ABS(D83-F83)<0.000000001,ABS(D83-G83)<0.000000001) -> TRUE
A84: 46278 | B84: Secundario | C84: =SUMIFS(Posiciones!$I$5:$I$44,Posiciones!$A$5:$A$44,A84,Posiciones!$B$5:$B$44,B84) -> 0 | D84: =SUMIFS(Posiciones!$Q$5:$Q$44,Posiciones!$A$5:$A$44,A84,Posiciones!$B$5:$B$44,B84) -> 0 | E84: =SUMIFS(Posiciones!$R$5:$R$44,Posiciones!$A$5:$A$44,A84,Posiciones!$B$5:$B$44,B84) -> 0 | F84: =SUMIFS(Posiciones!$F$48:$F$79,Posiciones!$A$48:$A$79,A84,Posiciones!$B$48:$B$79,B84) -> 0 | G84: =SUMIFS(Serie!$D$5:$D$74,Serie!$A$5:$A$74,A84,Serie!$B$5:$B$74,B84) -> 0 | H84: =AND(ABS(D84-F84)<0.000000001,ABS(D84-G84)<0.000000001) -> TRUE
A85: 46281 | B85: Principal | C85: =SUMIFS(Posiciones!$I$5:$I$44,Posiciones!$A$5:$A$44,A85,Posiciones!$B$5:$B$44,B85) -> 70308.42 | D85: =SUMIFS(Posiciones!$Q$5:$Q$44,Posiciones!$A$5:$A$44,A85,Posiciones!$B$5:$B$44,B85) -> 71641.877 | E85: =SUMIFS(Posiciones!$R$5:$R$44,Posiciones!$A$5:$A$44,A85,Posiciones!$B$5:$B$44,B85) -> 1333.4572 | F85: =SUMIFS(Posiciones!$F$48:$F$79,Posiciones!$A$48:$A$79,A85,Posiciones!$B$48:$B$79,B85) -> 71641.877 | G85: =SUMIFS(Serie!$D$5:$D$74,Serie!$A$5:$A$74,A85,Serie!$B$5:$B$74,B85) -> 71641.877 | H85: =AND(ABS(D85-F85)<0.000000001,ABS(D85-G85)<0.000000001) -> TRUE
A86: 46281 | B86: Secundario | C86: =SUMIFS(Posiciones!$I$5:$I$44,Posiciones!$A$5:$A$44,A86,Posiciones!$B$5:$B$44,B86) -> 15585.07 | D86: =SUMIFS(Posiciones!$Q$5:$Q$44,Posiciones!$A$5:$A$44,A86,Posiciones!$B$5:$B$44,B86) -> 15712.5 | E86: =SUMIFS(Posiciones!$R$5:$R$44,Posiciones!$A$5:$A$44,A86,Posiciones!$B$5:$B$44,B86) -> 127.43 | F86: =SUMIFS(Posiciones!$F$48:$F$79,Posiciones!$A$48:$A$79,A86,Posiciones!$B$48:$B$79,B86) -> 15712.5 | G86: =SUMIFS(Serie!$D$5:$D$74,Serie!$A$5:$A$74,A86,Serie!$B$5:$B$74,B86) -> 15712.5 | H86: =AND(ABS(D86-F86)<0.000000001,ABS(D86-G86)<0.000000001) -> TRUE
A87: 46303 | B87: Principal | C87: =SUMIFS(Posiciones!$I$5:$I$44,Posiciones!$A$5:$A$44,A87,Posiciones!$B$5:$B$44,B87) -> 56307.888 | D87: =SUMIFS(Posiciones!$Q$5:$Q$44,Posiciones!$A$5:$A$44,A87,Posiciones!$B$5:$B$44,B87) -> 57842.72 | E87: =SUMIFS(Posiciones!$R$5:$R$44,Posiciones!$A$5:$A$44,A87,Posiciones!$B$5:$B$44,B87) -> 1534.8314 | F87: =SUMIFS(Posiciones!$F$48:$F$79,Posiciones!$A$48:$A$79,A87,Posiciones!$B$48:$B$79,B87) -> 57842.72 | G87: =SUMIFS(Serie!$D$5:$D$74,Serie!$A$5:$A$74,A87,Serie!$B$5:$B$74,B87) -> 57842.72 | H87: =AND(ABS(D87-F87)<0.000000001,ABS(D87-G87)<0.000000001) -> TRUE
A88: 46303 | B88: Secundario | C88: =SUMIFS(Posiciones!$I$5:$I$44,Posiciones!$A$5:$A$44,A88,Posiciones!$B$5:$B$44,B88) -> 15585.07 | D88: =SUMIFS(Posiciones!$Q$5:$Q$44,Posiciones!$A$5:$A$44,A88,Posiciones!$B$5:$B$44,B88) -> 16110 | E88: =SUMIFS(Posiciones!$R$5:$R$44,Posiciones!$A$5:$A$44,A88,Posiciones!$B$5:$B$44,B88) -> 524.93 | F88: =SUMIFS(Posiciones!$F$48:$F$79,Posiciones!$A$48:$A$79,A88,Posiciones!$B$48:$B$79,B88) -> 16110 | G88: =SUMIFS(Serie!$D$5:$D$74,Serie!$A$5:$A$74,A88,Serie!$B$5:$B$74,B88) -> 16110 | H88: =AND(ABS(D88-F88)<0.000000001,ABS(D88-G88)<0.000000001) -> TRUE
A89: 46309 | B89: Principal | C89: =SUMIFS(Posiciones!$I$5:$I$44,Posiciones!$A$5:$A$44,A89,Posiciones!$B$5:$B$44,B89) -> 56307.888 | D89: =SUMIFS(Posiciones!$Q$5:$Q$44,Posiciones!$A$5:$A$44,A89,Posiciones!$B$5:$B$44,B89) -> 58940.878 | E89: =SUMIFS(Posiciones!$R$5:$R$44,Posiciones!$A$5:$A$44,A89,Posiciones!$B$5:$B$44,B89) -> 2632.9899 | F89: =SUMIFS(Posiciones!$F$48:$F$79,Posiciones!$A$48:$A$79,A89,Posiciones!$B$48:$B$79,B89) -> 58940.878 | G89: =SUMIFS(Serie!$D$5:$D$74,Serie!$A$5:$A$74,A89,Serie!$B$5:$B$74,B89) -> 58940.878 | H89: =AND(ABS(D89-F89)<0.000000001,ABS(D89-G89)<0.000000001) -> TRUE
A90: 46309 | B90: Secundario | C90: =SUMIFS(Posiciones!$I$5:$I$44,Posiciones!$A$5:$A$44,A90,Posiciones!$B$5:$B$44,B90) -> 15585.07 | D90: =SUMIFS(Posiciones!$Q$5:$Q$44,Posiciones!$A$5:$A$44,A90,Posiciones!$B$5:$B$44,B90) -> 16657.5 | E90: =SUMIFS(Posiciones!$R$5:$R$44,Posiciones!$A$5:$A$44,A90,Posiciones!$B$5:$B$44,B90) -> 1072.43 | F90: =SUMIFS(Posiciones!$F$48:$F$79,Posiciones!$A$48:$A$79,A90,Posiciones!$B$48:$B$79,B90) -> 16657.5 | G90: =SUMIFS(Serie!$D$5:$D$74,Serie!$A$5:$A$74,A90,Serie!$B$5:$B$74,B90) -> 16657.5 | H90: =AND(ABS(D90-F90)<0.000000001,ABS(D90-G90)<0.000000001) -> TRUE

Sheet Serie
A1: Serie diaria por día natural y portafolio (RF-09, RF-10, RF-11)
A2: V(t): valor al cierre de t. A(t): compras (títulos × precio + importe). R(t): ventas (títulos × precio − importe) y vencimientos (títulos × 10.00). r(t) = [V(t) + R(t)] / [V(t−1) + A(t)] − 1, y 0 si el denominador es 0. I(t) parte de 1 en el cierre base (10/09), que es el primer máximo.
A4: fecha | B4: portafolio | C4: llave | D4: V(t) valor | E4: A(t) aportaciones | F4: R ventas | G4: R vencimientos | H4: R(t) retiros | I4: V(t−1) | J4: denominador V(t−1) + A(t) | K4: r(t) (fracción) | L4: r(t) (%) | M4: I(t) índice | N4: máximo acumulado | O4: caída I/máx − 1
A5: 46275 | B5: Principal | C5: =A5&"|"&B5 -> 46275|Principal | D5: =SUMIFS('Valuación diaria'!$O$5:$O$354,'Valuación diaria'!$A$5:$A$354,A5,'Valuación diaria'!$B$5:$B$354,B5) -> 49929.06 | E5: =SUMIFS(Transacciones!$R$5:$R$20,Transacciones!$B$5:$B$20,B5,Transacciones!$F$5:$F$20,A5) -> 49946.54 | F5: =SUMIFS(Transacciones!$S$5:$S$20,Transacciones!$B$5:$B$20,B5,Transacciones!$F$5:$F$20,A5) -> 0 | G5: =SUMIFS('Valuación diaria'!$Q$5:$Q$354,'Valuación diaria'!$A$5:$A$354,A5,'Valuación diaria'!$B$5:$B$354,B5) -> 0 | H5: =F5+G5 -> 0 | I5: =IF(A5=Entradas!$B$8,"",D4) | J5: =IF(A5=Entradas!$B$8,"",I5+E5) | K5: =IF(A5=Entradas!$B$8,"",IF(J5=0,0,(D5+H5)/J5-1)) | L5: =IF(A5=Entradas!$B$8,"",K5*100) | M5: =IF(A5=Entradas!$B$8,1,M4*(1+K5)) -> 1 | N5: =IF(A5=Entradas!$B$8,1,MAX(N4,M5)) -> 1 | O5: =M5/N5-1 -> 0
A6: 46276 | B6: Principal | C6: =A6&"|"&B6 -> 46276|Principal | D6: =SUMIFS('Valuación diaria'!$O$5:$O$354,'Valuación diaria'!$A$5:$A$354,A6,'Valuación diaria'!$B$5:$B$354,B6) -> 60321.359 | E6: =SUMIFS(Transacciones!$R$5:$R$20,Transacciones!$B$5:$B$20,B6,Transacciones!$F$5:$F$20,A6) -> 10021.98 | F6: =SUMIFS(Transacciones!$S$5:$S$20,Transacciones!$B$5:$B$20,B6,Transacciones!$F$5:$F$20,A6) -> 0 | G6: =SUMIFS('Valuación diaria'!$Q$5:$Q$354,'Valuación diaria'!$A$5:$A$354,A6,'Valuación diaria'!$B$5:$B$354,B6) -> 0 | H6: =F6+G6 -> 0 | I6: =IF(A6=Entradas!$B$8,"",D5) -> 49929.06 | J6: =IF(A6=Entradas!$B$8,"",I6+E6) -> 59951.04 | K6: =IF(A6=Entradas!$B$8,"",IF(J6=0,0,(D6+H6)/J6-1)) -> 0.006177028 | L6: =IF(A6=Entradas!$B$8,"",K6*100) -> 0.6177028 | M6: =IF(A6=Entradas!$B$8,1,M5*(1+K6)) -> 1.006177 | N6: =IF(A6=Entradas!$B$8,1,MAX(N5,M6)) -> 1.006177 | O6: =M6/N6-1 -> 0
A7: 46277 | B7: Principal | C7: =A7&"|"&B7 -> 46277|Principal | D7: =SUMIFS('Valuación diaria'!$O$5:$O$354,'Valuación diaria'!$A$5:$A$354,A7,'Valuación diaria'!$B$5:$B$354,B7) -> 60325.66 | E7: =SUMIFS(Transacciones!$R$5:$R$20,Transacciones!$B$5:$B$20,B7,Transacciones!$F$5:$F$20,A7) -> 0 | F7: =SUMIFS(Transacciones!$S$5:$S$20,Transacciones!$B$5:$B$20,B7,Transacciones!$F$5:$F$20,A7) -> 0 | G7: =SUMIFS('Valuación diaria'!$Q$5:$Q$354,'Valuación diaria'!$A$5:$A$354,A7,'Valuación diaria'!$B$5:$B$354,B7) -> 0 | H7: =F7+G7 -> 0 | I7: =IF(A7=Entradas!$B$8,"",D6) -> 60321.359 | J7: =IF(A7=Entradas!$B$8,"",I7+E7) -> 60321.359 | K7: =IF(A7=Entradas!$B$8,"",IF(J7=0,0,(D7+H7)/J7-1)) -> 7.1293155e-05 | L7: =IF(A7=Entradas!$B$8,"",K7*100) -> 0.0071293155 | M7: =IF(A7=Entradas!$B$8,1,M6*(1+K7)) -> 1.0062488 | N7: =IF(A7=Entradas!$B$8,1,MAX(N6,M7)) -> 1.0062488 | O7: =M7/N7-1 -> 0
A8: 46278 | B8: Principal | C8: =A8&"|"&B8 -> 46278|Principal | D8: =SUMIFS('Valuación diaria'!$O$5:$O$354,'Valuación diaria'!$A$5:$A$354,A8,'Valuación diaria'!$B$5:$B$354,B8) -> 60329.962 | E8: =SUMIFS(Transacciones!$R$5:$R$20,Transacciones!$B$5:$B$20,B8,Transacciones!$F$5:$F$20,A8) -> 0 | F8: =SUMIFS(Transacciones!$S$5:$S$20,Transacciones!$B$5:$B$20,B8,Transacciones!$F$5:$F$20,A8) -> 0 | G8: =SUMIFS('Valuación diaria'!$Q$5:$Q$354,'Valuación diaria'!$A$5:$A$354,A8,'Valuación diaria'!$B$5:$B$354,B8) -> 0 | H8: =F8+G8 -> 0 | I8: =IF(A8=Entradas!$B$8,"",D7) -> 60325.66 | J8: =IF(A8=Entradas!$B$8,"",I8+E8) -> 60325.66 | K8: =IF(A8=Entradas!$B$8,"",IF(J8=0,0,(D8+H8)/J8-1)) -> 7.1317082e-05 | L8: =IF(A8=Entradas!$B$8,"",K8*100) -> 0.0071317082 | M8: =IF(A8=Entradas!$B$8,1,M7*(1+K8)) -> 1.0063205 | N8: =IF(A8=Entradas!$B$8,1,MAX(N7,M8)) -> 1.0063205 | O8: =M8/N8-1 -> 0
A9: 46279 | B9: Principal | C9: =A9&"|"&B9 -> 46279|Principal | D9: =SUMIFS('Valuación diaria'!$O$5:$O$354,'Valuación diaria'!$A$5:$A$354,A9,'Valuación diaria'!$B$5:$B$354,B9) -> 71116.266 | E9: =SUMIFS(Transacciones!$R$5:$R$20,Transacciones!$B$5:$B$20,B9,Transacciones!$F$5:$F$20,A9) -> 10339.9 | F9: =SUMIFS(Transacciones!$S$5:$S$20,Transacciones!$B$5:$B$20,B9,Transacciones!$F$5:$F$20,A9) -> 0 | G9: =SUMIFS('Valuación diaria'!$Q$5:$Q$354,'Valuación diaria'!$A$5:$A$354,A9,'Valuación diaria'!$B$5:$B$354,B9) -> 0 | H9: =F9+G9 -> 0 | I9: =IF(A9=Entradas!$B$8,"",D8) -> 60329.962 | J9: =IF(A9=Entradas!$B$8,"",I9+E9) -> 70669.862 | K9: =IF(A9=Entradas!$B$8,"",IF(J9=0,0,(D9+H9)/J9-1)) -> 0.006316745 | L9: =IF(A9=Entradas!$B$8,"",K9*100) -> 0.6316745 | M9: =IF(A9=Entradas!$B$8,1,M8*(1+K9)) -> 1.0126772 | N9: =IF(A9=Entradas!$B$8,1,MAX(N8,M9)) -> 1.0126772 | O9: =M9/N9-1 -> 0
A10: 46280 | B10: Principal | C10: =A10&"|"&B10 -> 46280|Principal | D10: =SUMIFS('Valuación diaria'!$O$5:$O$354,'Valuación diaria'!$A$5:$A$354,A10,'Valuación diaria'!$B$5:$B$354,B10) -> 71637.571 | E10: =SUMIFS(Transacciones!$R$5:$R$20,Transacciones!$B$5:$B$20,B10,Transacciones!$F$5:$F$20,A10) -> 0 | F10: =SUMIFS(Transacciones!$S$5:$S$20,Transacciones!$B$5:$B$20,B10,Transacciones!$F$5:$F$20,A10) -> 0 | G10: =SUMIFS('Valuación diaria'!$Q$5:$Q$354,'Valuación diaria'!$A$5:$A$354,A10,'Valuación diaria'!$B$5:$B$354,B10) -> 0 | H10: =F10+G10 -> 0 | I10: =IF(A10=Entradas!$B$8,"",D9) -> 71116.266 | J10: =IF(A10=Entradas!$B$8,"",I10+E10) -> 71116.266 | K10: =IF(A10=Entradas!$B$8,"",IF(J10=0,0,(D10+H10)/J10-1)) -> 0.0073303237 | L10: =IF(A10=Entradas!$B$8,"",K10*100) -> 0.73303237 | M10: =IF(A10=Entradas!$B$8,1,M9*(1+K10)) -> 1.0201004 | N10: =IF(A10=Entradas!$B$8,1,MAX(N9,M10)) -> 1.0201004 | O10: =M10/N10-1 -> 0
A11: 46281 | B11: Principal | C11: =A11&"|"&B11 -> 46281|Principal | D11: =SUMIFS('Valuación diaria'!$O$5:$O$354,'Valuación diaria'!$A$5:$A$354,A11,'Valuación diaria'!$B$5:$B$354,B11) -> 71641.877 | E11: =SUMIFS(Transacciones!$R$5:$R$20,Transacciones!$B$5:$B$20,B11,Transacciones!$F$5:$F$20,A11) -> 0 | F11: =SUMIFS(Transacciones!$S$5:$S$20,Transacciones!$B$5:$B$20,B11,Transacciones!$F$5:$F$20,A11) -> 0 | G11: =SUMIFS('Valuación diaria'!$Q$5:$Q$354,'Valuación diaria'!$A$5:$A$354,A11,'Valuación diaria'!$B$5:$B$354,B11) -> 0 | H11: =F11+G11 -> 0 | I11: =IF(A11=Entradas!$B$8,"",D10) -> 71637.571 | J11: =IF(A11=Entradas!$B$8,"",I11+E11) -> 71637.571 | K11: =IF(A11=Entradas!$B$8,"",IF(J11=0,0,(D11+H11)/J11-1)) -> 6.0115104e-05 | L11: =IF(A11=Entradas!$B$8,"",K11*100) -> 0.0060115104 | M11: =IF(A11=Entradas!$B$8,1,M10*(1+K11)) -> 1.0201618 | N11: =IF(A11=Entradas!$B$8,1,MAX(N10,M11)) -> 1.0201618 | O11: =M11/N11-1 -> 0
A12: 46282 | B12: Principal | C12: =A12&"|"&B12 -> 46282|Principal | D12: =SUMIFS('Valuación diaria'!$O$5:$O$354,'Valuación diaria'!$A$5:$A$354,A12,'Valuación diaria'!$B$5:$B$354,B12) -> 85262.085 | E12: =SUMIFS(Transacciones!$R$5:$R$20,Transacciones!$B$5:$B$20,B12,Transacciones!$F$5:$F$20,A12) -> 14665.9 | F12: =SUMIFS(Transacciones!$S$5:$S$20,Transacciones!$B$5:$B$20,B12,Transacciones!$F$5:$F$20,A12) -> 0 | G12: =SUMIFS('Valuación diaria'!$Q$5:$Q$354,'Valuación diaria'!$A$5:$A$354,A12,'Valuación diaria'!$B$5:$B$354,B12) -> 0 | H12: =F12+G12 -> 0 | I12: =IF(A12=Entradas!$B$8,"",D11) -> 71641.877 | J12: =IF(A12=Entradas!$B$8,"",I12+E12) -> 86307.777 | K12: =IF(A12=Entradas!$B$8,"",IF(J12=0,0,(D12+H12)/J12-1)) -> -0.012115849 | L12: =IF(A12=Entradas!$B$8,"",K12*100) -> -1.2115849 | M12: =IF(A12=Entradas!$B$8,1,M11*(1+K12)) -> 1.0078016 | N12: =IF(A12=Entradas!$B$8,1,MAX(N11,M12)) -> 1.0201618 | O12: =M12/N12-1 -> -0.012115849
A13: 46283 | B13: Principal | C13: =A13&"|"&B13 -> 46283|Principal | D13: =SUMIFS('Valuación diaria'!$O$5:$O$354,'Valuación diaria'!$A$5:$A$354,A13,'Valuación diaria'!$B$5:$B$354,B13) -> 83832.298 | E13: =SUMIFS(Transacciones!$R$5:$R$20,Transacciones!$B$5:$B$20,B13,Transacciones!$F$5:$F$20,A13) -> 0 | F13: =SUMIFS(Transacciones!$S$5:$S$20,Transacciones!$B$5:$B$20,B13,Transacciones!$F$5:$F$20,A13) -> 0 | G13: =SUMIFS('Valuación diaria'!$Q$5:$Q$354,'Valuación diaria'!$A$5:$A$354,A13,'Valuación diaria'!$B$5:$B$354,B13) -> 0 | H13: =F13+G13 -> 0 | I13: =IF(A13=Entradas!$B$8,"",D12) -> 85262.085 | J13: =IF(A13=Entradas!$B$8,"",I13+E13) -> 85262.085 | K13: =IF(A13=Entradas!$B$8,"",IF(J13=0,0,(D13+H13)/J13-1)) -> -0.016769313 | L13: =IF(A13=Entradas!$B$8,"",K13*100) -> -1.6769313 | M13: =IF(A13=Entradas!$B$8,1,M12*(1+K13)) -> 0.9909015 | N13: =IF(A13=Entradas!$B$8,1,MAX(N12,M13)) -> 1.0201618 | O13: =M13/N13-1 -> -0.028681988
A14: 46284 | B14: Principal | C14: =A14&"|"&B14 -> 46284|Principal | D14: =SUMIFS('Valuación diaria'!$O$5:$O$354,'Valuación diaria'!$A$5:$A$354,A14,'Valuación diaria'!$B$5:$B$354,B14) -> 83839.51 | E14: =SUMIFS(Transacciones!$R$5:$R$20,Transacciones!$B$5:$B$20,B14,Transacciones!$F$5:$F$20,A14) -> 0 | F14: =SUMIFS(Transacciones!$S$5:$S$20,Transacciones!$B$5:$B$20,B14,Transacciones!$F$5:$F$20,A14) -> 0 | G14: =SUMIFS('Valuación diaria'!$Q$5:$Q$354,'Valuación diaria'!$A$5:$A$354,A14,'Valuación diaria'!$B$5:$B$354,B14) -> 0 | H14: =F14+G14 -> 0 | I14: =IF(A14=Entradas!$B$8,"",D13) -> 83832.298 | J14: =IF(A14=Entradas!$B$8,"",I14+E14) -> 83832.298 | K14: =IF(A14=Entradas!$B$8,"",IF(J14=0,0,(D14+H14)/J14-1)) -> 8.6027702e-05 | L14: =IF(A14=Entradas!$B$8,"",K14*100) -> 0.0086027702 | M14: =IF(A14=Entradas!$B$8,1,M13*(1+K14)) -> 0.99098675 | N14: =IF(A14=Entradas!$B$8,1,MAX(N13,M14)) -> 1.0201618 | O14: =M14/N14-1 -> -0.028598427
A15: 46285 | B15: Principal | C15: =A15&"|"&B15 -> 46285|Principal | D15: =SUMIFS('Valuación diaria'!$O$5:$O$354,'Valuación diaria'!$A$5:$A$354,A15,'Valuación diaria'!$B$5:$B$354,B15) -> 83846.721 | E15: =SUMIFS(Transacciones!$R$5:$R$20,Transacciones!$B$5:$B$20,B15,Transacciones!$F$5:$F$20,A15) -> 0 | F15: =SUMIFS(Transacciones!$S$5:$S$20,Transacciones!$B$5:$B$20,B15,Transacciones!$F$5:$F$20,A15) -> 0 | G15: =SUMIFS('Valuación diaria'!$Q$5:$Q$354,'Valuación diaria'!$A$5:$A$354,A15,'Valuación diaria'!$B$5:$B$354,B15) -> 0 | H15: =F15+G15 -> 0 | I15: =IF(A15=Entradas!$B$8,"",D14) -> 83839.51 | J15: =IF(A15=Entradas!$B$8,"",I15+E15) -> 83839.51 | K15: =IF(A15=Entradas!$B$8,"",IF(J15=0,0,(D15+H15)/J15-1)) -> 8.60042e-05 | L15: =IF(A15=Entradas!$B$8,"",K15*100) -> 0.00860042 | M15: =IF(A15=Entradas!$B$8,1,M14*(1+K15)) -> 0.99107198 | N15: =IF(A15=Entradas!$B$8,1,MAX(N14,M15)) -> 1.0201618 | O15: =M15/N15-1 -> -0.028514883
A16: 46286 | B16: Principal | C16: =A16&"|"&B16 -> 46286|Principal | D16: =SUMIFS('Valuación diaria'!$O$5:$O$354,'Valuación diaria'!$A$5:$A$354,A16,'Valuación diaria'!$B$5:$B$354,B16) -> 82451.93 | E16: =SUMIFS(Transacciones!$R$5:$R$20,Transacciones!$B$5:$B$20,B16,Transacciones!$F$5:$F$20,A16) -> 0 | F16: =SUMIFS(Transacciones!$S$5:$S$20,Transacciones!$B$5:$B$20,B16,Transacciones!$F$5:$F$20,A16) -> 0 | G16: =SUMIFS('Valuación diaria'!$Q$5:$Q$354,'Valuación diaria'!$A$5:$A$354,A16,'Valuación diaria'!$B$5:$B$354,B16) -> 0 | H16: =F16+G16 -> 0 | I16: =IF(A16=Entradas!$B$8,"",D15) -> 83846.721 | J16: =IF(A16=Entradas!$B$8,"",I16+E16) -> 83846.721 | K16: =IF(A16=Entradas!$B$8,"",IF(J16=0,0,(D16+H16)/J16-1)) -> -0.016635012 | L16: =IF(A16=Entradas!$B$8,"",K16*100) -> -1.6635012 | M16: =IF(A16=Entradas!$B$8,1,M15*(1+K16)) -> 0.97458548 | N16: =IF(A16=Entradas!$B$8,1,MAX(N15,M16)) -> 1.0201618 | O16: =M16/N16-1 -> -0.044675549
... A74: 46309 | B74: Secundario | C74: =A74&"|"&B74 -> 46309|Secundario | D74: =SUMIFS('Valuación diaria'!$O$5:$O$354,'Valuación diaria'!$A$5:$A$354,A74,'Valuación diaria'!$B$5:$B$354,B74) -> 16657.5 | E74: =SUMIFS(Transacciones!$R$5:$R$20,Transacciones!$B$5:$B$20,B74,Transacciones!$F$5:$F$20,A74) -> 0 | F74: =SUMIFS(Transacciones!$S$5:$S$20,Transacciones!$B$5:$B$20,B74,Transacciones!$F$5:$F$20,A74) -> 0 | G74: =SUMIFS('Valuación diaria'!$Q$5:$Q$354,'Valuación diaria'!$A$5:$A$354,A74,'Valuación diaria'!$B$5:$B$354,B74) -> 0 | H74: =F74+G74 -> 0 | I74: =IF(A74=Entradas!$B$8,"",D73) -> 16380 | J74: =IF(A74=Entradas!$B$8,"",I74+E74) -> 16380 | K74: =IF(A74=Entradas!$B$8,"",IF(J74=0,0,(D74+H74)/J74-1)) -> 0.016941392 | L74: =IF(A74=Entradas!$B$8,"",K74*100) -> 1.6941392 | M74: =IF(A74=Entradas!$B$8,1,M73*(1+K74)) -> 1.0688114 | N74: =IF(A74=Entradas!$B$8,1,MAX(N73,M74)) -> 1.0688114 | O74: =M74/N74-1 -> 0

Sheet Periodos
A1: TWR y máxima caída por periodo (RF-09, RF-10)
A2: Cada bloque toma r(t) de la Serie. I = 1 en el cierre previo al inicio (primer máximo). TWR = Π(1 + r) − 1, sin anualizar, por dos caminos (índice final y PRODUCT); T lo recalcula con la Serie y las fechas de Entradas. Máxima caída = mín(I/máx) − 1. Pico: la primera fecha, contando la fecha base con I = 1, en que I alcanzó el máximo vigente en el valle (con empates, la más antigua). Valle: la primera fecha con la caída mínima. Los bloques tienen un largo fijo: cambiar inicio o fin exige regenerar el libro.
A4: periodo | B4: portafolio | C4: inicio | D4: fin | E4: fecha base (cierre previo) | F4: días | G4: V base | H4: V fin | I4: costo total al fin | J4: resultado no realizado al fin | K4: TWR (índice final − 1) | L4: TWR (PRODUCT − 1) | M4: TWR (%) | N4: máxima caída (fracción) | O4: máxima caída (%) | P4: fecha del valle | Q4: máximo vigente en el valle | R4: fecha del pico | S4: |diferencia entre los dos TWR| | T4: TWR por la Serie: I(fin) / I(base) − 1
A5: =Entradas!$A$21 -> P1-A | B5: =Entradas!$B$21 -> Principal | C5: =Entradas!$C$21 -> 46276 | D5: =Entradas!$D$21 -> 46309 | E5: =C5-1 -> 46275 | F5: =D5-C5+1 -> 34 | G5: =SUMIFS(Serie!$D$5:$D$74,Serie!$A$5:$A$74,E5,Serie!$B$5:$B$74,B5) -> 49929.06 | H5: =SUMIFS(Serie!$D$5:$D$74,Serie!$A$5:$A$74,D5,Serie!$B$5:$B$74,B5) -> 58940.878 | I5: =SUMIFS('Valuación diaria'!$L$5:$L$354,'Valuación diaria'!$A$5:$A$354,D5,'Valuación diaria'!$B$5:$B$354,B5) -> 56307.888 | J5: =SUMIFS('Valuación diaria'!$P$5:$P$354,'Valuación diaria'!$A$5:$A$354,D5,'Valuación diaria'!$B$5:$B$354,B5) -> 2632.9899 | K5: =D48-1 -> 0.043928084 | L5: =PRODUCT(C15:C48)-1 -> 0.043928084 | M5: =K5*100 -> 4.3928084 | N5: =MIN(F15:F48) -> -0.066804772 | O5: =N5*100 -> -6.6804772 | P5: =IF(N5=0,"",INDEX(A15:A48,MATCH(N5,F15:F48,0))) -> 46288 | Q5: =IF(N5=0,"",INDEX(E15:E48,MATCH(N5,F15:F48,0))) -> 1.0201618 | R5: =IF(N5=0,"",IF(Q5=1,E5,INDEX(A15:A48,MATCH(Q5,D15:D48,0)))) -> 46281 | S5: =ABS(K5-L5) -> 0 | T5: =INDEX(Serie!$M$5:$M$74,MATCH(D5&"|"&B5,Serie!$C$5:$C$74,0))/INDEX(Serie!$M$5:$M$74,MATCH(E5&"|"&B5,Serie!$C$5:$C$74,0))-1 -> 0.043928084
A6: =Entradas!$A$22 -> P1-B | B6: =Entradas!$B$22 -> Principal | C6: =Entradas!$C$22 -> 46276 | D6: =Entradas!$D$22 -> 46295 | E6: =C6-1 -> 46275 | F6: =D6-C6+1 -> 20 | G6: =SUMIFS(Serie!$D$5:$D$74,Serie!$A$5:$A$74,E6,Serie!$B$5:$B$74,B6) -> 49929.06 | H6: =SUMIFS(Serie!$D$5:$D$74,Serie!$A$5:$A$74,D6,Serie!$B$5:$B$74,B6) -> 73866.026 | I6: =SUMIFS('Valuación diaria'!$L$5:$L$354,'Valuación diaria'!$A$5:$A$354,D6,'Valuación diaria'!$B$5:$B$354,B6) -> 71908.29 | J6: =SUMIFS('Valuación diaria'!$P$5:$P$354,'Valuación diaria'!$A$5:$A$354,D6,'Valuación diaria'!$B$5:$B$354,B6) -> 1957.7358 | K6: =D72-1 -> 0.025044992 | L6: =PRODUCT(C53:C72)-1 -> 0.025044992 | M6: =K6*100 -> 2.5044992 | N6: =MIN(F53:F72) -> -0.066804772 | O6: =N6*100 -> -6.6804772 | P6: =IF(N6=0,"",INDEX(A53:A72,MATCH(N6,F53:F72,0))) -> 46288 | Q6: =IF(N6=0,"",INDEX(E53:E72,MATCH(N6,F53:F72,0))) -> 1.0201618 | R6: =IF(N6=0,"",IF(Q6=1,E6,INDEX(A53:A72,MATCH(Q6,D53:D72,0)))) -> 46281 | S6: =ABS(K6-L6) -> 0 | T6: =INDEX(Serie!$M$5:$M$74,MATCH(D6&"|"&B6,Serie!$C$5:$C$74,0))/INDEX(Serie!$M$5:$M$74,MATCH(E6&"|"&B6,Serie!$C$5:$C$74,0))-1 -> 0.025044992
A7: =Entradas!$A$23 -> P1-C | B7: =Entradas!$B$23 -> Principal | C7: =Entradas!$C$23 -> 46296 | D7: =Entradas!$D$23 -> 46309 | E7: =C7-1 -> 46295 | F7: =D7-C7+1 -> 14 | G7: =SUMIFS(Serie!$D$5:$D$74,Serie!$A$5:$A$74,E7,Serie!$B$5:$B$74,B7) -> 73866.026 | H7: =SUMIFS(Serie!$D$5:$D$74,Serie!$A$5:$A$74,D7,Serie!$B$5:$B$74,B7) -> 58940.878 | I7: =SUMIFS('Valuación diaria'!$L$5:$L$354,'Valuación diaria'!$A$5:$A$354,D7,'Valuación diaria'!$B$5:$B$354,B7) -> 56307.888 | J7: =SUMIFS('Valuación diaria'!$P$5:$P$354,'Valuación diaria'!$A$5:$A$354,D7,'Valuación diaria'!$B$5:$B$354,B7) -> 2632.9899 | K7: =D90-1 -> 0.01842172 | L7: =PRODUCT(C77:C90)-1 -> 0.01842172 | M7: =K7*100 -> 1.842172 | N7: =MIN(F77:F90) -> -0.021810296 | O7: =N7*100 -> -2.1810296 | P7: =IF(N7=0,"",INDEX(A77:A90,MATCH(N7,F77:F90,0))) -> 46300 | Q7: =IF(N7=0,"",INDEX(E77:E90,MATCH(N7,F77:F90,0))) -> 1 | R7: =IF(N7=0,"",IF(Q7=1,E7,INDEX(A77:A90,MATCH(Q7,D77:D90,0)))) -> 46295 | S7: =ABS(K7-L7) -> 0 | T7: =INDEX(Serie!$M$5:$M$74,MATCH(D7&"|"&B7,Serie!$C$5:$C$74,0))/INDEX(Serie!$M$5:$M$74,MATCH(E7&"|"&B7,Serie!$C$5:$C$74,0))-1 -> 0.01842172
A8: =Entradas!$A$24 -> P1-D | B8: =Entradas!$B$24 -> Principal | C8: =Entradas!$C$24 -> 46304 | D8: =Entradas!$D$24 -> 46307 | E8: =C8-1 -> 46303 | F8: =D8-C8+1 -> 4 | G8: =SUMIFS(Serie!$D$5:$D$74,Serie!$A$5:$A$74,E8,Serie!$B$5:$B$74,B8) -> 57842.72 | H8: =SUMIFS(Serie!$D$5:$D$74,Serie!$A$5:$A$74,D8,Serie!$B$5:$B$74,B8) -> 58708.694 | I8: =SUMIFS('Valuación diaria'!$L$5:$L$354,'Valuación diaria'!$A$5:$A$354,D8,'Valuación diaria'!$B$5:$B$354,B8) -> 56307.888 | J8: =SUMIFS('Valuación diaria'!$P$5:$P$354,'Valuación diaria'!$A$5:$A$354,D8,'Valuación diaria'!$B$5:$B$354,B8) -> 2400.8057 | K8: =D98-1 -> 0.014971188 | L8: =PRODUCT(C95:C98)-1 -> 0.014971188 | M8: =K8*100 -> 1.4971188 | N8: =MIN(F95:F98) -> 0 | O8: =N8*100 -> 0 | P8: =IF(N8=0,"",INDEX(A95:A98,MATCH(N8,F95:F98,0))) | Q8: =IF(N8=0,"",INDEX(E95:E98,MATCH(N8,F95:F98,0))) | R8: =IF(N8=0,"",IF(Q8=1,E8,INDEX(A95:A98,MATCH(Q8,D95:D98,0)))) | S8: =ABS(K8-L8) -> 0 | T8: =INDEX(Serie!$M$5:$M$74,MATCH(D8&"|"&B8,Serie!$C$5:$C$74,0))/INDEX(Serie!$M$5:$M$74,MATCH(E8&"|"&B8,Serie!$C$5:$C$74,0))-1 -> 0.014971188
A9: =Entradas!$A$25 -> P2-A | B9: =Entradas!$B$25 -> Secundario | C9: =Entradas!$C$25 -> 46276 | D9: =Entradas!$D$25 -> 46309 | E9: =C9-1 -> 46275 | F9: =D9-C9+1 -> 34 | G9: =SUMIFS(Serie!$D$5:$D$74,Serie!$A$5:$A$74,E9,Serie!$B$5:$B$74,B9) -> 0 | H9: =SUMIFS(Serie!$D$5:$D$74,Serie!$A$5:$A$74,D9,Serie!$B$5:$B$74,B9) -> 16657.5 | I9: =SUMIFS('Valuación diaria'!$L$5:$L$354,'Valuación diaria'!$A$5:$A$354,D9,'Valuación diaria'!$B$5:$B$354,B9) -> 15585.07 | J9: =SUMIFS('Valuación diaria'!$P$5:$P$354,'Valuación diaria'!$A$5:$A$354,D9,'Valuación diaria'!$B$5:$B$354,B9) -> 1072.43 | K9: =D136-1 -> 0.068811369 | L9: =PRODUCT(C103:C136)-1 -> 0.068811369 | M9: =K9*100 -> 6.8811369 | N9: =MIN(F103:F136) -> -0.13675418 | O9: =N9*100 -> -13.675418 | P9: =IF(N9=0,"",INDEX(A103:A136,MATCH(N9,F103:F136,0))) -> 46288 | Q9: =IF(N9=0,"",INDEX(E103:E136,MATCH(N9,F103:F136,0))) -> 1.0081764 | R9: =IF(N9=0,"",IF(Q9=1,E9,INDEX(A103:A136,MATCH(Q9,D103:D136,0)))) -> 46280 | S9: =ABS(K9-L9) -> 0 | T9: =INDEX(Serie!$M$5:$M$74,MATCH(D9&"|"&B9,Serie!$C$5:$C$74,0))/INDEX(Serie!$M$5:$M$74,MATCH(E9&"|"&B9,Serie!$C$5:$C$74,0))-1 -> 0.068811369
A10: =Entradas!$A$26 -> P2-C | B10: =Entradas!$B$26 -> Secundario | C10: =Entradas!$C$26 -> 46296 | D10: =Entradas!$D$26 -> 46309 | E10: =C10-1 -> 46295 | F10: =D10-C10+1 -> 14 | G10: =SUMIFS(Serie!$D$5:$D$74,Serie!$A$5:$A$74,E10,Serie!$B$5:$B$74,B10) -> 16065 | H10: =SUMIFS(Serie!$D$5:$D$74,Serie!$A$5:$A$74,D10,Serie!$B$5:$B$74,B10) -> 16657.5 | I10: =SUMIFS('Valuación diaria'!$L$5:$L$354,'Valuación diaria'!$A$5:$A$354,D10,'Valuación diaria'!$B$5:$B$354,B10) -> 15585.07 | J10: =SUMIFS('Valuación diaria'!$P$5:$P$354,'Valuación diaria'!$A$5:$A$354,D10,'Valuación diaria'!$B$5:$B$354,B10) -> 1072.43 | K10: =D154-1 -> 0.036881419 | L10: =PRODUCT(C141:C154)-1 -> 0.036881419 | M10: =K10*100 -> 3.6881419 | N10: =MIN(F141:F154) -> -0.050887021 | O10: =N10*100 -> -5.0887021 | P10: =IF(N10=0,"",INDEX(A141:A154,MATCH(N10,F141:F154,0))) -> 46300 | Q10: =IF(N10=0,"",INDEX(E141:E154,MATCH(N10,F141:F154,0))) -> 1 | R10: =IF(N10=0,"",IF(Q10=1,E10,INDEX(A141:A154,MATCH(Q10,D141:D154,0)))) -> 46295 | S10: =ABS(K10-L10) -> 0 | T10: =INDEX(Serie!$M$5:$M$74,MATCH(D10&"|"&B10,Serie!$C$5:$C$74,0))/INDEX(Serie!$M$5:$M$74,MATCH(E10&"|"&B10,Serie!$C$5:$C$74,0))-1 -> 0.036881419
A13: Periodo P1-A
A14: fecha | B14: r(t) | C14: 1 + r(t) | D14: I(t) | E14: máximo (con I = 1 inicial) | F14: caída I/máx − 1
A15: =$C$5 -> 46276 | B15: =INDEX(Serie!$K$5:$K$74,MATCH(A15&"|"&$B$5,Serie!$C$5:$C$74,0)) -> 0.006177028 | C15: =1+B15 -> 1.006177 | D15: =C15 -> 1.006177 | E15: =MAX(1,D15) -> 1.006177 | F15: =D15/E15-1 -> 0
A16: =A15+1 -> 46277 | B16: =INDEX(Serie!$K$5:$K$74,MATCH(A16&"|"&$B$5,Serie!$C$5:$C$74,0)) -> 7.1293155e-05 | C16: =1+B16 -> 1.0000713 | D16: =D15*C16 -> 1.0062488 | E16: =MAX(E15,D16) -> 1.0062488 | F16: =D16/E16-1 -> 0
A17: =A16+1 -> 46278 | B17: =INDEX(Serie!$K$5:$K$74,MATCH(A17&"|"&$B$5,Serie!$C$5:$C$74,0)) -> 7.1317082e-05 | C17: =1+B17 -> 1.0000713 | D17: =D16*C17 -> 1.0063205 | E17: =MAX(E16,D17) -> 1.0063205 | F17: =D17/E17-1 -> 0
A18: =A17+1 -> 46279 | B18: =INDEX(Serie!$K$5:$K$74,MATCH(A18&"|"&$B$5,Serie!$C$5:$C$74,0)) -> 0.006316745 | C18: =1+B18 -> 1.0063167 | D18: =D17*C18 -> 1.0126772 | E18: =MAX(E17,D18) -> 1.0126772 | F18: =D18/E18-1 -> 0
A19: =A18+1 -> 46280 | B19: =INDEX(Serie!$K$5:$K$74,MATCH(A19&"|"&$B$5,Serie!$C$5:$C$74,0)) -> 0.0073303237 | C19: =1+B19 -> 1.0073303 | D19: =D18*C19 -> 1.0201004 | E19: =MAX(E18,D19) -> 1.0201004 | F19: =D19/E19-1 -> 0
A20: =A19+1 -> 46281 | B20: =INDEX(Serie!$K$5:$K$74,MATCH(A20&"|"&$B$5,Serie!$C$5:$C$74,0)) -> 6.0115104e-05 | C20: =1+B20 -> 1.0000601 | D20: =D19*C20 -> 1.0201618 | E20: =MAX(E19,D20) -> 1.0201618 | F20: =D20/E20-1 -> 0
A21: =A20+1 -> 46282 | B21: =INDEX(Serie!$K$5:$K$74,MATCH(A21&"|"&$B$5,Serie!$C$5:$C$74,0)) -> -0.012115849 | C21: =1+B21 -> 0.98788415 | D21: =D20*C21 -> 1.0078016 | E21: =MAX(E20,D21) -> 1.0201618 | F21: =D21/E21-1 -> -0.012115849
A22: =A21+1 -> 46283 | B22: =INDEX(Serie!$K$5:$K$74,MATCH(A22&"|"&$B$5,Serie!$C$5:$C$74,0)) -> -0.016769313 | C22: =1+B22 -> 0.98323069 | D22: =D21*C22 -> 0.9909015 | E22: =MAX(E21,D22) -> 1.0201618 | F22: =D22/E22-1 -> -0.028681988
A23: =A22+1 -> 46284 | B23: =INDEX(Serie!$K$5:$K$74,MATCH(A23&"|"&$B$5,Serie!$C$5:$C$74,0)) -> 8.6027702e-05 | C23: =1+B23 -> 1.000086 | D23: =D22*C23 -> 0.99098675 | E23: =MAX(E22,D23) -> 1.0201618 | F23: =D23/E23-1 -> -0.028598427
A24: =A23+1 -> 46285 | B24: =INDEX(Serie!$K$5:$K$74,MATCH(A24&"|"&$B$5,Serie!$C$5:$C$74,0)) -> 8.60042e-05 | C24: =1+B24 -> 1.000086 | D24: =D23*C24 -> 0.99107198 | E24: =MAX(E23,D24) -> 1.0201618 | F24: =D24/E24-1 -> -0.028514883
A25: =A24+1 -> 46286 | B25: =INDEX(Serie!$K$5:$K$74,MATCH(A25&"|"&$B$5,Serie!$C$5:$C$74,0)) -> -0.016635012 | C25: =1+B25 -> 0.98336499 | D25: =D24*C25 -> 0.97458548 | E25: =MAX(E24,D25) -> 1.0201618 | F25: =D25/E25-1 -> -0.044675549
A26: =A25+1 -> 46287 | B26: =INDEX(Serie!$K$5:$K$74,MATCH(A26&"|"&$B$5,Serie!$C$5:$C$74,0)) -> -0.015193249 | C26: =1+B26 -> 0.98480675 | D26: =D25*C26 -> 0.95977836 | E26: =MAX(E25,D26) -> 1.0201618 | F26: =D26/E26-1 -> -0.059190032
A27: =A26+1 -> 46288 | B27: =INDEX(Serie!$K$5:$K$74,MATCH(A27&"|"&$B$5,Serie!$C$5:$C$74,0)) -> -0.0080938137 | C27: =1+B27 -> 0.99190619 | D27: =D26*C27 -> 0.95201009 | E27: =MAX(E26,D27) -> 1.0201618 | F27: =D27/E27-1 -> -0.066804772
... A48: =A47+1 -> 46309 | B48: =INDEX(Serie!$K$5:$K$74,MATCH(A48&"|"&$B$5,Serie!$C$5:$C$74,0)) -> 0.0091032754 | C48: =1+B48 -> 1.0091033 | D48: =D47*C48 -> 1.0439281 | E48: =MAX(E47,D48) -> 1.0439281 | F48: =D48/E48-1 -> 0
A51: Periodo P1-B
A52: fecha | B52: r(t) | C52: 1 + r(t) | D52: I(t) | E52: máximo (con I = 1 inicial) | F52: caída I/máx − 1
A53: =$C$6 -> 46276 | B53: =INDEX(Serie!$K$5:$K$74,MATCH(A53&"|"&$B$6,Serie!$C$5:$C$74,0)) -> 0.006177028 | C53: =1+B53 -> 1.006177 | D53: =C53 -> 1.006177 | E53: =MAX(1,D53) -> 1.006177 | F53: =D53/E53-1 -> 0
A54: =A53+1 -> 46277 | B54: =INDEX(Serie!$K$5:$K$74,MATCH(A54&"|"&$B$6,Serie!$C$5:$C$74,0)) -> 7.1293155e-05 | C54: =1+B54 -> 1.0000713 | D54: =D53*C54 -> 1.0062488 | E54: =MAX(E53,D54) -> 1.0062488 | F54: =D54/E54-1 -> 0
A55: =A54+1 -> 46278 | B55: =INDEX(Serie!$K$5:$K$74,MATCH(A55&"|"&$B$6,Serie!$C$5:$C$74,0)) -> 7.1317082e-05 | C55: =1+B55 -> 1.0000713 | D55: =D54*C55 -> 1.0063205 | E55: =MAX(E54,D55) -> 1.0063205 | F55: =D55/E55-1 -> 0
A56: =A55+1 -> 46279 | B56: =INDEX(Serie!$K$5:$K$74,MATCH(A56&"|"&$B$6,Serie!$C$5:$C$74,0)) -> 0.006316745 | C56: =1+B56 -> 1.0063167 | D56: =D55*C56 -> 1.0126772 | E56: =MAX(E55,D56) -> 1.0126772 | F56: =D56/E56-1 -> 0
A57: =A56+1 -> 46280 | B57: =INDEX(Serie!$K$5:$K$74,MATCH(A57&"|"&$B$6,Serie!$C$5:$C$74,0)) -> 0.0073303237 | C57: =1+B57 -> 1.0073303 | D57: =D56*C57 -> 1.0201004 | E57: =MAX(E56,D57) -> 1.0201004 | F57: =D57/E57-1 -> 0
A58: =A57+1 -> 46281 | B58: =INDEX(Serie!$K$5:$K$74,MATCH(A58&"|"&$B$6,Serie!$C$5:$C$74,0)) -> 6.0115104e-05 | C58: =1+B58 -> 1.0000601 | D58: =D57*C58 -> 1.0201618 | E58: =MAX(E57,D58) -> 1.0201618 | F58: =D58/E58-1 -> 0
A59: =A58+1 -> 46282 | B59: =INDEX(Serie!$K$5:$K$74,MATCH(A59&"|"&$B$6,Serie!$C$5:$C$74,0)) -> -0.012115849 | C59: =1+B59 -> 0.98788415 | D59: =D58*C59 -> 1.0078016 | E59: =MAX(E58,D59) -> 1.0201618 | F59: =D59/E59-1 -> -0.012115849
A60: =A59+1 -> 46283 | B60: =INDEX(Serie!$K$5:$K$74,MATCH(A60&"|"&$B$6,Serie!$C$5:$C$74,0)) -> -0.016769313 | C60: =1+B60 -> 0.98323069 | D60: =D59*C60 -> 0.9909015 | E60: =MAX(E59,D60) -> 1.0201618 | F60: =D60/E60-1 -> -0.028681988
A61: =A60+1 -> 46284 | B61: =INDEX(Serie!$K$5:$K$74,MATCH(A61&"|"&$B$6,Serie!$C$5:$C$74,0)) -> 8.6027702e-05 | C61: =1+B61 -> 1.000086 | D61: =D60*C61 -> 0.99098675 | E61: =MAX(E60,D61) -> 1.0201618 | F61: =D61/E61-1 -> -0.028598427
A62: =A61+1 -> 46285 | B62: =INDEX(Serie!$K$5:$K$74,MATCH(A62&"|"&$B$6,Serie!$C$5:$C$74,0)) -> 8.60042e-05 | C62: =1+B62 -> 1.000086 | D62: =D61*C62 -> 0.99107198 | E62: =MAX(E61,D62) -> 1.0201618 | F62: =D62/E62-1 -> -0.028514883
A63: =A62+1 -> 46286 | B63: =INDEX(Serie!$K$5:$K$74,MATCH(A63&"|"&$B$6,Serie!$C$5:$C$74,0)) -> -0.016635012 | C63: =1+B63 -> 0.98336499 | D63: =D62*C63 -> 0.97458548 | E63: =MAX(E62,D63) -> 1.0201618 | F63: =D63/E63-1 -> -0.044675549
A64: =A63+1 -> 46287 | B64: =INDEX(Serie!$K$5:$K$74,MATCH(A64&"|"&$B$6,Serie!$C$5:$C$74,0)) -> -0.015193249 | C64: =1+B64 -> 0.98480675 | D64: =D63*C64 -> 0.95977836 | E64: =MAX(E63,D64) -> 1.0201618 | F64: =D64/E64-1 -> -0.059190032
A65: =A64+1 -> 46288 | B65: =INDEX(Serie!$K$5:$K$74,MATCH(A65&"|"&$B$6,Serie!$C$5:$C$74,0)) -> -0.0080938137 | C65: =1+B65 -> 0.99190619 | D65: =D64*C65 -> 0.95201009 | E65: =MAX(E64,D65) -> 1.0201618 | F65: =D65/E65-1 -> -0.066804772
... A72: =A71+1 -> 46295 | B72: =INDEX(Serie!$K$5:$K$74,MATCH(A72&"|"&$B$6,Serie!$C$5:$C$74,0)) -> 0.016695018 | C72: =1+B72 -> 1.016695 | D72: =D71*C72 -> 1.025045 | E72: =MAX(E71,D72) -> 1.025045 | F72: =D72/E72-1 -> 0
A75: Periodo P1-C
A76: fecha | B76: r(t) | C76: 1 + r(t) | D76: I(t) | E76: máximo (con I = 1 inicial) | F76: caída I/máx − 1
A77: =$C$7 -> 46296 | B77: =INDEX(Serie!$K$5:$K$74,MATCH(A77&"|"&$B$7,Serie!$C$5:$C$74,0)) -> -0.0073298529 | C77: =1+B77 -> 0.99267015 | D77: =C77 -> 0.99267015 | E77: =MAX(1,D77) -> 1 | F77: =D77/E77-1 -> -0.0073298529
A78: =A77+1 -> 46297 | B78: =INDEX(Serie!$K$5:$K$74,MATCH(A78&"|"&$B$7,Serie!$C$5:$C$74,0)) -> -0.0065922835 | C78: =1+B78 -> 0.99340772 | D78: =D77*C78 -> 0.98612618 | E78: =MAX(E77,D78) -> 1 | F78: =D78/E78-1 -> -0.013873816
A79: =A78+1 -> 46298 | B79: =INDEX(Serie!$K$5:$K$74,MATCH(A79&"|"&$B$7,Serie!$C$5:$C$74,0)) -> 0.00010595175 | C79: =1+B79 -> 1.000106 | D79: =D78*C79 -> 0.98623067 | E79: =MAX(E78,D79) -> 1 | F79: =D79/E79-1 -> -0.013769334
A80: =A79+1 -> 46299 | B80: =INDEX(Serie!$K$5:$K$74,MATCH(A80&"|"&$B$7,Serie!$C$5:$C$74,0)) -> 0.00010586835 | C80: =1+B80 -> 1.0001059 | D80: =D79*C80 -> 0.98633508 | E80: =MAX(E79,D80) -> 1 | F80: =D80/E80-1 -> -0.013664924
A81: =A80+1 -> 46300 | B81: =INDEX(Serie!$K$5:$K$74,MATCH(A81&"|"&$B$7,Serie!$C$5:$C$74,0)) -> -0.0082582208 | C81: =1+B81 -> 0.99174178 | D81: =D80*C81 -> 0.9781897 | E81: =MAX(E80,D81) -> 1 | F81: =D81/E81-1 -> -0.021810296
A82: =A81+1 -> 46301 | B82: =INDEX(Serie!$K$5:$K$74,MATCH(A82&"|"&$B$7,Serie!$C$5:$C$74,0)) -> 0.0048091408 | C82: =1+B82 -> 1.0048091 | D82: =D81*C82 -> 0.98289396 | E82: =MAX(E81,D82) -> 1 | F82: =D82/E82-1 -> -0.017106044
A83: =A82+1 -> 46302 | B83: =INDEX(Serie!$K$5:$K$74,MATCH(A83&"|"&$B$7,Serie!$C$5:$C$74,0)) -> 0.0092940742 | C83: =1+B83 -> 1.0092941 | D83: =D82*C83 -> 0.99202905 | E83: =MAX(E82,D83) -> 1 | F83: =D83/E83-1 -> -0.007970955
A84: =A83+1 -> 46303 | B84: =INDEX(Serie!$K$5:$K$74,MATCH(A84&"|"&$B$7,Serie!$C$5:$C$74,0)) -> 0.0074775278 | C84: =1+B84 -> 1.0074775 | D84: =D83*C84 -> 0.99944697 | E84: =MAX(E83,D84) -> 1 | F84: =D84/E84-1 -> -0.00055303024
A85: =A84+1 -> 46304 | B85: =INDEX(Serie!$K$5:$K$74,MATCH(A85&"|"&$B$7,Serie!$C$5:$C$74,0)) -> 0.0089369596 | C85: =1+B85 -> 1.008937 | D85: =D84*C85 -> 1.008379 | E85: =MAX(E84,D85) -> 1.008379 | F85: =D85/E85-1 -> 0
A86: =A85+1 -> 46305 | B86: =INDEX(Serie!$K$5:$K$74,MATCH(A86&"|"&$B$7,Serie!$C$5:$C$74,0)) -> 7.8536273e-05 | C86: =1+B86 -> 1.0000785 | D86: =D85*C86 -> 1.0084582 | E86: =MAX(E85,D86) -> 1.0084582 | F86: =D86/E86-1 -> 0
A87: =A86+1 -> 46306 | B87: =INDEX(Serie!$K$5:$K$74,MATCH(A87&"|"&$B$7,Serie!$C$5:$C$74,0)) -> 7.845129e-05 | C87: =1+B87 -> 1.0000785 | D87: =D86*C87 -> 1.0085373 | E87: =MAX(E86,D87) -> 1.0085373 | F87: =D87/E87-1 -> 0
A88: =A87+1 -> 46307 | B88: =INDEX(Serie!$K$5:$K$74,MATCH(A88&"|"&$B$7,Serie!$C$5:$C$74,0)) -> 0.0058228709 | C88: =1+B88 -> 1.0058229 | D88: =D87*C88 -> 1.0144099 | E88: =MAX(E87,D88) -> 1.0144099 | F88: =D88/E88-1 -> 0
A89: =A88+1 -> 46308 | B89: =INDEX(Serie!$K$5:$K$74,MATCH(A89&"|"&$B$7,Serie!$C$5:$C$74,0)) -> -0.0051019777 | C89: =1+B89 -> 0.99489802 | D89: =D88*C89 -> 1.0092344 | E89: =MAX(E88,D89) -> 1.0144099 | F89: =D89/E89-1 -> -0.0051019777
A90: =A89+1 -> 46309 | B90: =INDEX(Serie!$K$5:$K$74,MATCH(A90&"|"&$B$7,Serie!$C$5:$C$74,0)) -> 0.0091032754 | C90: =1+B90 -> 1.0091033 | D90: =D89*C90 -> 1.0184217 | E90: =MAX(E89,D90) -> 1.0184217 | F90: =D90/E90-1 -> 0
A93: Periodo P1-D
A94: fecha | B94: r(t) | C94: 1 + r(t) | D94: I(t) | E94: máximo (con I = 1 inicial) | F94: caída I/máx − 1
A95: =$C$8 -> 46304 | B95: =INDEX(Serie!$K$5:$K$74,MATCH(A95&"|"&$B$8,Serie!$C$5:$C$74,0)) -> 0.0089369596 | C95: =1+B95 -> 1.008937 | D95: =C95 -> 1.008937 | E95: =MAX(1,D95) -> 1.008937 | F95: =D95/E95-1 -> 0
A96: =A95+1 -> 46305 | B96: =INDEX(Serie!$K$5:$K$74,MATCH(A96&"|"&$B$8,Serie!$C$5:$C$74,0)) -> 7.8536273e-05 | C96: =1+B96 -> 1.0000785 | D96: =D95*C96 -> 1.0090162 | E96: =MAX(E95,D96) -> 1.0090162 | F96: =D96/E96-1 -> 0
A97: =A96+1 -> 46306 | B97: =INDEX(Serie!$K$5:$K$74,MATCH(A97&"|"&$B$8,Serie!$C$5:$C$74,0)) -> 7.845129e-05 | C97: =1+B97 -> 1.0000785 | D97: =D96*C97 -> 1.0090954 | E97: =MAX(E96,D97) -> 1.0090954 | F97: =D97/E97-1 -> 0
A98: =A97+1 -> 46307 | B98: =INDEX(Serie!$K$5:$K$74,MATCH(A98&"|"&$B$8,Serie!$C$5:$C$74,0)) -> 0.0058228709 | C98: =1+B98 -> 1.0058229 | D98: =D97*C98 -> 1.0149712 | E98: =MAX(E97,D98) -> 1.0149712 | F98: =D98/E98-1 -> 0
A101: Periodo P2-A
A102: fecha | B102: r(t) | C102: 1 + r(t) | D102: I(t) | E102: máximo (con I = 1 inicial) | F102: caída I/máx − 1
A103: =$C$9 -> 46276 | B103: =INDEX(Serie!$K$5:$K$74,MATCH(A103&"|"&$B$9,Serie!$C$5:$C$74,0)) -> 0 | C103: =1+B103 -> 1 | D103: =C103 -> 1 | E103: =MAX(1,D103) -> 1 | F103: =D103/E103-1 -> 0
A104: =A103+1 -> 46277 | B104: =INDEX(Serie!$K$5:$K$74,MATCH(A104&"|"&$B$9,Serie!$C$5:$C$74,0)) -> 0 | C104: =1+B104 -> 1 | D104: =D103*C104 -> 1 | E104: =MAX(E103,D104) -> 1 | F104: =D104/E104-1 -> 0
A105: =A104+1 -> 46278 | B105: =INDEX(Serie!$K$5:$K$74,MATCH(A105&"|"&$B$9,Serie!$C$5:$C$74,0)) -> 0 | C105: =1+B105 -> 1 | D105: =D104*C105 -> 1 | E105: =MAX(E104,D105) -> 1 | F105: =D105/E105-1 -> 0
A106: =A105+1 -> 46279 | B106: =INDEX(Serie!$K$5:$K$74,MATCH(A106&"|"&$B$9,Serie!$C$5:$C$74,0)) -> -0.0048167894 | C106: =1+B106 -> 0.99518321 | D106: =D105*C106 -> 0.99518321 | E106: =MAX(E105,D106) -> 1 | F106: =D106/E106-1 -> -0.0048167894
A107: =A106+1 -> 46280 | B107: =INDEX(Serie!$K$5:$K$74,MATCH(A107&"|"&$B$9,Serie!$C$5:$C$74,0)) -> 0.013056093 | C107: =1+B107 -> 1.0130561 | D107: =D106*C107 -> 1.0081764 | E107: =MAX(E106,D107) -> 1.0081764 | F107: =D107/E107-1 -> 0
A108: =A107+1 -> 46281 | B108: =INDEX(Serie!$K$5:$K$74,MATCH(A108&"|"&$B$9,Serie!$C$5:$C$74,0)) -> 0 | C108: =1+B108 -> 1 | D108: =D107*C108 -> 1.0081764 | E108: =MAX(E107,D108) -> 1.0081764 | F108: =D108/E108-1 -> 0
A109: =A108+1 -> 46282 | B109: =INDEX(Serie!$K$5:$K$74,MATCH(A109&"|"&$B$9,Serie!$C$5:$C$74,0)) -> -0.025298329 | C109: =1+B109 -> 0.97470167 | D109: =D108*C109 -> 0.98267124 | E109: =MAX(E108,D109) -> 1.0081764 | F109: =D109/E109-1 -> -0.025298329
A110: =A109+1 -> 46283 | B110: =INDEX(Serie!$K$5:$K$74,MATCH(A110&"|"&$B$9,Serie!$C$5:$C$74,0)) -> -0.033790402 | C110: =1+B110 -> 0.9662096 | D110: =D109*C110 -> 0.94946638 | E110: =MAX(E109,D110) -> 1.0081764 | F110: =D110/E110-1 -> -0.05823389
A111: =A110+1 -> 46284 | B111: =INDEX(Serie!$K$5:$K$74,MATCH(A111&"|"&$B$9,Serie!$C$5:$C$74,0)) -> 0 | C111: =1+B111 -> 1 | D111: =D110*C111 -> 0.94946638 | E111: =MAX(E110,D111) -> 1.0081764 | F111: =D111/E111-1 -> -0.05823389
A112: =A111+1 -> 46285 | B112: =INDEX(Serie!$K$5:$K$74,MATCH(A112&"|"&$B$9,Serie!$C$5:$C$74,0)) -> 0 | C112: =1+B112 -> 1 | D112: =D111*C112 -> 0.94946638 | E112: =MAX(E111,D112) -> 1.0081764 | F112: =D112/E112-1 -> -0.05823389
A113: =A112+1 -> 46286 | B113: =INDEX(Serie!$K$5:$K$74,MATCH(A113&"|"&$B$9,Serie!$C$5:$C$74,0)) -> -0.033958439 | C113: =1+B113 -> 0.96604156 | D113: =D112*C113 -> 0.91722398 | E113: =MAX(E112,D113) -> 1.0081764 | F113: =D113/E113-1 -> -0.090214797
A114: =A113+1 -> 46287 | B114: =INDEX(Serie!$K$5:$K$74,MATCH(A114&"|"&$B$9,Serie!$C$5:$C$74,0)) -> -0.033053515 | C114: =1+B114 -> 0.96694648 | D114: =D113*C114 -> 0.88690651 | E114: =MAX(E113,D114) -> 1.0081764 | F114: =D114/E114-1 -> -0.1202864
A115: =A114+1 -> 46288 | B115: =INDEX(Serie!$K$5:$K$74,MATCH(A115&"|"&$B$9,Serie!$C$5:$C$74,0)) -> -0.018719479 | C115: =1+B115 -> 0.98128052 | D115: =D114*C115 -> 0.87030408 | E115: =MAX(E114,D115) -> 1.0081764 | F115: =D115/E115-1 -> -0.13675418
... A136: =A135+1 -> 46309 | B136: =INDEX(Serie!$K$5:$K$74,MATCH(A136&"|"&$B$9,Serie!$C$5:$C$74,0)) -> 0.016941392 | C136: =1+B136 -> 1.0169414 | D136: =D135*C136 -> 1.0688114 | E136: =MAX(E135,D136) -> 1.0688114 | F136: =D136/E136-1 -> 0
A139: Periodo P2-C
A140: fecha | B140: r(t) | C140: 1 + r(t) | D140: I(t) | E140: máximo (con I = 1 inicial) | F140: caída I/máx − 1
A141: =$C$10 -> 46296 | B141: =INDEX(Serie!$K$5:$K$74,MATCH(A141&"|"&$B$10,Serie!$C$5:$C$74,0)) -> -0.016339869 | C141: =1+B141 -> 0.98366013 | D141: =C141 -> 0.98366013 | E141: =MAX(1,D141) -> 1 | F141: =D141/E141-1 -> -0.016339869
A142: =A141+1 -> 46297 | B142: =INDEX(Serie!$K$5:$K$74,MATCH(A142&"|"&$B$10,Serie!$C$5:$C$74,0)) -> -0.013763645 | C142: =1+B142 -> 0.98623636 | D142: =D141*C142 -> 0.97012138 | E142: =MAX(E141,D142) -> 1 | F142: =D142/E142-1 -> -0.029878618
A143: =A142+1 -> 46298 | B143: =INDEX(Serie!$K$5:$K$74,MATCH(A143&"|"&$B$10,Serie!$C$5:$C$74,0)) -> 0 | C143: =1+B143 -> 1 | D143: =D142*C143 -> 0.97012138 | E143: =MAX(E142,D143) -> 1 | F143: =D143/E143-1 -> -0.029878618
A144: =A143+1 -> 46299 | B144: =INDEX(Serie!$K$5:$K$74,MATCH(A144&"|"&$B$10,Serie!$C$5:$C$74,0)) -> 0 | C144: =1+B144 -> 1 | D144: =D143*C144 -> 0.97012138 | E144: =MAX(E143,D144) -> 1 | F144: =D144/E144-1 -> -0.029878618
A145: =A144+1 -> 46300 | B145: =INDEX(Serie!$K$5:$K$74,MATCH(A145&"|"&$B$10,Serie!$C$5:$C$74,0)) -> -0.021655438 | C145: =1+B145 -> 0.97834456 | D145: =D144*C145 -> 0.94911298 | E145: =MAX(E144,D145) -> 1 | F145: =D145/E145-1 -> -0.050887021
A146: =A145+1 -> 46301 | B146: =INDEX(Serie!$K$5:$K$74,MATCH(A146&"|"&$B$10,Serie!$C$5:$C$74,0)) -> 0.01131333 | C146: =1+B146 -> 1.0113133 | D146: =D145*C146 -> 0.95985061 | E146: =MAX(E145,D146) -> 1 | F146: =D146/E146-1 -> -0.040149393
A147: =A146+1 -> 46302 | B147: =INDEX(Serie!$K$5:$K$74,MATCH(A147&"|"&$B$10,Serie!$C$5:$C$74,0)) -> 0.020914397 | C147: =1+B147 -> 1.0209144 | D147: =D146*C147 -> 0.9799253 | E147: =MAX(E146,D147) -> 1 | F147: =D147/E147-1 -> -0.020074697
A148: =A147+1 -> 46303 | B148: =INDEX(Serie!$K$5:$K$74,MATCH(A148&"|"&$B$10,Serie!$C$5:$C$74,0)) -> 0.02334445 | C148: =1+B148 -> 1.0233444 | D148: =D147*C148 -> 1.0028011 | E148: =MAX(E147,D148) -> 1.0028011 | F148: =D148/E148-1 -> 0
A149: =A148+1 -> 46304 | B149: =INDEX(Serie!$K$5:$K$74,MATCH(A149&"|"&$B$10,Serie!$C$5:$C$74,0)) -> 0.016294227 | C149: =1+B149 -> 1.0162942 | D149: =D148*C149 -> 1.019141 | E149: =MAX(E148,D149) -> 1.019141 | F149: =D149/E149-1 -> 0
A150: =A149+1 -> 46305 | B150: =INDEX(Serie!$K$5:$K$74,MATCH(A150&"|"&$B$10,Serie!$C$5:$C$74,0)) -> 0 | C150: =1+B150 -> 1 | D150: =D149*C150 -> 1.019141 | E150: =MAX(E149,D150) -> 1.019141 | F150: =D150/E150-1 -> 0
A151: =A150+1 -> 46306 | B151: =INDEX(Serie!$K$5:$K$74,MATCH(A151&"|"&$B$10,Serie!$C$5:$C$74,0)) -> 0 | C151: =1+B151 -> 1 | D151: =D150*C151 -> 1.019141 | E151: =MAX(E150,D151) -> 1.019141 | F151: =D151/E151-1 -> 0
A152: =A151+1 -> 46307 | B152: =INDEX(Serie!$K$5:$K$74,MATCH(A152&"|"&$B$10,Serie!$C$5:$C$74,0)) -> 0.01053596 | C152: =1+B152 -> 1.010536 | D152: =D151*C152 -> 1.0298786 | E152: =MAX(E151,D152) -> 1.0298786 | F152: =D152/E152-1 -> 0
A153: =A152+1 -> 46308 | B153: =INDEX(Serie!$K$5:$K$74,MATCH(A153&"|"&$B$10,Serie!$C$5:$C$74,0)) -> -0.0099728015 | C153: =1+B153 -> 0.9900272 | D153: =D152*C153 -> 1.0196078 | E153: =MAX(E152,D153) -> 1.0298786 | F153: =D153/E153-1 -> -0.0099728015
A154: =A153+1 -> 46309 | B154: =INDEX(Serie!$K$5:$K$74,MATCH(A154&"|"&$B$10,Serie!$C$5:$C$74,0)) -> 0.016941392 | C154: =1+B154 -> 1.0169414 | D154: =D153*C154 -> 1.0368814 | E154: =MAX(E153,D154) -> 1.0368814 | F154: =D154/E154-1 -> 0

Sheet Rechazos
A1: Rechazos esperados (RF-28, RF-26a, RF-05, RF-09) y caso positivo C1
A2: A–N: candidatos (entradas/candidatos_rechazo.csv), que se intentan registrar después de T01 a T16. S: saldo del par al cierre del día del candidato; T–AI: saldo al cierre de la fecha de cada transacción posterior del mismo par (fila 3), con el candidato. La regla se aplica en orden: intervalo, vencimiento, saldo negativo (RF-28, en cualquier fecha, compras antes que ventas).
S3: fecha de la transacción → | T3: =Transacciones!$F$5 -> 46275 | U3: =Transacciones!$F$6 -> 46275 | V3: =Transacciones!$F$7 -> 46275 | W3: =Transacciones!$F$8 -> 46275 | X3: =Transacciones!$F$9 -> 46276 | Y3: =Transacciones!$F$10 -> 46279 | Z3: =Transacciones!$F$11 -> 46279 | AA3: =Transacciones!$F$12 -> 46282 | AB3: =Transacciones!$F$13 -> 46282 | AC3: =Transacciones!$F$14 -> 46287 | AD3: =Transacciones!$F$15 -> 46290 | AE3: =Transacciones!$F$16 -> 46290 | AF3: =Transacciones!$F$17 -> 46296 | AG3: =Transacciones!$F$18 -> 46297 | AH3: =Transacciones!$F$19 -> 46300 | AI3: =Transacciones!$F$20 -> 46303
A4: id | B4: criterio | C4: caso | D4: portafolio_nombre | E4: intermediario_nombre | F4: instrumento_clave | G4: tipo | H4: fecha_concertacion | I4: cantidad | J4: precio | K4: importe_comisiones | L4: periodo_inicio | M4: periodo_fin | N4: motivo_esperado | O4: llave del par | P4: cantidad con signo | Q4: ¿fuera del intervalo de las semillas? | R4: ¿CETES en o después del vencimiento? | S4: saldo al cierre del día del candidato | T4: =Transacciones!$A$5 -> T01 | U4: =Transacciones!$A$6 -> T02 | V4: =Transacciones!$A$7 -> T03 | W4: =Transacciones!$A$8 -> T04 | X4: =Transacciones!$A$9 -> T05 | Y4: =Transacciones!$A$10 -> T06 | Z4: =Transacciones!$A$11 -> T07 | AA4: =Transacciones!$A$12 -> T08 | AB4: =Transacciones!$A$13 -> T09 | AC4: =Transacciones!$A$14 -> T10 | AD4: =Transacciones!$A$15 -> T11 | AE4: =Transacciones!$A$16 -> T12 | AF4: =Transacciones!$A$17 -> T13 | AG4: =Transacciones!$A$18 -> T14 | AH4: =Transacciones!$A$19 -> T15 | AI4: =Transacciones!$A$20 -> T16 | AJ4: saldo mínimo | AK4: primera fecha con saldo negativo | AL4: regla | AM4: resultado_esperado | AN4: fecha_saldo_negativo | AO4: saldo_resultante
A5: N1 | B5: RF-28 crit. 1 | C5: transaccion | D5: Principal | E5: Casa B | F5: DEMOACC | G5: venta | H5: 46283 | I5: 150 | J5: 98.5 | K5: 42.85 | N5: El saldo con Casa B es 100 aunque la posicion consolidada sea 300; su contraparte aceptada es T14 (80 <= 200) | O5: =IF($C5="transaccion",D5&"|"&F5&"|"&E5,"") -> Principal|DEMOACC|Casa B | P5: =IF($C5="transaccion",IF(G5="compra",1,-1)*I5,"") -> -150 | Q5: =IF($C5="transaccion",OR(H5<Entradas!$B$6,H5>Entradas!$B$7),"") -> FALSE | R5: =IF($C5="transaccion",AND(INDEX(Entradas!$C$40:$C$46,MATCH(F5,Entradas!$A$40:$A$46,0))="cetes",H5>=INDEX(Entradas!$F$40:$F$46,MATCH(F5,Entradas!$A$40:$A$46,0))),"") -> FALSE | S5: =IF($C5="transaccion",SUMIFS(Transacciones!$N$5:$N$20,Transacciones!$T$5:$T$20,O5,Transacciones!$F$5:$F$20,"<="&H5)+P5,"") -> -50 | T5: =IF($C5<>"transaccion","",IF(AND(Transacciones!$T$5=$O5,Transacciones!$F$5>$H5),SUMIFS(Transacciones!$N$5:$N$20,Transacciones!$T$5:$T$20,$O5,Transacciones!$F$5:$F$20,"<="&Transacciones!$F$5)+$P5,"")) | U5: =IF($C5<>"transaccion","",IF(AND(Transacciones!$T$6=$O5,Transacciones!$F$6>$H5),SUMIFS(Transacciones!$N$5:$N$20,Transacciones!$T$5:$T$20,$O5,Transacciones!$F$5:$F$20,"<="&Transacciones!$F$6)+$P5,"")) | V5: =IF($C5<>"transaccion","",IF(AND(Transacciones!$T$7=$O5,Transacciones!$F$7>$H5),SUMIFS(Transacciones!$N$5:$N$20,Transacciones!$T$5:$T$20,$O5,Transacciones!$F$5:$F$20,"<="&Transacciones!$F$7)+$P5,"")) | W5: =IF($C5<>"transaccion","",IF(AND(Transacciones!$T$8=$O5,Transacciones!$F$8>$H5),SUMIFS(Transacciones!$N$5:$N$20,Transacciones!$T$5:$T$20,$O5,Transacciones!$F$5:$F$20,"<="&Transacciones!$F$8)+$P5,"")) | X5: =IF($C5<>"transaccion","",IF(AND(Transacciones!$T$9=$O5,Transacciones!$F$9>$H5),SUMIFS(Transacciones!$N$5:$N$20,Transacciones!$T$5:$T$20,$O5,Transacciones!$F$5:$F$20,"<="&Transacciones!$F$9)+$P5,"")) | Y5: =IF($C5<>"transaccion","",IF(AND(Transacciones!$T$10=$O5,Transacciones!$F$10>$H5),SUMIFS(Transacciones!$N$5:$N$20,Transacciones!$T$5:$T$20,$O5,Transacciones!$F$5:$F$20,"<="&Transacciones!$F$10)+$P5,"")) | Z5: =IF($C5<>"transaccion","",IF(AND(Transacciones!$T$11=$O5,Transacciones!$F$11>$H5),SUMIFS(Transacciones!$N$5:$N$20,Transacciones!$T$5:$T$20,$O5,Transacciones!$F$5:$F$20,"<="&Transacciones!$F$11)+$P5,"")) | AA5: =IF($C5<>"transaccion","",IF(AND(Transacciones!$T$12=$O5,Transacciones!$F$12>$H5),SUMIFS(Transacciones!$N$5:$N$20,Transacciones!$T$5:$T$20,$O5,Transacciones!$F$5:$F$20,"<="&Transacciones!$F$12)+$P5,"")) | AB5: =IF($C5<>"transaccion","",IF(AND(Transacciones!$T$13=$O5,Transacciones!$F$13>$H5),SUMIFS(Transacciones!$N$5:$N$20,Transacciones!$T$5:$T$20,$O5,Transacciones!$F$5:$F$20,"<="&Transacciones!$F$13)+$P5,"")) | AC5: =IF($C5<>"transaccion","",IF(AND(Transacciones!$T$14=$O5,Transacciones!$F$14>$H5),SUMIFS(Transacciones!$N$5:$N$20,Transacciones!$T$5:$T$20,$O5,Transacciones!$F$5:$F$20,"<="&Transacciones!$F$14)+$P5,"")) | AD5: =IF($C5<>"transaccion","",IF(AND(Transacciones!$T$15=$O5,Transacciones!$F$15>$H5),SUMIFS(Transacciones!$N$5:$N$20,Transacciones!$T$5:$T$20,$O5,Transacciones!$F$5:$F$20,"<="&Transacciones!$F$15)+$P5,"")) | AE5: =IF($C5<>"transaccion","",IF(AND(Transacciones!$T$16=$O5,Transacciones!$F$16>$H5),SUMIFS(Transacciones!$N$5:$N$20,Transacciones!$T$5:$T$20,$O5,Transacciones!$F$5:$F$20,"<="&Transacciones!$F$16)+$P5,"")) | AF5: =IF($C5<>"transaccion","",IF(AND(Transacciones!$T$17=$O5,Transacciones!$F$17>$H5),SUMIFS(Transacciones!$N$5:$N$20,Transacciones!$T$5:$T$20,$O5,Transacciones!$F$5:$F$20,"<="&Transacciones!$F$17)+$P5,"")) | AG5: =IF($C5<>"transaccion","",IF(AND(Transacciones!$T$18=$O5,Transacciones!$F$18>$H5),SUMIFS(Transacciones!$N$5:$N$20,Transacciones!$T$5:$T$20,$O5,Transacciones!$F$5:$F$20,"<="&Transacciones!$F$18)+$P5,"")) | AH5: =IF($C5<>"transaccion","",IF(AND(Transacciones!$T$19=$O5,Transacciones!$F$19>$H5),SUMIFS(Transacciones!$N$5:$N$20,Transacciones!$T$5:$T$20,$O5,Transacciones!$F$5:$F$20,"<="&Transacciones!$F$19)+$P5,"")) | AI5: =IF($C5<>"transaccion","",IF(AND(Transacciones!$T$20=$O5,Transacciones!$F$20>$H5),SUMIFS(Transacciones!$N$5:$N$20,Transacciones!$T$5:$T$20,$O5,Transacciones!$F$5:$F$20,"<="&Transacciones!$F$20)+$P5,"")) | AJ5: =IF($C5="transaccion",MIN(S5,T5:AI5),"") -> -50 | AK5: =IF($C5<>"transaccion","",IF(S5<0,H5,IF(AJ5<0,_xlfn.MINIFS($T$3:$AI$3,T5:AI5,"<0"),""))) -> 46283 | AL5: =IF($C5="periodo",IF(M5<L5,"criterio 3 de RF-09: fecha final anterior a la inicial",IF(OR(L5-1<Entradas!$B$6,M5>Entradas!$B$7),"criterio 3 de RF-09: fechas fuera de las semillas","")),IF(Q5,"RD-07 y criterio 3 de RF-05: fecha fuera del intervalo de las semillas",IF(R5,"criterio 2 de RF-26a: fecha igual o posterior al vencimiento de la emision",IF(AJ5<0,"RF-28: deja negativo el saldo del instrumento con el intermediario dentro del portafolio","")))) -> RF-28: deja negativo el saldo del instrumento con el intermediario dentro del portafolio | AM5: =IF(AL5="","aceptar","rechazar") -> rechazar | AN5: =IF(LEFT(AL5,5)="RF-28",AK5,"") -> 46283 | AO5: =IF(LEFT(AL5,5)="RF-28",SUMIFS(Transacciones!$N$5:$N$20,Transacciones!$T$5:$T$20,O5,Transacciones!$F$5:$F$20,"<="&AK5)+P5,"") -> -50
A6: N2 | B6: RF-28 crit. 2 | C6: transaccion | D6: Principal | E6: Casa A | F6: DEMOFIB | G6: venta | H6: 46280 | I6: 100 | J6: 25.4 | K6: 7.37 | N6: El 15/09 quedaria en 300 y el 14/10 en 200, pero el 22/09, con T10, seria -100 | O6: =IF($C6="transaccion",D6&"|"&F6&"|"&E6,"") -> Principal|DEMOFIB|Casa A | P6: =IF($C6="transaccion",IF(G6="compra",1,-1)*I6,"") -> -100 | Q6: =IF($C6="transaccion",OR(H6<Entradas!$B$6,H6>Entradas!$B$7),"") -> FALSE | R6: =IF($C6="transaccion",AND(INDEX(Entradas!$C$40:$C$46,MATCH(F6,Entradas!$A$40:$A$46,0))="cetes",H6>=INDEX(Entradas!$F$40:$F$46,MATCH(F6,Entradas!$A$40:$A$46,0))),"") -> FALSE | S6: =IF($C6="transaccion",SUMIFS(Transacciones!$N$5:$N$20,Transacciones!$T$5:$T$20,O6,Transacciones!$F$5:$F$20,"<="&H6)+P6,"") -> 300 | T6: =IF($C6<>"transaccion","",IF(AND(Transacciones!$T$5=$O6,Transacciones!$F$5>$H6),SUMIFS(Transacciones!$N$5:$N$20,Transacciones!$T$5:$T$20,$O6,Transacciones!$F$5:$F$20,"<="&Transacciones!$F$5)+$P6,"")) | U6: =IF($C6<>"transaccion","",IF(AND(Transacciones!$T$6=$O6,Transacciones!$F$6>$H6),SUMIFS(Transacciones!$N$5:$N$20,Transacciones!$T$5:$T$20,$O6,Transacciones!$F$5:$F$20,"<="&Transacciones!$F$6)+$P6,"")) | V6: =IF($C6<>"transaccion","",IF(AND(Transacciones!$T$7=$O6,Transacciones!$F$7>$H6),SUMIFS(Transacciones!$N$5:$N$20,Transacciones!$T$5:$T$20,$O6,Transacciones!$F$5:$F$20,"<="&Transacciones!$F$7)+$P6,"")) | W6: =IF($C6<>"transaccion","",IF(AND(Transacciones!$T$8=$O6,Transacciones!$F$8>$H6),SUMIFS(Transacciones!$N$5:$N$20,Transacciones!$T$5:$T$20,$O6,Transacciones!$F$5:$F$20,"<="&Transacciones!$F$8)+$P6,"")) | X6: =IF($C6<>"transaccion","",IF(AND(Transacciones!$T$9=$O6,Transacciones!$F$9>$H6),SUMIFS(Transacciones!$N$5:$N$20,Transacciones!$T$5:$T$20,$O6,Transacciones!$F$5:$F$20,"<="&Transacciones!$F$9)+$P6,"")) | Y6: =IF($C6<>"transaccion","",IF(AND(Transacciones!$T$10=$O6,Transacciones!$F$10>$H6),SUMIFS(Transacciones!$N$5:$N$20,Transacciones!$T$5:$T$20,$O6,Transacciones!$F$5:$F$20,"<="&Transacciones!$F$10)+$P6,"")) | Z6: =IF($C6<>"transaccion","",IF(AND(Transacciones!$T$11=$O6,Transacciones!$F$11>$H6),SUMIFS(Transacciones!$N$5:$N$20,Transacciones!$T$5:$T$20,$O6,Transacciones!$F$5:$F$20,"<="&Transacciones!$F$11)+$P6,"")) | AA6: =IF($C6<>"transaccion","",IF(AND(Transacciones!$T$12=$O6,Transacciones!$F$12>$H6),SUMIFS(Transacciones!$N$5:$N$20,Transacciones!$T$5:$T$20,$O6,Transacciones!$F$5:$F$20,"<="&Transacciones!$F$12)+$P6,"")) | AB6: =IF($C6<>"transaccion","",IF(AND(Transacciones!$T$13=$O6,Transacciones!$F$13>$H6),SUMIFS(Transacciones!$N$5:$N$20,Transacciones!$T$5:$T$20,$O6,Transacciones!$F$5:$F$20,"<="&Transacciones!$F$13)+$P6,"")) | AC6: =IF($C6<>"transaccion","",IF(AND(Transacciones!$T$14=$O6,Transacciones!$F$14>$H6),SUMIFS(Transacciones!$N$5:$N$20,Transacciones!$T$5:$T$20,$O6,Transacciones!$F$5:$F$20,"<="&Transacciones!$F$14)+$P6,"")) -> -100 | AD6: =IF($C6<>"transaccion","",IF(AND(Transacciones!$T$15=$O6,Transacciones!$F$15>$H6),SUMIFS(Transacciones!$N$5:$N$20,Transacciones!$T$5:$T$20,$O6,Transacciones!$F$5:$F$20,"<="&Transacciones!$F$15)+$P6,"")) | AE6: =IF($C6<>"transaccion","",IF(AND(Transacciones!$T$16=$O6,Transacciones!$F$16>$H6),SUMIFS(Transacciones!$N$5:$N$20,Transacciones!$T$5:$T$20,$O6,Transacciones!$F$5:$F$20,"<="&Transacciones!$F$16)+$P6,"")) | AF6: =IF($C6<>"transaccion","",IF(AND(Transacciones!$T$17=$O6,Transacciones!$F$17>$H6),SUMIFS(Transacciones!$N$5:$N$20,Transacciones!$T$5:$T$20,$O6,Transacciones!$F$5:$F$20,"<="&Transacciones!$F$17)+$P6,"")) | AG6: =IF($C6<>"transaccion","",IF(AND(Transacciones!$T$18=$O6,Transacciones!$F$18>$H6),SUMIFS(Transacciones!$N$5:$N$20,Transacciones!$T$5:$T$20,$O6,Transacciones!$F$5:$F$20,"<="&Transacciones!$F$18)+$P6,"")) | AH6: =IF($C6<>"transaccion","",IF(AND(Transacciones!$T$19=$O6,Transacciones!$F$19>$H6),SUMIFS(Transacciones!$N$5:$N$20,Transacciones!$T$5:$T$20,$O6,Transacciones!$F$5:$F$20,"<="&Transacciones!$F$19)+$P6,"")) -> 200 | AI6: =IF($C6<>"transaccion","",IF(AND(Transacciones!$T$20=$O6,Transacciones!$F$20>$H6),SUMIFS(Transacciones!$N$5:$N$20,Transacciones!$T$5:$T$20,$O6,Transacciones!$F$5:$F$20,"<="&Transacciones!$F$20)+$P6,"")) | AJ6: =IF($C6="transaccion",MIN(S6,T6:AI6),"") -> -100 | AK6: =IF($C6<>"transaccion","",IF(S6<0,H6,IF(AJ6<0,_xlfn.MINIFS($T$3:$AI$3,T6:AI6,"<0"),""))) -> 46287 | AL6: =IF($C6="periodo",IF(M6<L6,"criterio 3 de RF-09: fecha final anterior a la inicial",IF(OR(L6-1<Entradas!$B$6,M6>Entradas!$B$7),"criterio 3 de RF-09: fechas fuera de las semillas","")),IF(Q6,"RD-07 y criterio 3 de RF-05: fecha fuera del intervalo de las semillas",IF(R6,"criterio 2 de RF-26a: fecha igual o posterior al vencimiento de la emision",IF(AJ6<0,"RF-28: deja negativo el saldo del instrumento con el intermediario dentro del portafolio","")))) -> RF-28: deja negativo el saldo del instrumento con el intermediario dentro del portafolio | AM6: =IF(AL6="","aceptar","rechazar") -> rechazar | AN6: =IF(LEFT(AL6,5)="RF-28",AK6,"") -> 46287 | AO6: =IF(LEFT(AL6,5)="RF-28",SUMIFS(Transacciones!$N$5:$N$20,Transacciones!$T$5:$T$20,O6,Transacciones!$F$5:$F$20,"<="&AK6)+P6,"") -> -100
A7: N3 | B7: RF-28 crit. 3 y X-06 | C7: transaccion | D7: Principal | E7: Casa A | F7: DEMOACC | G7: venta | H7: 46304 | I7: 150 | J7: 109 | K7: 47.42 | N7: El saldo del Principal con Casa A es 120; los 150 del Secundario con Casa A no cuentan | O7: =IF($C7="transaccion",D7&"|"&F7&"|"&E7,"") -> Principal|DEMOACC|Casa A | P7: =IF($C7="transaccion",IF(G7="compra",1,-1)*I7,"") -> -150 | Q7: =IF($C7="transaccion",OR(H7<Entradas!$B$6,H7>Entradas!$B$7),"") -> FALSE | R7: =IF($C7="transaccion",AND(INDEX(Entradas!$C$40:$C$46,MATCH(F7,Entradas!$A$40:$A$46,0))="cetes",H7>=INDEX(Entradas!$F$40:$F$46,MATCH(F7,Entradas!$A$40:$A$46,0))),"") -> FALSE | S7: =IF($C7="transaccion",SUMIFS(Transacciones!$N$5:$N$20,Transacciones!$T$5:$T$20,O7,Transacciones!$F$5:$F$20,"<="&H7)+P7,"") -> -30 | T7: =IF($C7<>"transaccion","",IF(AND(Transacciones!$T$5=$O7,Transacciones!$F$5>$H7),SUMIFS(Transacciones!$N$5:$N$20,Transacciones!$T$5:$T$20,$O7,Transacciones!$F$5:$F$20,"<="&Transacciones!$F$5)+$P7,"")) | U7: =IF($C7<>"transaccion","",IF(AND(Transacciones!$T$6=$O7,Transacciones!$F$6>$H7),SUMIFS(Transacciones!$N$5:$N$20,Transacciones!$T$5:$T$20,$O7,Transacciones!$F$5:$F$20,"<="&Transacciones!$F$6)+$P7,"")) | V7: =IF($C7<>"transaccion","",IF(AND(Transacciones!$T$7=$O7,Transacciones!$F$7>$H7),SUMIFS(Transacciones!$N$5:$N$20,Transacciones!$T$5:$T$20,$O7,Transacciones!$F$5:$F$20,"<="&Transacciones!$F$7)+$P7,"")) | W7: =IF($C7<>"transaccion","",IF(AND(Transacciones!$T$8=$O7,Transacciones!$F$8>$H7),SUMIFS(Transacciones!$N$5:$N$20,Transacciones!$T$5:$T$20,$O7,Transacciones!$F$5:$F$20,"<="&Transacciones!$F$8)+$P7,"")) | X7: =IF($C7<>"transaccion","",IF(AND(Transacciones!$T$9=$O7,Transacciones!$F$9>$H7),SUMIFS(Transacciones!$N$5:$N$20,Transacciones!$T$5:$T$20,$O7,Transacciones!$F$5:$F$20,"<="&Transacciones!$F$9)+$P7,"")) | Y7: =IF($C7<>"transaccion","",IF(AND(Transacciones!$T$10=$O7,Transacciones!$F$10>$H7),SUMIFS(Transacciones!$N$5:$N$20,Transacciones!$T$5:$T$20,$O7,Transacciones!$F$5:$F$20,"<="&Transacciones!$F$10)+$P7,"")) | Z7: =IF($C7<>"transaccion","",IF(AND(Transacciones!$T$11=$O7,Transacciones!$F$11>$H7),SUMIFS(Transacciones!$N$5:$N$20,Transacciones!$T$5:$T$20,$O7,Transacciones!$F$5:$F$20,"<="&Transacciones!$F$11)+$P7,"")) | AA7: =IF($C7<>"transaccion","",IF(AND(Transacciones!$T$12=$O7,Transacciones!$F$12>$H7),SUMIFS(Transacciones!$N$5:$N$20,Transacciones!$T$5:$T$20,$O7,Transacciones!$F$5:$F$20,"<="&Transacciones!$F$12)+$P7,"")) | AB7: =IF($C7<>"transaccion","",IF(AND(Transacciones!$T$13=$O7,Transacciones!$F$13>$H7),SUMIFS(Transacciones!$N$5:$N$20,Transacciones!$T$5:$T$20,$O7,Transacciones!$F$5:$F$20,"<="&Transacciones!$F$13)+$P7,"")) | AC7: =IF($C7<>"transaccion","",IF(AND(Transacciones!$T$14=$O7,Transacciones!$F$14>$H7),SUMIFS(Transacciones!$N$5:$N$20,Transacciones!$T$5:$T$20,$O7,Transacciones!$F$5:$F$20,"<="&Transacciones!$F$14)+$P7,"")) | AD7: =IF($C7<>"transaccion","",IF(AND(Transacciones!$T$15=$O7,Transacciones!$F$15>$H7),SUMIFS(Transacciones!$N$5:$N$20,Transacciones!$T$5:$T$20,$O7,Transacciones!$F$5:$F$20,"<="&Transacciones!$F$15)+$P7,"")) | AE7: =IF($C7<>"transaccion","",IF(AND(Transacciones!$T$16=$O7,Transacciones!$F$16>$H7),SUMIFS(Transacciones!$N$5:$N$20,Transacciones!$T$5:$T$20,$O7,Transacciones!$F$5:$F$20,"<="&Transacciones!$F$16)+$P7,"")) | AF7: =IF($C7<>"transaccion","",IF(AND(Transacciones!$T$17=$O7,Transacciones!$F$17>$H7),SUMIFS(Transacciones!$N$5:$N$20,Transacciones!$T$5:$T$20,$O7,Transacciones!$F$5:$F$20,"<="&Transacciones!$F$17)+$P7,"")) | AG7: =IF($C7<>"transaccion","",IF(AND(Transacciones!$T$18=$O7,Transacciones!$F$18>$H7),SUMIFS(Transacciones!$N$5:$N$20,Transacciones!$T$5:$T$20,$O7,Transacciones!$F$5:$F$20,"<="&Transacciones!$F$18)+$P7,"")) | AH7: =IF($C7<>"transaccion","",IF(AND(Transacciones!$T$19=$O7,Transacciones!$F$19>$H7),SUMIFS(Transacciones!$N$5:$N$20,Transacciones!$T$5:$T$20,$O7,Transacciones!$F$5:$F$20,"<="&Transacciones!$F$19)+$P7,"")) | AI7: =IF($C7<>"transaccion","",IF(AND(Transacciones!$T$20=$O7,Transacciones!$F$20>$H7),SUMIFS(Transacciones!$N$5:$N$20,Transacciones!$T$5:$T$20,$O7,Transacciones!$F$5:$F$20,"<="&Transacciones!$F$20)+$P7,"")) | AJ7: =IF($C7="transaccion",MIN(S7,T7:AI7),"") -> -30 | AK7: =IF($C7<>"transaccion","",IF(S7<0,H7,IF(AJ7<0,_xlfn.MINIFS($T$3:$AI$3,T7:AI7,"<0"),""))) -> 46304 | AL7: =IF($C7="periodo",IF(M7<L7,"criterio 3 de RF-09: fecha final anterior a la inicial",IF(OR(L7-1<Entradas!$B$6,M7>Entradas!$B$7),"criterio 3 de RF-09: fechas fuera de las semillas","")),IF(Q7,"RD-07 y criterio 3 de RF-05: fecha fuera del intervalo de las semillas",IF(R7,"criterio 2 de RF-26a: fecha igual o posterior al vencimiento de la emision",IF(AJ7<0,"RF-28: deja negativo el saldo del instrumento con el intermediario dentro del portafolio","")))) -> RF-28: deja negativo el saldo del instrumento con el intermediario dentro del portafolio | AM7: =IF(AL7="","aceptar","rechazar") -> rechazar | AN7: =IF(LEFT(AL7,5)="RF-28",AK7,"") -> 46304 | AO7: =IF(LEFT(AL7,5)="RF-28",SUMIFS(Transacciones!$N$5:$N$20,Transacciones!$T$5:$T$20,O7,Transacciones!$F$5:$F$20,"<="&AK7)+P7,"") -> -30
A8: N4 | B8: RF-26a crit. 2 | C8: transaccion | D8: Principal | E8: Casa B | F8: BI261008 | G8: venta | H8: 46303 | I8: 100 | J8: 10 | K8: 0 | N8: La fecha es igual al vencimiento de la emision | O8: =IF($C8="transaccion",D8&"|"&F8&"|"&E8,"") -> Principal|BI261008|Casa B | P8: =IF($C8="transaccion",IF(G8="compra",1,-1)*I8,"") -> -100 | Q8: =IF($C8="transaccion",OR(H8<Entradas!$B$6,H8>Entradas!$B$7),"") -> FALSE | R8: =IF($C8="transaccion",AND(INDEX(Entradas!$C$40:$C$46,MATCH(F8,Entradas!$A$40:$A$46,0))="cetes",H8>=INDEX(Entradas!$F$40:$F$46,MATCH(F8,Entradas!$A$40:$A$46,0))),"") -> TRUE | S8: =IF($C8="transaccion",SUMIFS(Transacciones!$N$5:$N$20,Transacciones!$T$5:$T$20,O8,Transacciones!$F$5:$F$20,"<="&H8)+P8,"") -> 900 | T8: =IF($C8<>"transaccion","",IF(AND(Transacciones!$T$5=$O8,Transacciones!$F$5>$H8),SUMIFS(Transacciones!$N$5:$N$20,Transacciones!$T$5:$T$20,$O8,Transacciones!$F$5:$F$20,"<="&Transacciones!$F$5)+$P8,"")) | U8: =IF($C8<>"transaccion","",IF(AND(Transacciones!$T$6=$O8,Transacciones!$F$6>$H8),SUMIFS(Transacciones!$N$5:$N$20,Transacciones!$T$5:$T$20,$O8,Transacciones!$F$5:$F$20,"<="&Transacciones!$F$6)+$P8,"")) | V8: =IF($C8<>"transaccion","",IF(AND(Transacciones!$T$7=$O8,Transacciones!$F$7>$H8),SUMIFS(Transacciones!$N$5:$N$20,Transacciones!$T$5:$T$20,$O8,Transacciones!$F$5:$F$20,"<="&Transacciones!$F$7)+$P8,"")) | W8: =IF($C8<>"transaccion","",IF(AND(Transacciones!$T$8=$O8,Transacciones!$F$8>$H8),SUMIFS(Transacciones!$N$5:$N$20,Transacciones!$T$5:$T$20,$O8,Transacciones!$F$5:$F$20,"<="&Transacciones!$F$8)+$P8,"")) | X8: =IF($C8<>"transaccion","",IF(AND(Transacciones!$T$9=$O8,Transacciones!$F$9>$H8),SUMIFS(Transacciones!$N$5:$N$20,Transacciones!$T$5:$T$20,$O8,Transacciones!$F$5:$F$20,"<="&Transacciones!$F$9)+$P8,"")) | Y8: =IF($C8<>"transaccion","",IF(AND(Transacciones!$T$10=$O8,Transacciones!$F$10>$H8),SUMIFS(Transacciones!$N$5:$N$20,Transacciones!$T$5:$T$20,$O8,Transacciones!$F$5:$F$20,"<="&Transacciones!$F$10)+$P8,"")) | Z8: =IF($C8<>"transaccion","",IF(AND(Transacciones!$T$11=$O8,Transacciones!$F$11>$H8),SUMIFS(Transacciones!$N$5:$N$20,Transacciones!$T$5:$T$20,$O8,Transacciones!$F$5:$F$20,"<="&Transacciones!$F$11)+$P8,"")) | AA8: =IF($C8<>"transaccion","",IF(AND(Transacciones!$T$12=$O8,Transacciones!$F$12>$H8),SUMIFS(Transacciones!$N$5:$N$20,Transacciones!$T$5:$T$20,$O8,Transacciones!$F$5:$F$20,"<="&Transacciones!$F$12)+$P8,"")) | AB8: =IF($C8<>"transaccion","",IF(AND(Transacciones!$T$13=$O8,Transacciones!$F$13>$H8),SUMIFS(Transacciones!$N$5:$N$20,Transacciones!$T$5:$T$20,$O8,Transacciones!$F$5:$F$20,"<="&Transacciones!$F$13)+$P8,"")) | AC8: =IF($C8<>"transaccion","",IF(AND(Transacciones!$T$14=$O8,Transacciones!$F$14>$H8),SUMIFS(Transacciones!$N$5:$N$20,Transacciones!$T$5:$T$20,$O8,Transacciones!$F$5:$F$20,"<="&Transacciones!$F$14)+$P8,"")) | AD8: =IF($C8<>"transaccion","",IF(AND(Transacciones!$T$15=$O8,Transacciones!$F$15>$H8),SUMIFS(Transacciones!$N$5:$N$20,Transacciones!$T$5:$T$20,$O8,Transacciones!$F$5:$F$20,"<="&Transacciones!$F$15)+$P8,"")) | AE8: =IF($C8<>"transaccion","",IF(AND(Transacciones!$T$16=$O8,Transacciones!$F$16>$H8),SUMIFS(Transacciones!$N$5:$N$20,Transacciones!$T$5:$T$20,$O8,Transacciones!$F$5:$F$20,"<="&Transacciones!$F$16)+$P8,"")) | AF8: =IF($C8<>"transaccion","",IF(AND(Transacciones!$T$17=$O8,Transacciones!$F$17>$H8),SUMIFS(Transacciones!$N$5:$N$20,Transacciones!$T$5:$T$20,$O8,Transacciones!$F$5:$F$20,"<="&Transacciones!$F$17)+$P8,"")) | AG8: =IF($C8<>"transaccion","",IF(AND(Transacciones!$T$18=$O8,Transacciones!$F$18>$H8),SUMIFS(Transacciones!$N$5:$N$20,Transacciones!$T$5:$T$20,$O8,Transacciones!$F$5:$F$20,"<="&Transacciones!$F$18)+$P8,"")) | AH8: =IF($C8<>"transaccion","",IF(AND(Transacciones!$T$19=$O8,Transacciones!$F$19>$H8),SUMIFS(Transacciones!$N$5:$N$20,Transacciones!$T$5:$T$20,$O8,Transacciones!$F$5:$F$20,"<="&Transacciones!$F$19)+$P8,"")) | AI8: =IF($C8<>"transaccion","",IF(AND(Transacciones!$T$20=$O8,Transacciones!$F$20>$H8),SUMIFS(Transacciones!$N$5:$N$20,Transacciones!$T$5:$T$20,$O8,Transacciones!$F$5:$F$20,"<="&Transacciones!$F$20)+$P8,"")) | AJ8: =IF($C8="transaccion",MIN(S8,T8:AI8),"") -> 900 | AK8: =IF($C8<>"transaccion","",IF(S8<0,H8,IF(AJ8<0,_xlfn.MINIFS($T$3:$AI$3,T8:AI8,"<0"),""))) | AL8: =IF($C8="periodo",IF(M8<L8,"criterio 3 de RF-09: fecha final anterior a la inicial",IF(OR(L8-1<Entradas!$B$6,M8>Entradas!$B$7),"criterio 3 de RF-09: fechas fuera de las semillas","")),IF(Q8,"RD-07 y criterio 3 de RF-05: fecha fuera del intervalo de las semillas",IF(R8,"criterio 2 de RF-26a: fecha igual o posterior al vencimiento de la emision",IF(AJ8<0,"RF-28: deja negativo el saldo del instrumento con el intermediario dentro del portafolio","")))) -> criterio 2 de RF-26a: fecha igual o posterior al vencimiento de la emision | AM8: =IF(AL8="","aceptar","rechazar") -> rechazar | AN8: =IF(LEFT(AL8,5)="RF-28",AK8,"") | AO8: =IF(LEFT(AL8,5)="RF-28",SUMIFS(Transacciones!$N$5:$N$20,Transacciones!$T$5:$T$20,O8,Transacciones!$F$5:$F$20,"<="&AK8)+P8,"")
A9: N5 | B9: RF-05 crit. 3 (opcional) | C9: transaccion | D9: Principal | E9: Casa A | F9: DEMOACC | G9: compra | H9: 46274 | I9: 10 | J9: 100 | K9: 2.9 | N9: Compra fechada el 09/09, antes del intervalo de las semillas | O9: =IF($C9="transaccion",D9&"|"&F9&"|"&E9,"") -> Principal|DEMOACC|Casa A | P9: =IF($C9="transaccion",IF(G9="compra",1,-1)*I9,"") -> 10 | Q9: =IF($C9="transaccion",OR(H9<Entradas!$B$6,H9>Entradas!$B$7),"") -> TRUE | R9: =IF($C9="transaccion",AND(INDEX(Entradas!$C$40:$C$46,MATCH(F9,Entradas!$A$40:$A$46,0))="cetes",H9>=INDEX(Entradas!$F$40:$F$46,MATCH(F9,Entradas!$A$40:$A$46,0))),"") -> FALSE | S9: =IF($C9="transaccion",SUMIFS(Transacciones!$N$5:$N$20,Transacciones!$T$5:$T$20,O9,Transacciones!$F$5:$F$20,"<="&H9)+P9,"") -> 10 | T9: =IF($C9<>"transaccion","",IF(AND(Transacciones!$T$5=$O9,Transacciones!$F$5>$H9),SUMIFS(Transacciones!$N$5:$N$20,Transacciones!$T$5:$T$20,$O9,Transacciones!$F$5:$F$20,"<="&Transacciones!$F$5)+$P9,"")) -> 210 | U9: =IF($C9<>"transaccion","",IF(AND(Transacciones!$T$6=$O9,Transacciones!$F$6>$H9),SUMIFS(Transacciones!$N$5:$N$20,Transacciones!$T$5:$T$20,$O9,Transacciones!$F$5:$F$20,"<="&Transacciones!$F$6)+$P9,"")) | V9: =IF($C9<>"transaccion","",IF(AND(Transacciones!$T$7=$O9,Transacciones!$F$7>$H9),SUMIFS(Transacciones!$N$5:$N$20,Transacciones!$T$5:$T$20,$O9,Transacciones!$F$5:$F$20,"<="&Transacciones!$F$7)+$P9,"")) | W9: =IF($C9<>"transaccion","",IF(AND(Transacciones!$T$8=$O9,Transacciones!$F$8>$H9),SUMIFS(Transacciones!$N$5:$N$20,Transacciones!$T$5:$T$20,$O9,Transacciones!$F$5:$F$20,"<="&Transacciones!$F$8)+$P9,"")) | X9: =IF($C9<>"transaccion","",IF(AND(Transacciones!$T$9=$O9,Transacciones!$F$9>$H9),SUMIFS(Transacciones!$N$5:$N$20,Transacciones!$T$5:$T$20,$O9,Transacciones!$F$5:$F$20,"<="&Transacciones!$F$9)+$P9,"")) | Y9: =IF($C9<>"transaccion","",IF(AND(Transacciones!$T$10=$O9,Transacciones!$F$10>$H9),SUMIFS(Transacciones!$N$5:$N$20,Transacciones!$T$5:$T$20,$O9,Transacciones!$F$5:$F$20,"<="&Transacciones!$F$10)+$P9,"")) | Z9: =IF($C9<>"transaccion","",IF(AND(Transacciones!$T$11=$O9,Transacciones!$F$11>$H9),SUMIFS(Transacciones!$N$5:$N$20,Transacciones!$T$5:$T$20,$O9,Transacciones!$F$5:$F$20,"<="&Transacciones!$F$11)+$P9,"")) | AA9: =IF($C9<>"transaccion","",IF(AND(Transacciones!$T$12=$O9,Transacciones!$F$12>$H9),SUMIFS(Transacciones!$N$5:$N$20,Transacciones!$T$5:$T$20,$O9,Transacciones!$F$5:$F$20,"<="&Transacciones!$F$12)+$P9,"")) | AB9: =IF($C9<>"transaccion","",IF(AND(Transacciones!$T$13=$O9,Transacciones!$F$13>$H9),SUMIFS(Transacciones!$N$5:$N$20,Transacciones!$T$5:$T$20,$O9,Transacciones!$F$5:$F$20,"<="&Transacciones!$F$13)+$P9,"")) | AC9: =IF($C9<>"transaccion","",IF(AND(Transacciones!$T$14=$O9,Transacciones!$F$14>$H9),SUMIFS(Transacciones!$N$5:$N$20,Transacciones!$T$5:$T$20,$O9,Transacciones!$F$5:$F$20,"<="&Transacciones!$F$14)+$P9,"")) | AD9: =IF($C9<>"transaccion","",IF(AND(Transacciones!$T$15=$O9,Transacciones!$F$15>$H9),SUMIFS(Transacciones!$N$5:$N$20,Transacciones!$T$5:$T$20,$O9,Transacciones!$F$5:$F$20,"<="&Transacciones!$F$15)+$P9,"")) | AE9: =IF($C9<>"transaccion","",IF(AND(Transacciones!$T$16=$O9,Transacciones!$F$16>$H9),SUMIFS(Transacciones!$N$5:$N$20,Transacciones!$T$5:$T$20,$O9,Transacciones!$F$5:$F$20,"<="&Transacciones!$F$16)+$P9,"")) | AF9: =IF($C9<>"transaccion","",IF(AND(Transacciones!$T$17=$O9,Transacciones!$F$17>$H9),SUMIFS(Transacciones!$N$5:$N$20,Transacciones!$T$5:$T$20,$O9,Transacciones!$F$5:$F$20,"<="&Transacciones!$F$17)+$P9,"")) | AG9: =IF($C9<>"transaccion","",IF(AND(Transacciones!$T$18=$O9,Transacciones!$F$18>$H9),SUMIFS(Transacciones!$N$5:$N$20,Transacciones!$T$5:$T$20,$O9,Transacciones!$F$5:$F$20,"<="&Transacciones!$F$18)+$P9,"")) -> 130 | AH9: =IF($C9<>"transaccion","",IF(AND(Transacciones!$T$19=$O9,Transacciones!$F$19>$H9),SUMIFS(Transacciones!$N$5:$N$20,Transacciones!$T$5:$T$20,$O9,Transacciones!$F$5:$F$20,"<="&Transacciones!$F$19)+$P9,"")) | AI9: =IF($C9<>"transaccion","",IF(AND(Transacciones!$T$20=$O9,Transacciones!$F$20>$H9),SUMIFS(Transacciones!$N$5:$N$20,Transacciones!$T$5:$T$20,$O9,Transacciones!$F$5:$F$20,"<="&Transacciones!$F$20)+$P9,"")) | AJ9: =IF($C9="transaccion",MIN(S9,T9:AI9),"") -> 10 | AK9: =IF($C9<>"transaccion","",IF(S9<0,H9,IF(AJ9<0,_xlfn.MINIFS($T$3:$AI$3,T9:AI9,"<0"),""))) | AL9: =IF($C9="periodo",IF(M9<L9,"criterio 3 de RF-09: fecha final anterior a la inicial",IF(OR(L9-1<Entradas!$B$6,M9>Entradas!$B$7),"criterio 3 de RF-09: fechas fuera de las semillas","")),IF(Q9,"RD-07 y criterio 3 de RF-05: fecha fuera del intervalo de las semillas",IF(R9,"criterio 2 de RF-26a: fecha igual o posterior al vencimiento de la emision",IF(AJ9<0,"RF-28: deja negativo el saldo del instrumento con el intermediario dentro del portafolio","")))) -> RD-07 y criterio 3 de RF-05: fecha fuera del intervalo de las semillas | AM9: =IF(AL9="","aceptar","rechazar") -> rechazar | AN9: =IF(LEFT(AL9,5)="RF-28",AK9,"") | AO9: =IF(LEFT(AL9,5)="RF-28",SUMIFS(Transacciones!$N$5:$N$20,Transacciones!$T$5:$T$20,O9,Transacciones!$F$5:$F$20,"<="&AK9)+P9,"")
A10: N6 | B10: RF-05 crit. 3 (opcional) | C10: transaccion | D10: Principal | E10: Casa A | F10: DEMOACC | G10: compra | H10: 46310 | I10: 10 | J10: 111 | K10: 3.22 | N10: Compra fechada el 15/10, despues del intervalo de las semillas | O10: =IF($C10="transaccion",D10&"|"&F10&"|"&E10,"") -> Principal|DEMOACC|Casa A | P10: =IF($C10="transaccion",IF(G10="compra",1,-1)*I10,"") -> 10 | Q10: =IF($C10="transaccion",OR(H10<Entradas!$B$6,H10>Entradas!$B$7),"") -> TRUE | R10: =IF($C10="transaccion",AND(INDEX(Entradas!$C$40:$C$46,MATCH(F10,Entradas!$A$40:$A$46,0))="cetes",H10>=INDEX(Entradas!$F$40:$F$46,MATCH(F10,Entradas!$A$40:$A$46,0))),"") -> FALSE | S10: =IF($C10="transaccion",SUMIFS(Transacciones!$N$5:$N$20,Transacciones!$T$5:$T$20,O10,Transacciones!$F$5:$F$20,"<="&H10)+P10,"") -> 130 | T10: =IF($C10<>"transaccion","",IF(AND(Transacciones!$T$5=$O10,Transacciones!$F$5>$H10),SUMIFS(Transacciones!$N$5:$N$20,Transacciones!$T$5:$T$20,$O10,Transacciones!$F$5:$F$20,"<="&Transacciones!$F$5)+$P10,"")) | U10: =IF($C10<>"transaccion","",IF(AND(Transacciones!$T$6=$O10,Transacciones!$F$6>$H10),SUMIFS(Transacciones!$N$5:$N$20,Transacciones!$T$5:$T$20,$O10,Transacciones!$F$5:$F$20,"<="&Transacciones!$F$6)+$P10,"")) | V10: =IF($C10<>"transaccion","",IF(AND(Transacciones!$T$7=$O10,Transacciones!$F$7>$H10),SUMIFS(Transacciones!$N$5:$N$20,Transacciones!$T$5:$T$20,$O10,Transacciones!$F$5:$F$20,"<="&Transacciones!$F$7)+$P10,"")) | W10: =IF($C10<>"transaccion","",IF(AND(Transacciones!$T$8=$O10,Transacciones!$F$8>$H10),SUMIFS(Transacciones!$N$5:$N$20,Transacciones!$T$5:$T$20,$O10,Transacciones!$F$5:$F$20,"<="&Transacciones!$F$8)+$P10,"")) | X10: =IF($C10<>"transaccion","",IF(AND(Transacciones!$T$9=$O10,Transacciones!$F$9>$H10),SUMIFS(Transacciones!$N$5:$N$20,Transacciones!$T$5:$T$20,$O10,Transacciones!$F$5:$F$20,"<="&Transacciones!$F$9)+$P10,"")) | Y10: =IF($C10<>"transaccion","",IF(AND(Transacciones!$T$10=$O10,Transacciones!$F$10>$H10),SUMIFS(Transacciones!$N$5:$N$20,Transacciones!$T$5:$T$20,$O10,Transacciones!$F$5:$F$20,"<="&Transacciones!$F$10)+$P10,"")) | Z10: =IF($C10<>"transaccion","",IF(AND(Transacciones!$T$11=$O10,Transacciones!$F$11>$H10),SUMIFS(Transacciones!$N$5:$N$20,Transacciones!$T$5:$T$20,$O10,Transacciones!$F$5:$F$20,"<="&Transacciones!$F$11)+$P10,"")) | AA10: =IF($C10<>"transaccion","",IF(AND(Transacciones!$T$12=$O10,Transacciones!$F$12>$H10),SUMIFS(Transacciones!$N$5:$N$20,Transacciones!$T$5:$T$20,$O10,Transacciones!$F$5:$F$20,"<="&Transacciones!$F$12)+$P10,"")) | AB10: =IF($C10<>"transaccion","",IF(AND(Transacciones!$T$13=$O10,Transacciones!$F$13>$H10),SUMIFS(Transacciones!$N$5:$N$20,Transacciones!$T$5:$T$20,$O10,Transacciones!$F$5:$F$20,"<="&Transacciones!$F$13)+$P10,"")) | AC10: =IF($C10<>"transaccion","",IF(AND(Transacciones!$T$14=$O10,Transacciones!$F$14>$H10),SUMIFS(Transacciones!$N$5:$N$20,Transacciones!$T$5:$T$20,$O10,Transacciones!$F$5:$F$20,"<="&Transacciones!$F$14)+$P10,"")) | AD10: =IF($C10<>"transaccion","",IF(AND(Transacciones!$T$15=$O10,Transacciones!$F$15>$H10),SUMIFS(Transacciones!$N$5:$N$20,Transacciones!$T$5:$T$20,$O10,Transacciones!$F$5:$F$20,"<="&Transacciones!$F$15)+$P10,"")) | AE10: =IF($C10<>"transaccion","",IF(AND(Transacciones!$T$16=$O10,Transacciones!$F$16>$H10),SUMIFS(Transacciones!$N$5:$N$20,Transacciones!$T$5:$T$20,$O10,Transacciones!$F$5:$F$20,"<="&Transacciones!$F$16)+$P10,"")) | AF10: =IF($C10<>"transaccion","",IF(AND(Transacciones!$T$17=$O10,Transacciones!$F$17>$H10),SUMIFS(Transacciones!$N$5:$N$20,Transacciones!$T$5:$T$20,$O10,Transacciones!$F$5:$F$20,"<="&Transacciones!$F$17)+$P10,"")) | AG10: =IF($C10<>"transaccion","",IF(AND(Transacciones!$T$18=$O10,Transacciones!$F$18>$H10),SUMIFS(Transacciones!$N$5:$N$20,Transacciones!$T$5:$T$20,$O10,Transacciones!$F$5:$F$20,"<="&Transacciones!$F$18)+$P10,"")) | AH10: =IF($C10<>"transaccion","",IF(AND(Transacciones!$T$19=$O10,Transacciones!$F$19>$H10),SUMIFS(Transacciones!$N$5:$N$20,Transacciones!$T$5:$T$20,$O10,Transacciones!$F$5:$F$20,"<="&Transacciones!$F$19)+$P10,"")) | AI10: =IF($C10<>"transaccion","",IF(AND(Transacciones!$T$20=$O10,Transacciones!$F$20>$H10),SUMIFS(Transacciones!$N$5:$N$20,Transacciones!$T$5:$T$20,$O10,Transacciones!$F$5:$F$20,"<="&Transacciones!$F$20)+$P10,"")) | AJ10: =IF($C10="transaccion",MIN(S10,T10:AI10),"") -> 130 | AK10: =IF($C10<>"transaccion","",IF(S10<0,H10,IF(AJ10<0,_xlfn.MINIFS($T$3:$AI$3,T10:AI10,"<0"),""))) | AL10: =IF($C10="periodo",IF(M10<L10,"criterio 3 de RF-09: fecha final anterior a la inicial",IF(OR(L10-1<Entradas!$B$6,M10>Entradas!$B$7),"criterio 3 de RF-09: fechas fuera de las semillas","")),IF(Q10,"RD-07 y criterio 3 de RF-05: fecha fuera del intervalo de las semillas",IF(R10,"criterio 2 de RF-26a: fecha igual o posterior al vencimiento de la emision",IF(AJ10<0,"RF-28: deja negativo el saldo del instrumento con el intermediario dentro del portafolio","")))) -> RD-07 y criterio 3 de RF-05: fecha fuera del intervalo de las semillas | AM10: =IF(AL10="","aceptar","rechazar") -> rechazar | AN10: =IF(LEFT(AL10,5)="RF-28",AK10,"") | AO10: =IF(LEFT(AL10,5)="RF-28",SUMIFS(Transacciones!$N$5:$N$20,Transacciones!$T$5:$T$20,O10,Transacciones!$F$5:$F$20,"<="&AK10)+P10,"")
